Workbook
Name Slicer_Return: #N/A
Name Slicer_Sector: #N/A
Name Slicer_Sector1: #N/A
Name Slicer_Stock_Name: #N/A

Sheet Home
G1: 📈 STOCK MARKET PORTFOLIO TRACKER & RETURN ANALYZER

Sheet Dashboard
G2: 📈 STOCK MARKET PORTFOLIO TRACKER & RETURN ANALYZER
G8: Total Market Value | O8: Total Investment | W8: ="Total " & IF($W$11>=0, "Profit", "Loss") -> Total Profit | AE8: Return On Investment
G11: ='My Holdings'!O32 -> 6272596.7 | O11: ='My Holdings'!M32 -> 3533128.6 | W11: ='My Holdings'!P32 -> 2739468.1 | AE11: ='My Holdings'!Q32 -> 0.77536609
G19: Sector Wise Allocation | S19: Investment vs Profit / Loss | AE19: Quantity in Hold
G45: Sector Vs Month
G60: Total Investment Vs Total Market Value Vs Profit/Loss

Sheet Raw Data
F1: 📈 STOCK MARKET PORTFOLIO TRACKER & RETURN ANALYZER
F6: Raw Data
F9: Order_ID | G9: Date | H9: Sector | I9: Stock_Name | J9: Buy_Price | K9: Sell_Price | L9: Quantity | M9: Order_Type | O9: Cleaned_Order_Type | P9: Curr_Hold | Q9: Date_format | R9: Reason_1 | S9: Reason_2 | T9: Reason_3 | U9: Reason_4 | V9: Decision
F10: ORD1076 | G10: 2025-04-09 | H10: Paints | I10: ASIANPAINT | J10: NULL | K10: 2464.09 | L10: 10 | M10: B | O10: =IF(LEFT(UPPER(M10),1)="S","SELL",IF(LEFT(UPPER(M10),1)="B","BUY","INVALID")) -> BUY | P10: =IF(L10 = "NULL", 0, IF(AND(I10=I11, H10=H11), P11 + IF(O10="BUY", L10, -L10), IF(O10="BUY", L10, -L10))) -> 25 | Q10: =DATEVALUE(Table1[[#This Row],[Date]]) -> 45756 | R10: =IF(F10="NULL", "INVALID", "VALID") -> VALID | S10: =IF(R10="VALID", IF(AND(J10="NULL",K10="NULL"), "INVALID", "VALID"), "INVALID") -> VALID | T10: =IF(S10="VALID", IF(P10<0, "INVALID", "VALID"), "INVALID") -> VALID | U10: =IF(T10="VALID", IF(Table1[[#This Row],[Quantity]]="NULL", "INVALID", "VALID"), "INVALID") -> VALID | V10: =IF(U10="VALID", "KEEP","DELETE") -> KEEP
F11: ORD1073 | G11: 2025-03-31 | H11: Paints | I11: ASIANPAINT | J11: 3284.04 | L11: 25 | M11: Buy | O11: =IF(LEFT(UPPER(M11),1)="S","SELL",IF(LEFT(UPPER(M11),1)="B","BUY","INVALID")) -> BUY | P11: =IF(L11 = "NULL", 0, IF(AND(I11=I12, H11=H12), P12 + IF(O11="BUY", L11, -L11), IF(O11="BUY", L11, -L11))) -> 15 | Q11: =DATEVALUE(Table1[[#This Row],[Date]]) -> 45747 | R11: =IF(F11="NULL", "INVALID", "VALID") -> VALID | S11: =IF(R11="VALID", IF(AND(J11="NULL",K11="NULL"), "INVALID", "VALID"), "INVALID") -> VALID | T11: =IF(S11="VALID", IF(P11<0, "INVALID", "VALID"), "INVALID") -> VALID | U11: =IF(T11="VALID", IF(Table1[[#This Row],[Quantity]]="NULL", "INVALID", "VALID"), "INVALID") -> VALID | V11: =IF(U11="VALID", "KEEP","DELETE") -> KEEP
F12: ORD1079 | G12: 2025-03-18 | H12: Paints | I12: ASIANPAINT | J12: NULL | K12: 2494.34 | L12: 10 | M12: SELLA | O12: =IF(LEFT(UPPER(M12),1)="S","SELL",IF(LEFT(UPPER(M12),1)="B","BUY","INVALID")) -> SELL | P12: =IF(L12 = "NULL", 0, IF(AND(I12=I13, H12=H13), P13 + IF(O12="BUY", L12, -L12), IF(O12="BUY", L12, -L12))) -> -10 | Q12: =DATEVALUE(Table1[[#This Row],[Date]]) -> 45734 | R12: =IF(F12="NULL", "INVALID", "VALID") -> VALID | S12: =IF(R12="VALID", IF(AND(J12="NULL",K12="NULL"), "INVALID", "VALID"), "INVALID") -> VALID | T12: =IF(S12="VALID", IF(P12<0, "INVALID", "VALID"), "INVALID") -> INVALID | U12: =IF(T12="VALID", IF(Table1[[#This Row],[Quantity]]="NULL", "INVALID", "VALID"), "INVALID") -> INVALID | V12: =IF(U12="VALID", "KEEP","DELETE") -> DELETE
F13: ORD1166 | G13: 2025-02-18 | H13: Paints | I13: ASIANPAINT | J13: 1920.27 | L13: 50 | M13: BUY | O13: =IF(LEFT(UPPER(M13),1)="S","SELL",IF(LEFT(UPPER(M13),1)="B","BUY","INVALID")) -> BUY | P13: =IF(L13 = "NULL", 0, IF(AND(I13=I14, H13=H14), P14 + IF(O13="BUY", L13, -L13), IF(O13="BUY", L13, -L13))) -> 0 | Q13: =DATEVALUE(Table1[[#This Row],[Date]]) -> 45706 | R13: =IF(F13="NULL", "INVALID", "VALID") -> VALID | S13: =IF(R13="VALID", IF(AND(J13="NULL",K13="NULL"), "INVALID", "VALID"), "INVALID") -> VALID | T13: =IF(S13="VALID", IF(P13<0, "INVALID", "VALID"), "INVALID") -> VALID | U13: =IF(T13="VALID", IF(Table1[[#This Row],[Quantity]]="NULL", "INVALID", "VALID"), "INVALID") -> VALID | V13: =IF(U13="VALID", "KEEP","DELETE") -> KEEP
F14: ORD1005 | G14: 2025-01-27 | H14: Paints | I14: ASIANPAINT | J14: NULL | K14: 649.76 | L14: 50 | M14: SELL | O14: =IF(LEFT(UPPER(M14),1)="S","SELL",IF(LEFT(UPPER(M14),1)="B","BUY","INVALID")) -> SELL | P14: =IF(L14 = "NULL", 0, IF(AND(I14=I15, H14=H15), P15 + IF(O14="BUY", L14, -L14), IF(O14="BUY", L14, -L14))) -> -50 | Q14: =DATEVALUE(Table1[[#This Row],[Date]]) -> 45684 | R14: =IF(F14="NULL", "INVALID", "VALID") -> VALID | S14: =IF(R14="VALID", IF(AND(J14="NULL",K14="NULL"), "INVALID", "VALID"), "INVALID") -> VALID | T14: =IF(S14="VALID", IF(P14<0, "INVALID", "VALID"), "INVALID") -> INVALID | U14: =IF(T14="VALID", IF(Table1[[#This Row],[Quantity]]="NULL", "INVALID", "VALID"), "INVALID") -> INVALID | V14: =IF(U14="VALID", "KEEP","DELETE") -> DELETE
F15: ORD1186 | G15: 2025-06-23 | H15: Banking | I15: AXISBANK | J15: 2282.67 | K15: NULL | L15: 25 | M15: BUY | O15: =IF(LEFT(UPPER(M15),1)="S","SELL",IF(LEFT(UPPER(M15),1)="B","BUY","INVALID")) -> BUY | P15: =IF(L15 = "NULL", 0, IF(AND(I15=I16, H15=H16), P16 + IF(O15="BUY", L15, -L15), IF(O15="BUY", L15, -L15))) -> 50 | Q15: =DATEVALUE(Table1[[#This Row],[Date]]) -> 45831 | R15: =IF(F15="NULL", "INVALID", "VALID") -> VALID | S15: =IF(R15="VALID", IF(AND(J15="NULL",K15="NULL"), "INVALID", "VALID"), "INVALID") -> VALID | T15: =IF(S15="VALID", IF(P15<0, "INVALID", "VALID"), "INVALID") -> VALID | U15: =IF(T15="VALID", IF(Table1[[#This Row],[Quantity]]="NULL", "INVALID", "VALID"), "INVALID") -> VALID | V15: =IF(U15="VALID", "KEEP","DELETE") -> KEEP
F16: ORD1011 | G16: 2025-06-21 | H16: Banking | I16: AXISBANK | J16: 1390.11 | K16: NULL | L16: 20 | M16: BUYY | O16: =IF(LEFT(UPPER(M16),1)="S","SELL",IF(LEFT(UPPER(M16),1)="B","BUY","INVALID")) -> BUY | P16: =IF(L16 = "NULL", 0, IF(AND(I16=I17, H16=H17), P17 + IF(O16="BUY", L16, -L16), IF(O16="BUY", L16, -L16))) -> 25 | Q16: =DATEVALUE(Table1[[#This Row],[Date]]) -> 45829 | R16: =IF(F16="NULL", "INVALID", "VALID") -> VALID | S16: =IF(R16="VALID", IF(AND(J16="NULL",K16="NULL"), "INVALID", "VALID"), "INVALID") -> VALID | T16: =IF(S16="VALID", IF(P16<0, "INVALID", "VALID"), "INVALID") -> VALID | U16: =IF(T16="VALID", IF(Table1[[#This Row],[Quantity]]="NULL", "INVALID", "VALID"), "INVALID") -> VALID | V16: =IF(U16="VALID", "KEEP","DELETE") -> KEEP
F17: ORD1122 | G17: 2025-05-23 | H17: Banking | I17: AXISBANK | J17: NULL | K17: 1228.25 | L17: 25 | M17: SELL | O17: =IF(LEFT(UPPER(M17),1)="S","SELL",IF(LEFT(UPPER(M17),1)="B","BUY","INVALID")) -> SELL | P17: =IF(L17 = "NULL", 0, IF(AND(I17=I18, H17=H18), P18 + IF(O17="BUY", L17, -L17), IF(O17="BUY", L17, -L17))) -> 5 | Q17: =DATEVALUE(Table1[[#This Row],[Date]]) -> 45800 | R17: =IF(F17="NULL", "INVALID", "VALID") -> VALID | S17: =IF(R17="VALID", IF(AND(J17="NULL",K17="NULL"), "INVALID", "VALID"), "INVALID") -> VALID | T17: =IF(S17="VALID", IF(P17<0, "INVALID", "VALID"), "INVALID") -> VALID | U17: =IF(T17="VALID", IF(Table1[[#This Row],[Quantity]]="NULL", "INVALID", "VALID"), "INVALID") -> VALID | V17: =IF(U17="VALID", "KEEP","DELETE") -> KEEP
F18: ORD1177 | G18: 2025-05-16 | H18: Banking | I18: AXISBANK | J18: NULL | K18: 1644.42 | L18: 20 | M18: SELL | O18: =IF(LEFT(UPPER(M18),1)="S","SELL",IF(LEFT(UPPER(M18),1)="B","BUY","INVALID")) -> SELL | P18: =IF(L18 = "NULL", 0, IF(AND(I18=I19, H18=H19), P19 + IF(O18="BUY", L18, -L18), IF(O18="BUY", L18, -L18))) -> 30 | Q18: =DATEVALUE(Table1[[#This Row],[Date]]) -> 45793 | R18: =IF(F18="NULL", "INVALID", "VALID") -> VALID | S18: =IF(R18="VALID", IF(AND(J18="NULL",K18="NULL"), "INVALID", "VALID"), "INVALID") -> VALID | T18: =IF(S18="VALID", IF(P18<0, "INVALID", "VALID"), "INVALID") -> VALID | U18: =IF(T18="VALID", IF(Table1[[#This Row],[Quantity]]="NULL", "INVALID", "VALID"), "INVALID") -> VALID | V18: =IF(U18="VALID", "KEEP","DELETE") -> KEEP
F19: ORD1127 | G19: 2025-04-01 | H19: Banking | I19: AXISBANK | J19: NULL | K19: 3804.69 | L19: 50 | M19: SELL | O19: =IF(LEFT(UPPER(M19),1)="S","SELL",IF(LEFT(UPPER(M19),1)="B","BUY","INVALID")) -> SELL | P19: =IF(L19 = "NULL", 0, IF(AND(I19=I20, H19=H20), P20 + IF(O19="BUY", L19, -L19), IF(O19="BUY", L19, -L19))) -> 50 | Q19: =DATEVALUE(Table1[[#This Row],[Date]]) -> 45748 | R19: =IF(F19="NULL", "INVALID", "VALID") -> VALID | S19: =IF(R19="VALID", IF(AND(J19="NULL",K19="NULL"), "INVALID", "VALID"), "INVALID") -> VALID | T19: =IF(S19="VALID", IF(P19<0, "INVALID", "VALID"), "INVALID") -> VALID | U19: =IF(T19="VALID", IF(Table1[[#This Row],[Quantity]]="NULL", "INVALID", "VALID"), "INVALID") -> VALID | V19: =IF(U19="VALID", "KEEP","DELETE") -> KEEP
F20: ORD1195 | G20: 2025-01-07 | H20: Banking | I20: AXISBANK | J20: 2410.7 | K20: NULL | L20: 100 | M20: BUY | O20: =IF(LEFT(UPPER(M20),1)="S","SELL",IF(LEFT(UPPER(M20),1)="B","BUY","INVALID")) -> BUY | P20: =IF(L20 = "NULL", 0, IF(AND(I20=I21, H20=H21), P21 + IF(O20="BUY", L20, -L20), IF(O20="BUY", L20, -L20))) -> 100 | Q20: =DATEVALUE(Table1[[#This Row],[Date]]) -> 45664 | R20: =IF(F20="NULL", "INVALID", "VALID") -> VALID | S20: =IF(R20="VALID", IF(AND(J20="NULL",K20="NULL"), "INVALID", "VALID"), "INVALID") -> VALID | T20: =IF(S20="VALID", IF(P20<0, "INVALID", "VALID"), "INVALID") -> VALID | U20: =IF(T20="VALID", IF(Table1[[#This Row],[Quantity]]="NULL", "INVALID", "VALID"), "INVALID") -> VALID | V20: =IF(U20="VALID", "KEEP","DELETE") -> KEEP
F21: ORD1022 | G21: 2025-06-24 | H21: Finance | I21: BAJFINANCE | J21: 2428.95 | K21: NULL | L21: 10 | M21: BUY | O21: =IF(LEFT(UPPER(M21),1)="S","SELL",IF(LEFT(UPPER(M21),1)="B","BUY","INVALID")) -> BUY | P21: =IF(L21 = "NULL", 0, IF(AND(I21=I22, H21=H22), P22 + IF(O21="BUY", L21, -L21), IF(O21="BUY", L21, -L21))) -> 280 | Q21: =DATEVALUE(Table1[[#This Row],[Date]]) -> 45832 | R21: =IF(F21="NULL", "INVALID", "VALID") -> VALID | S21: =IF(R21="VALID", IF(AND(J21="NULL",K21="NULL"), "INVALID", "VALID"), "INVALID") -> VALID | T21: =IF(S21="VALID", IF(P21<0, "INVALID", "VALID"), "INVALID") -> VALID | U21: =IF(T21="VALID", IF(Table1[[#This Row],[Quantity]]="NULL", "INVALID", "VALID"), "INVALID") -> VALID | V21: =IF(U21="VALID", "KEEP","DELETE") -> KEEP
F22: ORD1199 | G22: 2025-06-21 | H22: Finance | I22: BAJFINANCE | J22: 1451.96 | K22: NULL | L22: 50 | M22: BUY | O22: =IF(LEFT(UPPER(M22),1)="S","SELL",IF(LEFT(UPPER(M22),1)="B","BUY","INVALID")) -> BUY | P22: =IF(L22 = "NULL", 0, IF(AND(I22=I23, H22=H23), P23 + IF(O22="BUY", L22, -L22), IF(O22="BUY", L22, -L22))) -> 270 | Q22: =DATEVALUE(Table1[[#This Row],[Date]]) -> 45829 | R22: =IF(F22="NULL", "INVALID", "VALID") -> VALID | S22: =IF(R22="VALID", IF(AND(J22="NULL",K22="NULL"), "INVALID", "VALID"), "INVALID") -> VALID | T22: =IF(S22="VALID", IF(P22<0, "INVALID", "VALID"), "INVALID") -> VALID | U22: =IF(T22="VALID", IF(Table1[[#This Row],[Quantity]]="NULL", "INVALID", "VALID"), "INVALID") -> VALID | V22: =IF(U22="VALID", "KEEP","DELETE") -> KEEP
F23: ORD1057 | G23: 2025-06-20 | H23: Finance | I23: BAJFINANCE | J23: NULL | K23: 2448.55 | L23: 5 | M23: SEL | O23: =IF(LEFT(UPPER(M23),1)="S","SELL",IF(LEFT(UPPER(M23),1)="B","BUY","INVALID")) -> SELL | P23: =IF(L23 = "NULL", 0, IF(AND(I23=I24, H23=H24), P24 + IF(O23="BUY", L23, -L23), IF(O23="BUY", L23, -L23))) -> 220 | Q23: =DATEVALUE(Table1[[#This Row],[Date]]) -> 45828 | R23: =IF(F23="NULL", "INVALID", "VALID") -> VALID | S23: =IF(R23="VALID", IF(AND(J23="NULL",K23="NULL"), "INVALID", "VALID"), "INVALID") -> VALID | T23: =IF(S23="VALID", IF(P23<0, "INVALID", "VALID"), "INVALID") -> VALID | U23: =IF(T23="VALID", IF(Table1[[#This Row],[Quantity]]="NULL", "INVALID", "VALID"), "INVALID") -> VALID | V23: =IF(U23="VALID", "KEEP","DELETE") -> KEEP
F24: ORD1078 | G24: 2025-06-20 | H24: Finance | I24: BAJFINANCE | J24: 1370.14 | K24: NULL | L24: 10 | M24: BUY | O24: =IF(LEFT(UPPER(M24),1)="S","SELL",IF(LEFT(UPPER(M24),1)="B","BUY","INVALID")) -> BUY | P24: =IF(L24 = "NULL", 0, IF(AND(I24=I25, H24=H25), P25 + IF(O24="BUY", L24, -L24), IF(O24="BUY", L24, -L24))) -> 225 | Q24: =DATEVALUE(Table1[[#This Row],[Date]]) -> 45828 | R24: =IF(F24="NULL", "INVALID", "VALID") -> VALID | S24: =IF(R24="VALID", IF(AND(J24="NULL",K24="NULL"), "INVALID", "VALID"), "INVALID") -> VALID | T24: =IF(S24="VALID", IF(P24<0, "INVALID", "VALID"), "INVALID") -> VALID | U24: =IF(T24="VALID", IF(Table1[[#This Row],[Quantity]]="NULL", "INVALID", "VALID"), "INVALID") -> VALID | V24: =IF(U24="VALID", "KEEP","DELETE") -> KEEP
F25: ORD1091 | G25: 2025-06-06 | H25: Finance | I25: BAJFINANCE | J25: NULL | K25: 3709.22 | L25: 100 | M25: SELL | O25: =IF(LEFT(UPPER(M25),1)="S","SELL",IF(LEFT(UPPER(M25),1)="B","BUY","INVALID")) -> SELL | P25: =IF(L25 = "NULL", 0, IF(AND(I25=I26, H25=H26), P26 + IF(O25="BUY", L25, -L25), IF(O25="BUY", L25, -L25))) -> 215 | Q25: =DATEVALUE(Table1[[#This Row],[Date]]) -> 45814 | R25: =IF(F25="NULL", "INVALID", "VALID") -> VALID | S25: =IF(R25="VALID", IF(AND(J25="NULL",K25="NULL"), "INVALID", "VALID"), "INVALID") -> VALID | T25: =IF(S25="VALID", IF(P25<0, "INVALID", "VALID"), "INVALID") -> VALID | U25: =IF(T25="VALID", IF(Table1[[#This Row],[Quantity]]="NULL", "INVALID", "VALID"), "INVALID") -> VALID | V25: =IF(U25="VALID", "KEEP","DELETE") -> KEEP
F26: ORD1181 | G26: 2025-05-31 | H26: Finance | I26: BAJFINANCE | J26: 397.44 | K26: NULL | L26: 50 | M26: BUY | O26: =IF(LEFT(UPPER(M26),1)="S","SELL",IF(LEFT(UPPER(M26),1)="B","BUY","INVALID")) -> BUY | P26: =IF(L26 = "NULL", 0, IF(AND(I26=I27, H26=H27), P27 + IF(O26="BUY", L26, -L26), IF(O26="BUY", L26, -L26))) -> 315 | Q26: =DATEVALUE(Table1[[#This Row],[Date]]) -> 45808 | R26: =IF(F26="NULL", "INVALID", "VALID") -> VALID | S26: =IF(R26="VALID", IF(AND(J26="NULL",K26="NULL"), "INVALID", "VALID"), "INVALID") -> VALID | T26: =IF(S26="VALID", IF(P26<0, "INVALID", "VALID"), "INVALID") -> VALID | U26: =IF(T26="VALID", IF(Table1[[#This Row],[Quantity]]="NULL", "INVALID", "VALID"), "INVALID") -> VALID | V26: =IF(U26="VALID", "KEEP","DELETE") -> KEEP
F27: ORD1018 | G27: 2025-05-30 | H27: Finance | I27: BAJFINANCE | J27: NULL | K27: 2731.75 | L27: 75 | M27: SELL | O27: =IF(LEFT(UPPER(M27),1)="S","SELL",IF(LEFT(UPPER(M27),1)="B","BUY","INVALID")) -> SELL | P27: =IF(L27 = "NULL", 0, IF(AND(I27=I28, H27=H28), P28 + IF(O27="BUY", L27, -L27), IF(O27="BUY", L27, -L27))) -> 265 | Q27: =DATEVALUE(Table1[[#This Row],[Date]]) -> 45807 | R27: =IF(F27="NULL", "INVALID", "VALID") -> VALID | S27: =IF(R27="VALID", IF(AND(J27="NULL",K27="NULL"), "INVALID", "VALID"), "INVALID") -> VALID | T27: =IF(S27="VALID", IF(P27<0, "INVALID", "VALID"), "INVALID") -> VALID | U27: =IF(T27="VALID", IF(Table1[[#This Row],[Quantity]]="NULL", "INVALID", "VALID"), "INVALID") -> VALID | V27: =IF(U27="VALID", "KEEP","DELETE") -> KEEP
F28: ORD1008 | G28: 2025-05-28 | H28: Finance | I28: BAJFINANCE | J28: NULL | K28: 2894.7 | L28: 50 | M28: SELL | O28: =IF(LEFT(UPPER(M28),1)="S","SELL",IF(LEFT(UPPER(M28),1)="B","BUY","INVALID")) -> SELL | P28: =IF(L28 = "NULL", 0, IF(AND(I28=I29, H28=H29), P29 + IF(O28="BUY", L28, -L28), IF(O28="BUY", L28, -L28))) -> 340 | Q28: =DATEVALUE(Table1[[#This Row],[Date]]) -> 45805 | R28: =IF(F28="NULL", "INVALID", "VALID") -> VALID | S28: =IF(R28="VALID", IF(AND(J28="NULL",K28="NULL"), "INVALID", "VALID"), "INVALID") -> VALID | T28: =IF(S28="VALID", IF(P28<0, "INVALID", "VALID"), "INVALID") -> VALID | U28: =IF(T28="VALID", IF(Table1[[#This Row],[Quantity]]="NULL", "INVALID", "VALID"), "INVALID") -> VALID | V28: =IF(U28="VALID", "KEEP","DELETE") -> KEEP
F29: ORD1030 | G29: 2025-05-21 | H29: Finance | I29: BAJFINANCE | J29: 580.11 | K29: NULL | L29: 100 | M29: BUY | O29: =IF(LEFT(UPPER(M29),1)="S","SELL",IF(LEFT(UPPER(M29),1)="B","BUY","INVALID")) -> BUY | P29: =IF(L29 = "NULL", 0, IF(AND(I29=I30, H29=H30), P30 + IF(O29="BUY", L29, -L29), IF(O29="BUY", L29, -L29))) -> 390 | Q29: =DATEVALUE(Table1[[#This Row],[Date]]) -> 45798 | R29: =IF(F29="NULL", "INVALID", "VALID") -> VALID | S29: =IF(R29="VALID", IF(AND(J29="NULL",K29="NULL"), "INVALID", "VALID"), "INVALID") -> VALID | T29: =IF(S29="VALID", IF(P29<0, "INVALID", "VALID"), "INVALID") -> VALID | U29: =IF(T29="VALID", IF(Table1[[#This Row],[Quantity]]="NULL", "INVALID", "VALID"), "INVALID") -> VALID | V29: =IF(U29="VALID", "KEEP","DELETE") -> KEEP
F30: ORD1116 | G30: 2025-05-10 | H30: Finance | I30: BAJFINANCE | J30: NULL | K30: 2554.22 | L30: 10 | M30: SELL | O30: =IF(LEFT(UPPER(M30),1)="S","SELL",IF(LEFT(UPPER(M30),1)="B","BUY","INVALID")) -> SELL | P30: =IF(L30 = "NULL", 0, IF(AND(I30=I31, H30=H31), P31 + IF(O30="BUY", L30, -L30), IF(O30="BUY", L30, -L30))) -> 290 | Q30: =DATEVALUE(Table1[[#This Row],[Date]]) -> 45787 | R30: =IF(F30="NULL", "INVALID", "VALID") -> VALID | S30: =IF(R30="VALID", IF(AND(J30="NULL",K30="NULL"), "INVALID", "VALID"), "INVALID") -> VALID | T30: =IF(S30="VALID", IF(P30<0, "INVALID", "VALID"), "INVALID") -> VALID | U30: =IF(T30="VALID", IF(Table1[[#This Row],[Quantity]]="NULL", "INVALID", "VALID"), "INVALID") -> VALID | V30: =IF(U30="VALID", "KEEP","DELETE") -> KEEP
F31: ORD1124 | G31: 2025-04-25 | H31: Finance | I31: BAJFINANCE | J31: 2463.54 | K31: NULL | L31: 100 | M31: buy | O31: =IF(LEFT(UPPER(M31),1)="S","SELL",IF(LEFT(UPPER(M31),1)="B","BUY","INVALID")) -> BUY | P31: =IF(L31 = "NULL", 0, IF(AND(I31=I32, H31=H32), P32 + IF(O31="BUY", L31, -L31), IF(O31="BUY", L31, -L31))) -> 300 | Q31: =DATEVALUE(Table1[[#This Row],[Date]]) -> 45772 | R31: =IF(F31="NULL", "INVALID", "VALID") -> VALID | S31: =IF(R31="VALID", IF(AND(J31="NULL",K31="NULL"), "INVALID", "VALID"), "INVALID") -> VALID | T31: =IF(S31="VALID", IF(P31<0, "INVALID", "VALID"), "INVALID") -> VALID | U31: =IF(T31="VALID", IF(Table1[[#This Row],[Quantity]]="NULL", "INVALID", "VALID"), "INVALID") -> VALID | V31: =IF(U31="VALID", "KEEP","DELETE") -> KEEP
F32: ORD1101 | G32: 2025-04-22 | H32: Finance | I32: BAJFINANCE | J32: 1785.57 | K32: NULL | L32: 25 | M32: BUY | O32: =IF(LEFT(UPPER(M32),1)="S","SELL",IF(LEFT(UPPER(M32),1)="B","BUY","INVALID")) -> BUY | P32: =IF(L32 = "NULL", 0, IF(AND(I32=I33, H32=H33), P33 + IF(O32="BUY", L32, -L32), IF(O32="BUY", L32, -L32))) -> 200 | Q32: =DATEVALUE(Table1[[#This Row],[Date]]) -> 45769 | R32: =IF(F32="NULL", "INVALID", "VALID") -> VALID | S32: =IF(R32="VALID", IF(AND(J32="NULL",K32="NULL"), "INVALID", "VALID"), "INVALID") -> VALID | T32: =IF(S32="VALID", IF(P32<0, "INVALID", "VALID"), "INVALID") -> VALID | U32: =IF(T32="VALID", IF(Table1[[#This Row],[Quantity]]="NULL", "INVALID", "VALID"), "INVALID") -> VALID | V32: =IF(U32="VALID", "KEEP","DELETE") -> KEEP
F33: ORD1098 | G33: 2025-04-18 | H33: Finance | I33: BAJFINANCE | J33: NULL | K33: 1585.88 | L33: 20 | M33: Sell | O33: =IF(LEFT(UPPER(M33),1)="S","SELL",IF(LEFT(UPPER(M33),1)="B","BUY","INVALID")) -> SELL | P33: =IF(L33 = "NULL", 0, IF(AND(I33=I34, H33=H34), P34 + IF(O33="BUY", L33, -L33), IF(O33="BUY", L33, -L33))) -> 175 | Q33: =DATEVALUE(Table1[[#This Row],[Date]]) -> 45765 | R33: =IF(F33="NULL", "INVALID", "VALID") -> VALID | S33: =IF(R33="VALID", IF(AND(J33="NULL",K33="NULL"), "INVALID", "VALID"), "INVALID") -> VALID | T33: =IF(S33="VALID", IF(P33<0, "INVALID", "VALID"), "INVALID") -> VALID | U33: =IF(T33="VALID", IF(Table1[[#This Row],[Quantity]]="NULL", "INVALID", "VALID"), "INVALID") -> VALID | V33: =IF(U33="VALID", "KEEP","DELETE") -> KEEP
F34: ORD1055 | G34: 2025-03-31 | H34: Finance | I34: BAJFINANCE | J34: 1844.71 | K34: NULL | L34: 15 | M34: BUY | O34: =IF(LEFT(UPPER(M34),1)="S","SELL",IF(LEFT(UPPER(M34),1)="B","BUY","INVALID")) -> BUY | P34: =IF(L34 = "NULL", 0, IF(AND(I34=I35, H34=H35), P35 + IF(O34="BUY", L34, -L34), IF(O34="BUY", L34, -L34))) -> 195 | Q34: =DATEVALUE(Table1[[#This Row],[Date]]) -> 45747 | R34: =IF(F34="NULL", "INVALID", "VALID") -> VALID | S34: =IF(R34="VALID", IF(AND(J34="NULL",K34="NULL"), "INVALID", "VALID"), "INVALID") -> VALID | T34: =IF(S34="VALID", IF(P34<0, "INVALID", "VALID"), "INVALID") -> VALID | U34: =IF(T34="VALID", IF(Table1[[#This Row],[Quantity]]="NULL", "INVALID", "VALID"), "INVALID") -> VALID | V34: =IF(U34="VALID", "KEEP","DELETE") -> KEEP
F35: ORD1119 | G35: 2025-03-24 | H35: Finance | I35: BAJFINANCE | J35: NULL | K35: 1912.79 | L35: 25 | M35: SELL | O35: =IF(LEFT(UPPER(M35),1)="S","SELL",IF(LEFT(UPPER(M35),1)="B","BUY","INVALID")) -> SELL | P35: =IF(L35 = "NULL", 0, IF(AND(I35=I36, H35=H36), P36 + IF(O35="BUY", L35, -L35), IF(O35="BUY", L35, -L35))) -> 180 | Q35: =DATEVALUE(Table1[[#This Row],[Date]]) -> 45740 | R35: =IF(F35="NULL", "INVALID", "VALID") -> VALID | S35: =IF(R35="VALID", IF(AND(J35="NULL",K35="NULL"), "INVALID", "VALID"), "INVALID") -> VALID | T35: =IF(S35="VALID", IF(P35<0, "INVALID", "VALID"), "INVALID") -> VALID | U35: =IF(T35="VALID", IF(Table1[[#This Row],[Quantity]]="NULL", "INVALID", "VALID"), "INVALID") -> VALID | V35: =IF(U35="VALID", "KEEP","DELETE") -> KEEP
F36: ORD1129 | G36: 2025-03-12 | H36: Finance | I36: BAJFINANCE | J36: 791.66 | K36: NULL | L36: 100 | M36: BUY | O36: =IF(LEFT(UPPER(M36),1)="S","SELL",IF(LEFT(UPPER(M36),1)="B","BUY","INVALID")) -> BUY | P36: =IF(L36 = "NULL", 0, IF(AND(I36=I37, H36=H37), P37 + IF(O36="BUY", L36, -L36), IF(O36="BUY", L36, -L36))) -> 205 | Q36: =DATEVALUE(Table1[[#This Row],[Date]]) -> 45728 | R36: =IF(F36="NULL", "INVALID", "VALID") -> VALID | S36: =IF(R36="VALID", IF(AND(J36="NULL",K36="NULL"), "INVALID", "VALID"), "INVALID") -> VALID | T36: =IF(S36="VALID", IF(P36<0, "INVALID", "VALID"), "INVALID") -> VALID | U36: =IF(T36="VALID", IF(Table1[[#This Row],[Quantity]]="NULL", "INVALID", "VALID"), "INVALID") -> VALID | V36: =IF(U36="VALID", "KEEP","DELETE") -> KEEP
F37: ORD1037 | G37: 2025-03-04 | H37: Finance | I37: BAJFINANCE | J37: 2573.23 | K37: NULL | L37: 100 | M37: BUY | O37: =IF(LEFT(UPPER(M37),1)="S","SELL",IF(LEFT(UPPER(M37),1)="B","BUY","INVALID")) -> BUY | P37: =IF(L37 = "NULL", 0, IF(AND(I37=I38, H37=H38), P38 + IF(O37="BUY", L37, -L37), IF(O37="BUY", L37, -L37))) -> 105 | Q37: =DATEVALUE(Table1[[#This Row],[Date]]) -> 45720 | R37: =IF(F37="NULL", "INVALID", "VALID") -> VALID | S37: =IF(R37="VALID", IF(AND(J37="NULL",K37="NULL"), "INVALID", "VALID"), "INVALID") -> VALID | T37: =IF(S37="VALID", IF(P37<0, "INVALID", "VALID"), "INVALID") -> VALID | U37: =IF(T37="VALID", IF(Table1[[#This Row],[Quantity]]="NULL", "INVALID", "VALID"), "INVALID") -> VALID | V37: =IF(U37="VALID", "KEEP","DELETE") -> KEEP
F38: ORD1014 | G38: 2025-02-28 | H38: Finance | I38: BAJFINANCE | J38: 2443.46 | K38: NULL | L38: 5 | M38: BUY | O38: =IF(LEFT(UPPER(M38),1)="S","SELL",IF(LEFT(UPPER(M38),1)="B","BUY","INVALID")) -> BUY | P38: =IF(L38 = "NULL", 0, IF(AND(I38=I39, H38=H39), P39 + IF(O38="BUY", L38, -L38), IF(O38="BUY", L38, -L38))) -> 5 | Q38: =DATEVALUE(Table1[[#This Row],[Date]]) -> 45716 | R38: =IF(F38="NULL", "INVALID", "VALID") -> VALID | S38: =IF(R38="VALID", IF(AND(J38="NULL",K38="NULL"), "INVALID", "VALID"), "INVALID") -> VALID | T38: =IF(S38="VALID", IF(P38<0, "INVALID", "VALID"), "INVALID") -> VALID | U38: =IF(T38="VALID", IF(Table1[[#This Row],[Quantity]]="NULL", "INVALID", "VALID"), "INVALID") -> VALID | V38: =IF(U38="VALID", "KEEP","DELETE") -> KEEP
F39: ORD1190 | G39: 2025-02-12 | H39: Finance | I39: BAJFINANCE | J39: NULL | K39: 1931.04 | L39: 25 | M39: SELL | O39: =IF(LEFT(UPPER(M39),1)="S","SELL",IF(LEFT(UPPER(M39),1)="B","BUY","INVALID")) -> SELL | P39: =IF(L39 = "NULL", 0, IF(AND(I39=I40, H39=H40), P40 + IF(O39="BUY", L39, -L39), IF(O39="BUY", L39, -L39))) -> 0 | Q39: =DATEVALUE(Table1[[#This Row],[Date]]) -> 45700 | R39: =IF(F39="NULL", "INVALID", "VALID") -> VALID | S39: =IF(R39="VALID", IF(AND(J39="NULL",K39="NULL"), "INVALID", "VALID"), "INVALID") -> VALID | T39: =IF(S39="VALID", IF(P39<0, "INVALID", "VALID"), "INVALID") -> VALID | U39: =IF(T39="VALID", IF(Table1[[#This Row],[Quantity]]="NULL", "INVALID", "VALID"), "INVALID") -> VALID | V39: =IF(U39="VALID", "KEEP","DELETE") -> KEEP
F40: ORD1023 | G40: 2025-01-29 | H40: Finance | I40: BAJFINANCE | J40: NULL | K40: 2748.51 | L40: 50 | M40: SELL | O40: =IF(LEFT(UPPER(M40),1)="S","SELL",IF(LEFT(UPPER(M40),1)="B","BUY","INVALID")) -> SELL | P40: =IF(L40 = "NULL", 0, IF(AND(I40=I41, H40=H41), P41 + IF(O40="BUY", L40, -L40), IF(O40="BUY", L40, -L40))) -> 25 | Q40: =DATEVALUE(Table1[[#This Row],[Date]]) -> 45686 | R40: =IF(F40="NULL", "INVALID", "VALID") -> VALID | S40: =IF(R40="VALID", IF(AND(J40="NULL",K40="NULL"), "INVALID", "VALID"), "INVALID") -> VALID | T40: =IF(S40="VALID", IF(P40<0, "INVALID", "VALID"), "INVALID") -> VALID | U40: =IF(T40="VALID", IF(Table1[[#This Row],[Quantity]]="NULL", "INVALID", "VALID"), "INVALID") -> VALID | V40: =IF(U40="VALID", "KEEP","DELETE") -> KEEP
F41: ORD1007 | G41: 2025-01-21 | H41: Finance | I41: BAJFINANCE | J41: 3409.94 | K41: NULL | L41: 75 | M41: BUY | O41: =IF(LEFT(UPPER(M41),1)="S","SELL",IF(LEFT(UPPER(M41),1)="B","BUY","INVALID")) -> BUY | P41: =IF(L41 = "NULL", 0, IF(AND(I41=I42, H41=H42), P42 + IF(O41="BUY", L41, -L41), IF(O41="BUY", L41, -L41))) -> 75 | Q41: =DATEVALUE(Table1[[#This Row],[Date]]) -> 45678 | R41: =IF(F41="NULL", "INVALID", "VALID") -> VALID | S41: =IF(R41="VALID", IF(AND(J41="NULL",K41="NULL"), "INVALID", "VALID"), "INVALID") -> VALID | T41: =IF(S41="VALID", IF(P41<0, "INVALID", "VALID"), "INVALID") -> VALID | U41: =IF(T41="VALID", IF(Table1[[#This Row],[Quantity]]="NULL", "INVALID", "VALID"), "INVALID") -> VALID | V41: =IF(U41="VALID", "KEEP","DELETE") -> KEEP
F42: ORD1123 | G42: 2025-05-06 | H42: Telecom | I42: BHARTIARTL | J42: 958.54 | K42: NULL | L42: 75 | M42: BUY | O42: =IF(LEFT(UPPER(M42),1)="S","SELL",IF(LEFT(UPPER(M42),1)="B","BUY","INVALID")) -> BUY | P42: =IF(L42 = "NULL", 0, IF(AND(I42=I43, H42=H43), P43 + IF(O42="BUY", L42, -L42), IF(O42="BUY", L42, -L42))) -> -145 | Q42: =DATEVALUE(Table1[[#This Row],[Date]]) -> 45783 | R42: =IF(F42="NULL", "INVALID", "VALID") -> VALID | S42: =IF(R42="VALID", IF(AND(J42="NULL",K42="NULL"), "INVALID", "VALID"), "INVALID") -> VALID | T42: =IF(S42="VALID", IF(P42<0, "INVALID", "VALID"), "INVALID") -> INVALID | U42: =IF(T42="VALID", IF(Table1[[#This Row],[Quantity]]="NULL", "INVALID", "VALID"), "INVALID") -> INVALID | V42: =IF(U42="VALID", "KEEP","DELETE") -> DELETE
F43: ORD1086 | G43: 2025-05-02 | H43: Telecom | I43: BHARTIARTL | J43: 231.83 | K43: NULL | L43: 20 | M43: BUY | O43: =IF(LEFT(UPPER(M43),1)="S","SELL",IF(LEFT(UPPER(M43),1)="B","BUY","INVALID")) -> BUY | P43: =IF(L43 = "NULL", 0, IF(AND(I43=I44, H43=H44), P44 + IF(O43="BUY", L43, -L43), IF(O43="BUY", L43, -L43))) -> -220 | Q43: =DATEVALUE(Table1[[#This Row],[Date]]) -> 45779 | R43: =IF(F43="NULL", "INVALID", "VALID") -> VALID | S43: =IF(R43="VALID", IF(AND(J43="NULL",K43="NULL"), "INVALID", "VALID"), "INVALID") -> VALID | T43: =IF(S43="VALID", IF(P43<0, "INVALID", "VALID"), "INVALID") -> INVALID | U43: =IF(T43="VALID", IF(Table1[[#This Row],[Quantity]]="NULL", "INVALID", "VALID"), "INVALID") -> INVALID | V43: =IF(U43="VALID", "KEEP","DELETE") -> DELETE
F44: ORD1032 | G44: 2025-04-23 | H44: Telecom | I44: BHARTIARTL | J44: NULL | K44: 1679.77 | L44: 50 | M44: SELL | O44: =IF(LEFT(UPPER(M44),1)="S","SELL",IF(LEFT(UPPER(M44),1)="B","BUY","INVALID")) -> SELL | P44: =IF(L44 = "NULL", 0, IF(AND(I44=I45, H44=H45), P45 + IF(O44="BUY", L44, -L44), IF(O44="BUY", L44, -L44))) -> -240 | Q44: =DATEVALUE(Table1[[#This Row],[Date]]) -> 45770 | R44: =IF(F44="NULL", "INVALID", "VALID") -> VALID | S44: =IF(R44="VALID", IF(AND(J44="NULL",K44="NULL"), "INVALID", "VALID"), "INVALID") -> VALID | T44: =IF(S44="VALID", IF(P44<0, "INVALID", "VALID"), "INVALID") -> INVALID | U44: =IF(T44="VALID", IF(Table1[[#This Row],[Quantity]]="NULL", "INVALID", "VALID"), "INVALID") -> INVALID | V44: =IF(U44="VALID", "KEEP","DELETE") -> DELETE
F45: ORD1047 | G45: 2025-03-22 | H45: Telecom | I45: BHARTIARTL | J45: 2090.25 | K45: NULL | L45: 5 | M45: BUY | O45: =IF(LEFT(UPPER(M45),1)="S","SELL",IF(LEFT(UPPER(M45),1)="B","BUY","INVALID")) -> BUY | P45: =IF(L45 = "NULL", 0, IF(AND(I45=I46, H45=H46), P46 + IF(O45="BUY", L45, -L45), IF(O45="BUY", L45, -L45))) -> -190 | Q45: =DATEVALUE(Table1[[#This Row],[Date]]) -> 45738 | R45: =IF(F45="NULL", "INVALID", "VALID") -> VALID | S45: =IF(R45="VALID", IF(AND(J45="NULL",K45="NULL"), "INVALID", "VALID"), "INVALID") -> VALID | T45: =IF(S45="VALID", IF(P45<0, "INVALID", "VALID"), "INVALID") -> INVALID | U45: =IF(T45="VALID", IF(Table1[[#This Row],[Quantity]]="NULL", "INVALID", "VALID"), "INVALID") -> INVALID | V45: =IF(U45="VALID", "KEEP","DELETE") -> DELETE
F46: ORD1106 | G46: 2025-03-13 | H46: Telecom | I46: BHARTIARTL | J46: NULL | K46: 1369.93 | L46: 75 | M46: SELL | O46: =IF(LEFT(UPPER(M46),1)="S","SELL",IF(LEFT(UPPER(M46),1)="B","BUY","INVALID")) -> SELL | P46: =IF(L46 = "NULL", 0, IF(AND(I46=I47, H46=H47), P47 + IF(O46="BUY", L46, -L46), IF(O46="BUY", L46, -L46))) -> -195 | Q46: =DATEVALUE(Table1[[#This Row],[Date]]) -> 45729 | R46: =IF(F46="NULL", "INVALID", "VALID") -> VALID | S46: =IF(R46="VALID", IF(AND(J46="NULL",K46="NULL"), "INVALID", "VALID"), "INVALID") -> VALID | T46: =IF(S46="VALID", IF(P46<0, "INVALID", "VALID"), "INVALID") -> INVALID | U46: =IF(T46="VALID", IF(Table1[[#This Row],[Quantity]]="NULL", "INVALID", "VALID"), "INVALID") -> INVALID | V46: =IF(U46="VALID", "KEEP","DELETE") -> DELETE
F47: ORD1141 | G47: 2025-03-03 | H47: Telecom | I47: BHARTIARTL | J47: NULL | K47: 2326.44 | L47: 15 | M47: Sl | O47: =IF(LEFT(UPPER(M47),1)="S","SELL",IF(LEFT(UPPER(M47),1)="B","BUY","INVALID")) -> SELL | P47: =IF(L47 = "NULL", 0, IF(AND(I47=I48, H47=H48), P48 + IF(O47="BUY", L47, -L47), IF(O47="BUY", L47, -L47))) -> -120 | Q47: =DATEVALUE(Table1[[#This Row],[Date]]) -> 45719 | R47: =IF(F47="NULL", "INVALID", "VALID") -> VALID | S47: =IF(R47="VALID", IF(AND(J47="NULL",K47="NULL"), "INVALID", "VALID"), "INVALID") -> VALID | T47: =IF(S47="VALID", IF(P47<0, "INVALID", "VALID"), "INVALID") -> INVALID | U47: =IF(T47="VALID", IF(Table1[[#This Row],[Quantity]]="NULL", "INVALID", "VALID"), "INVALID") -> INVALID | V47: =IF(U47="VALID", "KEEP","DELETE") -> DELETE
F48: ORD1111 | G48: 2025-02-12 | H48: Telecom | I48: BHARTIARTL | J48: NULL | K48: 2670.67 | L48: 50 | M48: SELL | O48: =IF(LEFT(UPPER(M48),1)="S","SELL",IF(LEFT(UPPER(M48),1)="B","BUY","INVALID")) -> SELL | P48: =IF(L48 = "NULL", 0, IF(AND(I48=I49, H48=H49), P49 + IF(O48="BUY", L48, -L48), IF(O48="BUY", L48, -L48))) -> -105 | Q48: =DATEVALUE(Table1[[#This Row],[Date]]) -> 45700 | R48: =IF(F48="NULL", "INVALID", "VALID") -> VALID | S48: =IF(R48="VALID", IF(AND(J48="NULL",K48="NULL"), "INVALID", "VALID"), "INVALID") -> VALID | T48: =IF(S48="VALID", IF(P48<0, "INVALID", "VALID"), "INVALID") -> INVALID | U48: =IF(T48="VALID", IF(Table1[[#This Row],[Quantity]]="NULL", "INVALID", "VALID"), "INVALID") -> INVALID | V48: =IF(U48="VALID", "KEEP","DELETE") -> DELETE
F49: ORD1114 | G49: 2025-01-27 | H49: Telecom | I49: BHARTIARTL | J49: 2133.53 | K49: NULL | L49: 20 | M49: BUY | O49: =IF(LEFT(UPPER(M49),1)="S","SELL",IF(LEFT(UPPER(M49),1)="B","BUY","INVALID")) -> BUY | P49: =IF(L49 = "NULL", 0, IF(AND(I49=I50, H49=H50), P50 + IF(O49="BUY", L49, -L49), IF(O49="BUY", L49, -L49))) -> -55 | Q49: =DATEVALUE(Table1[[#This Row],[Date]]) -> 45684 | R49: =IF(F49="NULL", "INVALID", "VALID") -> VALID | S49: =IF(R49="VALID", IF(AND(J49="NULL",K49="NULL"), "INVALID", "VALID"), "INVALID") -> VALID | T49: =IF(S49="VALID", IF(P49<0, "INVALID", "VALID"), "INVALID") -> INVALID | U49: =IF(T49="VALID", IF(Table1[[#This Row],[Quantity]]="NULL", "INVALID", "VALID"), "INVALID") -> INVALID | V49: =IF(U49="VALID", "KEEP","DELETE") -> DELETE
F50: ORD1077 | G50: 2025-01-01 | H50: Telecom | I50: BHARTIARTL | J50: NULL | K50: 314.82 | L50: 75 | M50: SELL | O50: =IF(LEFT(UPPER(M50),1)="S","SELL",IF(LEFT(UPPER(M50),1)="B","BUY","INVALID")) -> SELL | P50: =IF(L50 = "NULL", 0, IF(AND(I50=I51, H50=H51), P51 + IF(O50="BUY", L50, -L50), IF(O50="BUY", L50, -L50))) -> -75 | Q50: =DATEVALUE(Table1[[#This Row],[Date]]) -> 45658 | R50: =IF(F50="NULL", "INVALID", "VALID") -> VALID | S50: =IF(R50="VALID", IF(AND(J50="NULL",K50="NULL"), "INVALID", "VALID"), "INVALID") -> VALID | T50: =IF(S50="VALID", IF(P50<0, "INVALID", "VALID"), "INVALID") -> INVALID | U50: =IF(T50="VALID", IF(Table1[[#This Row],[Quantity]]="NULL", "INVALID", "VALID"), "INVALID") -> INVALID | V50: =IF(U50="VALID", "KEEP","DELETE") -> DELETE
F51: ORD1090 | G51: 2025-06-20 | H51: Banking | I51: HDFCBANK | J51: NULL | K51: 630.24 | L51: 100 | M51: SELL | O51: =IF(LEFT(UPPER(M51),1)="S","SELL",IF(LEFT(UPPER(M51),1)="B","BUY","INVALID")) -> SELL | P51: =IF(L51 = "NULL", 0, IF(AND(I51=I52, H51=H52), P52 + IF(O51="BUY", L51, -L51), IF(O51="BUY", L51, -L51))) -> -105 | Q51: =DATEVALUE(Table1[[#This Row],[Date]]) -> 45828 | R51: =IF(F51="NULL", "INVALID", "VALID") -> VALID | S51: =IF(R51="VALID", IF(AND(J51="NULL",K51="NULL"), "INVALID", "VALID"), "INVALID") -> VALID | T51: =IF(S51="VALID", IF(P51<0, "INVALID", "VALID"), "INVALID") -> INVALID | U51: =IF(T51="VALID", IF(Table1[[#This Row],[Quantity]]="NULL", "INVALID", "VALID"), "INVALID") -> INVALID | V51: =IF(U51="VALID", "KEEP","DELETE") -> DELETE
F52: ORD1020 | G52: 2025-06-02 | H52: Banking | I52: HDFCBANK | J52: 2251.94 | K52: NULL | L52: 75 | M52: BUY | O52: =IF(LEFT(UPPER(M52),1)="S","SELL",IF(LEFT(UPPER(M52),1)="B","BUY","INVALID")) -> BUY | P52: =IF(L52 = "NULL", 0, IF(AND(I52=I53, H52=H53), P53 + IF(O52="BUY", L52, -L52), IF(O52="BUY", L52, -L52))) -> -5 | Q52: =DATEVALUE(Table1[[#This Row],[Date]]) -> 45810 | R52: =IF(F52="NULL", "INVALID", "VALID") -> VALID | S52: =IF(R52="VALID", IF(AND(J52="NULL",K52="NULL"), "INVALID", "VALID"), "INVALID") -> VALID | T52: =IF(S52="VALID", IF(P52<0, "INVALID", "VALID"), "INVALID") -> INVALID | U52: =IF(T52="VALID", IF(Table1[[#This Row],[Quantity]]="NULL", "INVALID", "VALID"), "INVALID") -> INVALID | V52: =IF(U52="VALID", "KEEP","DELETE") -> DELETE
F53: ORD1194 | G53: 2025-05-30 | H53: Banking | I53: HDFCBANK | J53: NULL | K53: 1421.05 | L53: 25 | M53: SELL | O53: =IF(LEFT(UPPER(M53),1)="S","SELL",IF(LEFT(UPPER(M53),1)="B","BUY","INVALID")) -> SELL | P53: =IF(L53 = "NULL", 0, IF(AND(I53=I54, H53=H54), P54 + IF(O53="BUY", L53, -L53), IF(O53="BUY", L53, -L53))) -> -80 | Q53: =DATEVALUE(Table1[[#This Row],[Date]]) -> 45807 | R53: =IF(F53="NULL", "INVALID", "VALID") -> VALID | S53: =IF(R53="VALID", IF(AND(J53="NULL",K53="NULL"), "INVALID", "VALID"), "INVALID") -> VALID | T53: =IF(S53="VALID", IF(P53<0, "INVALID", "VALID"), "INVALID") -> INVALID | U53: =IF(T53="VALID", IF(Table1[[#This Row],[Quantity]]="NULL", "INVALID", "VALID"), "INVALID") -> INVALID | V53: =IF(U53="VALID", "KEEP","DELETE") -> DELETE
F54: ORD1112 | G54: 2025-05-29 | H54: Banking | I54: HDFCBANK | J54: 3381.81 | K54: NULL | L54: 10 | M54: BUY | O54: =IF(LEFT(UPPER(M54),1)="S","SELL",IF(LEFT(UPPER(M54),1)="B","BUY","INVALID")) -> BUY | P54: =IF(L54 = "NULL", 0, IF(AND(I54=I55, H54=H55), P55 + IF(O54="BUY", L54, -L54), IF(O54="BUY", L54, -L54))) -> -55 | Q54: =DATEVALUE(Table1[[#This Row],[Date]]) -> 45806 | R54: =IF(F54="NULL", "INVALID", "VALID") -> VALID | S54: =IF(R54="VALID", IF(AND(J54="NULL",K54="NULL"), "INVALID", "VALID"), "INVALID") -> VALID | T54: =IF(S54="VALID", IF(P54<0, "INVALID", "VALID"), "INVALID") -> INVALID | U54: =IF(T54="VALID", IF(Table1[[#This Row],[Quantity]]="NULL", "INVALID", "VALID"), "INVALID") -> INVALID | V54: =IF(U54="VALID", "KEEP","DELETE") -> DELETE
F55: ORD1059 | G55: 2025-03-11 | H55: Banking | I55: HDFCBANK | J55: 2637.1 | K55: NULL | L55: 15 | M55: BUY | O55: =IF(LEFT(UPPER(M55),1)="S","SELL",IF(LEFT(UPPER(M55),1)="B","BUY","INVALID")) -> BUY | P55: =IF(L55 = "NULL", 0, IF(AND(I55=I56, H55=H56), P56 + IF(O55="BUY", L55, -L55), IF(O55="BUY", L55, -L55))) -> -65 | Q55: =DATEVALUE(Table1[[#This Row],[Date]]) -> 45727 | R55: =IF(F55="NULL", "INVALID", "VALID") -> VALID | S55: =IF(R55="VALID", IF(AND(J55="NULL",K55="NULL"), "INVALID", "VALID"), "INVALID") -> VALID | T55: =IF(S55="VALID", IF(P55<0, "INVALID", "VALID"), "INVALID") -> INVALID | U55: =IF(T55="VALID", IF(Table1[[#This Row],[Quantity]]="NULL", "INVALID", "VALID"), "INVALID") -> INVALID | V55: =IF(U55="VALID", "KEEP","DELETE") -> DELETE
F56: ORD1028 | G56: 2025-03-03 | H56: Banking | I56: HDFCBANK | J56: NULL | K56: 2974.87 | L56: 25 | M56: SELL | O56: =IF(LEFT(UPPER(M56),1)="S","SELL",IF(LEFT(UPPER(M56),1)="B","BUY","INVALID")) -> SELL | P56: =IF(L56 = "NULL", 0, IF(AND(I56=I57, H56=H57), P57 + IF(O56="BUY", L56, -L56), IF(O56="BUY", L56, -L56))) -> -80 | Q56: =DATEVALUE(Table1[[#This Row],[Date]]) -> 45719 | R56: =IF(F56="NULL", "INVALID", "VALID") -> VALID | S56: =IF(R56="VALID", IF(AND(J56="NULL",K56="NULL"), "INVALID", "VALID"), "INVALID") -> VALID | T56: =IF(S56="VALID", IF(P56<0, "INVALID", "VALID"), "INVALID") -> INVALID | U56: =IF(T56="VALID", IF(Table1[[#This Row],[Quantity]]="NULL", "INVALID", "VALID"), "INVALID") -> INVALID | V56: =IF(U56="VALID", "KEEP","DELETE") -> DELETE
F57: ORD1000 | G57: 2025-02-27 | H57: Banking | I57: HDFCBANK | J57: 2634.19 | K57: NULL | L57: 20 | M57: BUY | O57: =IF(LEFT(UPPER(M57),1)="S","SELL",IF(LEFT(UPPER(M57),1)="B","BUY","INVALID")) -> BUY | P57: =IF(L57 = "NULL", 0, IF(AND(I57=I58, H57=H58), P58 + IF(O57="BUY", L57, -L57), IF(O57="BUY", L57, -L57))) -> -55 | Q57: =DATEVALUE(Table1[[#This Row],[Date]]) -> 45715 | R57: =IF(F57="NULL", "INVALID", "VALID") -> VALID | S57: =IF(R57="VALID", IF(AND(J57="NULL",K57="NULL"), "INVALID", "VALID"), "INVALID") -> VALID | T57: =IF(S57="VALID", IF(P57<0, "INVALID", "VALID"), "INVALID") -> INVALID | U57: =IF(T57="VALID", IF(Table1[[#This Row],[Quantity]]="NULL", "INVALID", "VALID"), "INVALID") -> INVALID | V57: =IF(U57="VALID", "KEEP","DELETE") -> DELETE
F58: ORD1040 | G58: 2025-01-28 | H58: Banking | I58: HDFCBANK | J58: 1498.78 | K58: NULL | L58: 50 | M58: BUY | O58: =IF(LEFT(UPPER(M58),1)="S","SELL",IF(LEFT(UPPER(M58),1)="B","BUY","INVALID")) -> BUY | P58: =IF(L58 = "NULL", 0, IF(AND(I58=I59, H58=H59), P59 + IF(O58="BUY", L58, -L58), IF(O58="BUY", L58, -L58))) -> -75 | Q58: =DATEVALUE(Table1[[#This Row],[Date]]) -> 45685 | R58: =IF(F58="NULL", "INVALID", "VALID") -> VALID | S58: =IF(R58="VALID", IF(AND(J58="NULL",K58="NULL"), "INVALID", "VALID"), "INVALID") -> VALID | T58: =IF(S58="VALID", IF(P58<0, "INVALID", "VALID"), "INVALID") -> INVALID | U58: =IF(T58="VALID", IF(Table1[[#This Row],[Quantity]]="NULL", "INVALID", "VALID"), "INVALID") -> INVALID | V58: =IF(U58="VALID", "KEEP","DELETE") -> DELETE
F59: ORD1089 | G59: 2025-01-13 | H59: Banking | I59: HDFCBANK | J59: NULL | K59: 937.41 | L59: 100 | M59: SELL | O59: =IF(LEFT(UPPER(M59),1)="S","SELL",IF(LEFT(UPPER(M59),1)="B","BUY","INVALID")) -> SELL | P59: =IF(L59 = "NULL", 0, IF(AND(I59=I60, H59=H60), P60 + IF(O59="BUY", L59, -L59), IF(O59="BUY", L59, -L59))) -> -125 | Q59: =DATEVALUE(Table1[[#This Row],[Date]]) -> 45670 | R59: =IF(F59="NULL", "INVALID", "VALID") -> VALID | S59: =IF(R59="VALID", IF(AND(J59="NULL",K59="NULL"), "INVALID", "VALID"), "INVALID") -> VALID | T59: =IF(S59="VALID", IF(P59<0, "INVALID", "VALID"), "INVALID") -> INVALID | U59: =IF(T59="VALID", IF(Table1[[#This Row],[Quantity]]="NULL", "INVALID", "VALID"), "INVALID") -> INVALID | V59: =IF(U59="VALID", "KEEP","DELETE") -> DELETE
F60: ORD1006 | G60: 2025-01-12 | H60: Banking | I60: HDFCBANK | J60: NULL | K60: 3275.9 | L60: 25 | M60: SELL | O60: =IF(LEFT(UPPER(M60),1)="S","SELL",IF(LEFT(UPPER(M60),1)="B","BUY","INVALID")) -> SELL | P60: =IF(L60 = "NULL", 0, IF(AND(I60=I61, H60=H61), P61 + IF(O60="BUY", L60, -L60), IF(O60="BUY", L60, -L60))) -> -25 | Q60: =DATEVALUE(Table1[[#This Row],[Date]]) -> 45669 | R60: =IF(F60="NULL", "INVALID", "VALID") -> VALID | S60: =IF(R60="VALID", IF(AND(J60="NULL",K60="NULL"), "INVALID", "VALID"), "INVALID") -> VALID | T60: =IF(S60="VALID", IF(P60<0, "INVALID", "VALID"), "INVALID") -> INVALID | U60: =IF(T60="VALID", IF(Table1[[#This Row],[Quantity]]="NULL", "INVALID", "VALID"), "INVALID") -> INVALID | V60: =IF(U60="VALID", "KEEP","DELETE") -> DELETE
F61: ORD1001 | G61: 2025-06-01 | H61: Banking | I61: ICICIBANK | J61: 2416.94 | K61: NULL | L61: 10 | M61: BUY | O61: =IF(LEFT(UPPER(M61),1)="S","SELL",IF(LEFT(UPPER(M61),1)="B","BUY","INVALID")) -> BUY | P61: =IF(L61 = "NULL", 0, IF(AND(I61=I62, H61=H62), P62 + IF(O61="BUY", L61, -L61), IF(O61="BUY", L61, -L61))) -> 155 | Q61: =DATEVALUE(Table1[[#This Row],[Date]]) -> 45809 | R61: =IF(F61="NULL", "INVALID", "VALID") -> VALID | S61: =IF(R61="VALID", IF(AND(J61="NULL",K61="NULL"), "INVALID", "VALID"), "INVALID") -> VALID | T61: =IF(S61="VALID", IF(P61<0, "INVALID", "VALID"), "INVALID") -> VALID | U61: =IF(T61="VALID", IF(Table1[[#This Row],[Quantity]]="NULL", "INVALID", "VALID"), "INVALID") -> VALID | V61: =IF(U61="VALID", "KEEP","DELETE") -> KEEP
F62: ORD1110 | G62: 2025-05-25 | H62: Banking | I62: ICICIBANK | J62: 572.84 | K62: NULL | L62: 10 | M62: BUY | O62: =IF(LEFT(UPPER(M62),1)="S","SELL",IF(LEFT(UPPER(M62),1)="B","BUY","INVALID")) -> BUY | P62: =IF(L62 = "NULL", 0, IF(AND(I62=I63, H62=H63), P63 + IF(O62="BUY", L62, -L62), IF(O62="BUY", L62, -L62))) -> 145 | Q62: =DATEVALUE(Table1[[#This Row],[Date]]) -> 45802 | R62: =IF(F62="NULL", "INVALID", "VALID") -> VALID | S62: =IF(R62="VALID", IF(AND(J62="NULL",K62="NULL"), "INVALID", "VALID"), "INVALID") -> VALID | T62: =IF(S62="VALID", IF(P62<0, "INVALID", "VALID"), "INVALID") -> VALID | U62: =IF(T62="VALID", IF(Table1[[#This Row],[Quantity]]="NULL", "INVALID", "VALID"), "INVALID") -> VALID | V62: =IF(U62="VALID", "KEEP","DELETE") -> KEEP | X62: Cleaned_Order_Type | Y62: Resolved Mistyped Values
F63: ORD1161 | G63: 2025-05-11 | H63: Banking | I63: ICICIBANK | J63: NULL | K63: 3572.63 | L63: 25 | M63: SELL | O63: =IF(LEFT(UPPER(M63),1)="S","SELL",IF(LEFT(UPPER(M63),1)="B","BUY","INVALID")) -> SELL | P63: =IF(L63 = "NULL", 0, IF(AND(I63=I64, H63=H64), P64 + IF(O63="BUY", L63, -L63), IF(O63="BUY", L63, -L63))) -> 135 | Q63: =DATEVALUE(Table1[[#This Row],[Date]]) -> 45788 | R63: =IF(F63="NULL", "INVALID", "VALID") -> VALID | S63: =IF(R63="VALID", IF(AND(J63="NULL",K63="NULL"), "INVALID", "VALID"), "INVALID") -> VALID | T63: =IF(S63="VALID", IF(P63<0, "INVALID", "VALID"), "INVALID") -> VALID | U63: =IF(T63="VALID", IF(Table1[[#This Row],[Quantity]]="NULL", "INVALID", "VALID"), "INVALID") -> VALID | V63: =IF(U63="VALID", "KEEP","DELETE") -> KEEP | X63: Curr_Hold | Y63: Cummulative quantity
F64: ORD1068 | G64: 2025-04-16 | H64: Banking | I64: ICICIBANK | J64: 3046.43 | K64: NULL | L64: 15 | M64: BUY | O64: =IF(LEFT(UPPER(M64),1)="S","SELL",IF(LEFT(UPPER(M64),1)="B","BUY","INVALID")) -> BUY | P64: =IF(L64 = "NULL", 0, IF(AND(I64=I65, H64=H65), P65 + IF(O64="BUY", L64, -L64), IF(O64="BUY", L64, -L64))) -> 160 | Q64: =DATEVALUE(Table1[[#This Row],[Date]]) -> 45763 | R64: =IF(F64="NULL", "INVALID", "VALID") -> VALID | S64: =IF(R64="VALID", IF(AND(J64="NULL",K64="NULL"), "INVALID", "VALID"), "INVALID") -> VALID | T64: =IF(S64="VALID", IF(P64<0, "INVALID", "VALID"), "INVALID") -> VALID | U64: =IF(T64="VALID", IF(Table1[[#This Row],[Quantity]]="NULL", "INVALID", "VALID"), "INVALID") -> VALID | V64: =IF(U64="VALID", "KEEP","DELETE") -> KEEP | X64: Date_format | Y64: Converted text to Actual Date format
F65: ORD1171 | G65: 2025-03-28 | H65: Banking | I65: ICICIBANK | J65: 1722.79 | K65: NULL | L65: 25 | M65: BUY | O65: =IF(LEFT(UPPER(M65),1)="S","SELL",IF(LEFT(UPPER(M65),1)="B","BUY","INVALID")) -> BUY | P65: =IF(L65 = "NULL", 0, IF(AND(I65=I66, H65=H66), P66 + IF(O65="BUY", L65, -L65), IF(O65="BUY", L65, -L65))) -> 145 | Q65: =DATEVALUE(Table1[[#This Row],[Date]]) -> 45744 | R65: =IF(F65="NULL", "INVALID", "VALID") -> VALID | S65: =IF(R65="VALID", IF(AND(J65="NULL",K65="NULL"), "INVALID", "VALID"), "INVALID") -> VALID | T65: =IF(S65="VALID", IF(P65<0, "INVALID", "VALID"), "INVALID") -> VALID | U65: =IF(T65="VALID", IF(Table1[[#This Row],[Quantity]]="NULL", "INVALID", "VALID"), "INVALID") -> VALID | V65: =IF(U65="VALID", "KEEP","DELETE") -> KEEP | X65: Reason_1 | Y65: Order_ID Missing
F66: ORD1097 | G66: 2025-03-26 | H66: Banking | I66: ICICIBANK | J66: 365.17 | K66: NULL | L66: 75 | M66: BUY | O66: =IF(LEFT(UPPER(M66),1)="S","SELL",IF(LEFT(UPPER(M66),1)="B","BUY","INVALID")) -> BUY | P66: =IF(L66 = "NULL", 0, IF(AND(I66=I67, H66=H67), P67 + IF(O66="BUY", L66, -L66), IF(O66="BUY", L66, -L66))) -> 120 | Q66: =DATEVALUE(Table1[[#This Row],[Date]]) -> 45742 | R66: =IF(F66="NULL", "INVALID", "VALID") -> VALID | S66: =IF(R66="VALID", IF(AND(J66="NULL",K66="NULL"), "INVALID", "VALID"), "INVALID") -> VALID | T66: =IF(S66="VALID", IF(P66<0, "INVALID", "VALID"), "INVALID") -> VALID | U66: =IF(T66="VALID", IF(Table1[[#This Row],[Quantity]]="NULL", "INVALID", "VALID"), "INVALID") -> VALID | V66: =IF(U66="VALID", "KEEP","DELETE") -> KEEP | X66: Reason_2 | Y66: Both Buy_Price & Sell_Price is Missing
F67: ORD1187 | G67: 2025-03-21 | H67: Banking | I67: ICICIBANK | J67: 3176.4 | K67: NULL | L67: 5 | M67: BUY | O67: =IF(LEFT(UPPER(M67),1)="S","SELL",IF(LEFT(UPPER(M67),1)="B","BUY","INVALID")) -> BUY | P67: =IF(L67 = "NULL", 0, IF(AND(I67=I68, H67=H68), P68 + IF(O67="BUY", L67, -L67), IF(O67="BUY", L67, -L67))) -> 45 | Q67: =DATEVALUE(Table1[[#This Row],[Date]]) -> 45737 | R67: =IF(F67="NULL", "INVALID", "VALID") -> VALID | S67: =IF(R67="VALID", IF(AND(J67="NULL",K67="NULL"), "INVALID", "VALID"), "INVALID") -> VALID | T67: =IF(S67="VALID", IF(P67<0, "INVALID", "VALID"), "INVALID") -> VALID | U67: =IF(T67="VALID", IF(Table1[[#This Row],[Quantity]]="NULL", "INVALID", "VALID"), "INVALID") -> VALID | V67: =IF(U67="VALID", "KEEP","DELETE") -> KEEP | X67: Reason_3 | Y67: Cannot SELL before BUYING
F68: ORD1169 | G68: 2025-01-26 | H68: Banking | I68: ICICIBANK | J68: NULL | K68: 3232.57 | L68: 50 | M68: by | O68: =IF(LEFT(UPPER(M68),1)="S","SELL",IF(LEFT(UPPER(M68),1)="B","BUY","INVALID")) -> BUY | P68: =IF(L68 = "NULL", 0, IF(AND(I68=I69, H68=H69), P69 + IF(O68="BUY", L68, -L68), IF(O68="BUY", L68, -L68))) -> 40 | Q68: =DATEVALUE(Table1[[#This Row],[Date]]) -> 45683 | R68: =IF(F68="NULL", "INVALID", "VALID") -> VALID | S68: =IF(R68="VALID", IF(AND(J68="NULL",K68="NULL"), "INVALID", "VALID"), "INVALID") -> VALID | T68: =IF(S68="VALID", IF(P68<0, "INVALID", "VALID"), "INVALID") -> VALID | U68: =IF(T68="VALID", IF(Table1[[#This Row],[Quantity]]="NULL", "INVALID", "VALID"), "INVALID") -> VALID | V68: =IF(U68="VALID", "KEEP","DELETE") -> KEEP | X68: Reason_4 | Y68: Quantity Missing
F69: ORD1146 | G69: 2025-01-16 | H69: Banking | I69: ICICIBANK | J69: NULL | K69: 2870.13 | L69: 10 | M69: SELL | O69: =IF(LEFT(UPPER(M69),1)="S","SELL",IF(LEFT(UPPER(M69),1)="B","BUY","INVALID")) -> SELL | P69: =IF(L69 = "NULL", 0, IF(AND(I69=I70, H69=H70), P70 + IF(O69="BUY", L69, -L69), IF(O69="BUY", L69, -L69))) -> -10 | Q69: =DATEVALUE(Table1[[#This Row],[Date]]) -> 45673 | R69: =IF(F69="NULL", "INVALID", "VALID") -> VALID | S69: =IF(R69="VALID", IF(AND(J69="NULL",K69="NULL"), "INVALID", "VALID"), "INVALID") -> VALID | T69: =IF(S69="VALID", IF(P69<0, "INVALID", "VALID"), "INVALID") -> INVALID | U69: =IF(T69="VALID", IF(Table1[[#This Row],[Quantity]]="NULL", "INVALID", "VALID"), "INVALID") -> INVALID | V69: =IF(U69="VALID", "KEEP","DELETE") -> DELETE
F70: ORD1096 | G70: 2025-06-27 | H70: IT | I70: INFY | J70: 655.28 | K70: NULL | L70: 75 | M70: BUY | O70: =IF(LEFT(UPPER(M70),1)="S","SELL",IF(LEFT(UPPER(M70),1)="B","BUY","INVALID")) -> BUY | P70: =IF(L70 = "NULL", 0, IF(AND(I70=I71, H70=H71), P71 + IF(O70="BUY", L70, -L70), IF(O70="BUY", L70, -L70))) -> 275 | Q70: =DATEVALUE(Table1[[#This Row],[Date]]) -> 45835 | R70: =IF(F70="NULL", "INVALID", "VALID") -> VALID | S70: =IF(R70="VALID", IF(AND(J70="NULL",K70="NULL"), "INVALID", "VALID"), "INVALID") -> VALID | T70: =IF(S70="VALID", IF(P70<0, "INVALID", "VALID"), "INVALID") -> VALID | U70: =IF(T70="VALID", IF(Table1[[#This Row],[Quantity]]="NULL", "INVALID", "VALID"), "INVALID") -> VALID | V70: =IF(U70="VALID", "KEEP","DELETE") -> KEEP
F71: ORD1142 | G71: 2025-06-26 | H71: IT | I71: INFY | J71: 158.96 | K71: NULL | L71: 100 | M71: BUY | O71: =IF(LEFT(UPPER(M71),1)="S","SELL",IF(LEFT(UPPER(M71),1)="B","BUY","INVALID")) -> BUY | P71: =IF(L71 = "NULL", 0, IF(AND(I71=I72, H71=H72), P72 + IF(O71="BUY", L71, -L71), IF(O71="BUY", L71, -L71))) -> 200 | Q71: =DATEVALUE(Table1[[#This Row],[Date]]) -> 45834 | R71: =IF(F71="NULL", "INVALID", "VALID") -> VALID | S71: =IF(R71="VALID", IF(AND(J71="NULL",K71="NULL"), "INVALID", "VALID"), "INVALID") -> VALID | T71: =IF(S71="VALID", IF(P71<0, "INVALID", "VALID"), "INVALID") -> VALID | U71: =IF(T71="VALID", IF(Table1[[#This Row],[Quantity]]="NULL", "INVALID", "VALID"), "INVALID") -> VALID | V71: =IF(U71="VALID", "KEEP","DELETE") -> KEEP
F72: ORD1192 | G72: 2025-06-23 | H72: IT | I72: INFY | J72: 2676.41 | K72: NULL | L72: 20 | M72: BUY | O72: =IF(LEFT(UPPER(M72),1)="S","SELL",IF(LEFT(UPPER(M72),1)="B","BUY","INVALID")) -> BUY | P72: =IF(L72 = "NULL", 0, IF(AND(I72=I73, H72=H73), P73 + IF(O72="BUY", L72, -L72), IF(O72="BUY", L72, -L72))) -> 100 | Q72: =DATEVALUE(Table1[[#This Row],[Date]]) -> 45831 | R72: =IF(F72="NULL", "INVALID", "VALID") -> VALID | S72: =IF(R72="VALID", IF(AND(J72="NULL",K72="NULL"), "INVALID", "VALID"), "INVALID") -> VALID | T72: =IF(S72="VALID", IF(P72<0, "INVALID", "VALID"), "INVALID") -> VALID | U72: =IF(T72="VALID", IF(Table1[[#This Row],[Quantity]]="NULL", "INVALID", "VALID"), "INVALID") -> VALID | V72: =IF(U72="VALID", "KEEP","DELETE") -> KEEP
F73: ORD1050 | G73: 2025-05-29 | H73: IT | I73: INFY | J73: 1502.65 | K73: NULL | L73: 20 | M73: BUY | O73: =IF(LEFT(UPPER(M73),1)="S","SELL",IF(LEFT(UPPER(M73),1)="B","BUY","INVALID")) -> BUY | P73: =IF(L73 = "NULL", 0, IF(AND(I73=I74, H73=H74), P74 + IF(O73="BUY", L73, -L73), IF(O73="BUY", L73, -L73))) -> 80 | Q73: =DATEVALUE(Table1[[#This Row],[Date]]) -> 45806 | R73: =IF(F73="NULL", "INVALID", "VALID") -> VALID | S73: =IF(R73="VALID", IF(AND(J73="NULL",K73="NULL"), "INVALID", "VALID"), "INVALID") -> VALID | T73: =IF(S73="VALID", IF(P73<0, "INVALID", "VALID"), "INVALID") -> VALID | U73: =IF(T73="VALID", IF(Table1[[#This Row],[Quantity]]="NULL", "INVALID", "VALID"), "INVALID") -> VALID | V73: =IF(U73="VALID", "KEEP","DELETE") -> KEEP
F74: ORD1021 | G74: 2025-05-16 | H74: IT | I74: INFY | J74: NULL | K74: 1428.83 | L74: 100 | M74: SELL | O74: =IF(LEFT(UPPER(M74),1)="S","SELL",IF(LEFT(UPPER(M74),1)="B","BUY","INVALID")) -> SELL | P74: =IF(L74 = "NULL", 0, IF(AND(I74=I75, H74=H75), P75 + IF(O74="BUY", L74, -L74), IF(O74="BUY", L74, -L74))) -> 60 | Q74: =DATEVALUE(Table1[[#This Row],[Date]]) -> 45793 | R74: =IF(F74="NULL", "INVALID", "VALID") -> VALID | S74: =IF(R74="VALID", IF(AND(J74="NULL",K74="NULL"), "INVALID", "VALID"), "INVALID") -> VALID | T74: =IF(S74="VALID", IF(P74<0, "INVALID", "VALID"), "INVALID") -> VALID | U74: =IF(T74="VALID", IF(Table1[[#This Row],[Quantity]]="NULL", "INVALID", "VALID"), "INVALID") -> VALID | V74: =IF(U74="VALID", "KEEP","DELETE") -> KEEP
F75: ORD1120 | G75: 2025-04-29 | H75: IT | I75: INFY | J75: NULL | K75: 3301.99 | L75: 20 | M75: sale | O75: =IF(LEFT(UPPER(M75),1)="S","SELL",IF(LEFT(UPPER(M75),1)="B","BUY","INVALID")) -> SELL | P75: =IF(L75 = "NULL", 0, IF(AND(I75=I76, H75=H76), P76 + IF(O75="BUY", L75, -L75), IF(O75="BUY", L75, -L75))) -> 160 | Q75: =DATEVALUE(Table1[[#This Row],[Date]]) -> 45776 | R75: =IF(F75="NULL", "INVALID", "VALID") -> VALID | S75: =IF(R75="VALID", IF(AND(J75="NULL",K75="NULL"), "INVALID", "VALID"), "INVALID") -> VALID | T75: =IF(S75="VALID", IF(P75<0, "INVALID", "VALID"), "INVALID") -> VALID | U75: =IF(T75="VALID", IF(Table1[[#This Row],[Quantity]]="NULL", "INVALID", "VALID"), "INVALID") -> VALID | V75: =IF(U75="VALID", "KEEP","DELETE") -> KEEP
F76: ORD1175 | G76: 2025-04-24 | H76: IT | I76: INFY | J76: NULL | K76: 3370.1 | L76: 10 | M76: SELL | O76: =IF(LEFT(UPPER(M76),1)="S","SELL",IF(LEFT(UPPER(M76),1)="B","BUY","INVALID")) -> SELL | P76: =IF(L76 = "NULL", 0, IF(AND(I76=I77, H76=H77), P77 + IF(O76="BUY", L76, -L76), IF(O76="BUY", L76, -L76))) -> 180 | Q76: =DATEVALUE(Table1[[#This Row],[Date]]) -> 45771 | R76: =IF(F76="NULL", "INVALID", "VALID") -> VALID | S76: =IF(R76="VALID", IF(AND(J76="NULL",K76="NULL"), "INVALID", "VALID"), "INVALID") -> VALID | T76: =IF(S76="VALID", IF(P76<0, "INVALID", "VALID"), "INVALID") -> VALID | U76: =IF(T76="VALID", IF(Table1[[#This Row],[Quantity]]="NULL", "INVALID", "VALID"), "INVALID") -> VALID | V76: =IF(U76="VALID", "KEEP","DELETE") -> KEEP
F77: ORD1056 | G77: 2025-04-23 | H77: IT | I77: INFY | J77: 1387.92 | K77: NULL | L77: 15 | M77: BUY | O77: =IF(LEFT(UPPER(M77),1)="S","SELL",IF(LEFT(UPPER(M77),1)="B","BUY","INVALID")) -> BUY | P77: =IF(L77 = "NULL", 0, IF(AND(I77=I78, H77=H78), P78 + IF(O77="BUY", L77, -L77), IF(O77="BUY", L77, -L77))) -> 190 | Q77: =DATEVALUE(Table1[[#This Row],[Date]]) -> 45770 | R77: =IF(F77="NULL", "INVALID", "VALID") -> VALID | S77: =IF(R77="VALID", IF(AND(J77="NULL",K77="NULL"), "INVALID", "VALID"), "INVALID") -> VALID | T77: =IF(S77="VALID", IF(P77<0, "INVALID", "VALID"), "INVALID") -> VALID | U77: =IF(T77="VALID", IF(Table1[[#This Row],[Quantity]]="NULL", "INVALID", "VALID"), "INVALID") -> VALID | V77: =IF(U77="VALID", "KEEP","DELETE") -> KEEP
F78: ORD1155 | G78: 2025-04-14 | H78: IT | I78: INFY | J78: NULL | K78: 1117.97 | L78: 10 | M78: SELL | O78: =IF(LEFT(UPPER(M78),1)="S","SELL",IF(LEFT(UPPER(M78),1)="B","BUY","INVALID")) -> SELL | P78: =IF(L78 = "NULL", 0, IF(AND(I78=I79, H78=H79), P79 + IF(O78="BUY", L78, -L78), IF(O78="BUY", L78, -L78))) -> 175 | Q78: =DATEVALUE(Table1[[#This Row],[Date]]) -> 45761 | R78: =IF(F78="NULL", "INVALID", "VALID") -> VALID | S78: =IF(R78="VALID", IF(AND(J78="NULL",K78="NULL"), "INVALID", "VALID"), "INVALID") -> VALID | T78: =IF(S78="VALID", IF(P78<0, "INVALID", "VALID"), "INVALID") -> VALID | U78: =IF(T78="VALID", IF(Table1[[#This Row],[Quantity]]="NULL", "INVALID", "VALID"), "INVALID") -> VALID | V78: =IF(U78="VALID", "KEEP","DELETE") -> KEEP
F79: ORD1174 | G79: 2025-02-28 | H79: IT | I79: INFY | J79: 2264.39 | K79: NULL | L79: 25 | M79: BUY | O79: =IF(LEFT(UPPER(M79),1)="S","SELL",IF(LEFT(UPPER(M79),1)="B","BUY","INVALID")) -> BUY | P79: =IF(L79 = "NULL", 0, IF(AND(I79=I80, H79=H80), P80 + IF(O79="BUY", L79, -L79), IF(O79="BUY", L79, -L79))) -> 185 | Q79: =DATEVALUE(Table1[[#This Row],[Date]]) -> 45716 | R79: =IF(F79="NULL", "INVALID", "VALID") -> VALID | S79: =IF(R79="VALID", IF(AND(J79="NULL",K79="NULL"), "INVALID", "VALID"), "INVALID") -> VALID | T79: =IF(S79="VALID", IF(P79<0, "INVALID", "VALID"), "INVALID") -> VALID | U79: =IF(T79="VALID", IF(Table1[[#This Row],[Quantity]]="NULL", "INVALID", "VALID"), "INVALID") -> VALID | V79: =IF(U79="VALID", "KEEP","DELETE") -> KEEP
F80: ORD1036 | G80: 2025-02-24 | H80: IT | I80: INFY | J80: 1082.9 | K80: NULL | L80: 100 | M80: BUY | O80: =IF(LEFT(UPPER(M80),1)="S","SELL",IF(LEFT(UPPER(M80),1)="B","BUY","INVALID")) -> BUY | P80: =IF(L80 = "NULL", 0, IF(AND(I80=I81, H80=H81), P81 + IF(O80="BUY", L80, -L80), IF(O80="BUY", L80, -L80))) -> 160 | Q80: =DATEVALUE(Table1[[#This Row],[Date]]) -> 45712 | R80: =IF(F80="NULL", "INVALID", "VALID") -> VALID | S80: =IF(R80="VALID", IF(AND(J80="NULL",K80="NULL"), "INVALID", "VALID"), "INVALID") -> VALID | T80: =IF(S80="VALID", IF(P80<0, "INVALID", "VALID"), "INVALID") -> VALID | U80: =IF(T80="VALID", IF(Table1[[#This Row],[Quantity]]="NULL", "INVALID", "VALID"), "INVALID") -> VALID | V80: =IF(U80="VALID", "KEEP","DELETE") -> KEEP
F81: ORD1136 | G81: 2025-01-22 | H81: IT | I81: INFY | J81: 658.29 | K81: NULL | L81: 25 | M81: BUY | O81: =IF(LEFT(UPPER(M81),1)="S","SELL",IF(LEFT(UPPER(M81),1)="B","BUY","INVALID")) -> BUY | P81: =IF(L81 = "NULL", 0, IF(AND(I81=I82, H81=H82), P82 + IF(O81="BUY", L81, -L81), IF(O81="BUY", L81, -L81))) -> 60 | Q81: =DATEVALUE(Table1[[#This Row],[Date]]) -> 45679 | R81: =IF(F81="NULL", "INVALID", "VALID") -> VALID | S81: =IF(R81="VALID", IF(AND(J81="NULL",K81="NULL"), "INVALID", "VALID"), "INVALID") -> VALID | T81: =IF(S81="VALID", IF(P81<0, "INVALID", "VALID"), "INVALID") -> VALID | U81: =IF(T81="VALID", IF(Table1[[#This Row],[Quantity]]="NULL", "INVALID", "VALID"), "INVALID") -> VALID | V81: =IF(U81="VALID", "KEEP","DELETE") -> KEEP
F82: ORD1009 | G82: 2025-01-21 | H82: IT | I82: INFY | J82: 2365.23 | K82: NULL | L82: 25 | M82: BUY | O82: =IF(LEFT(UPPER(M82),1)="S","SELL",IF(LEFT(UPPER(M82),1)="B","BUY","INVALID")) -> BUY | P82: =IF(L82 = "NULL", 0, IF(AND(I82=I83, H82=H83), P83 + IF(O82="BUY", L82, -L82), IF(O82="BUY", L82, -L82))) -> 35 | Q82: =DATEVALUE(Table1[[#This Row],[Date]]) -> 45678 | R82: =IF(F82="NULL", "INVALID", "VALID") -> VALID | S82: =IF(R82="VALID", IF(AND(J82="NULL",K82="NULL"), "INVALID", "VALID"), "INVALID") -> VALID | T82: =IF(S82="VALID", IF(P82<0, "INVALID", "VALID"), "INVALID") -> VALID | U82: =IF(T82="VALID", IF(Table1[[#This Row],[Quantity]]="NULL", "INVALID", "VALID"), "INVALID") -> VALID | V82: =IF(U82="VALID", "KEEP","DELETE") -> KEEP
F83: ORD1054 | G83: 2025-01-19 | H83: IT | I83: INFY | J83: 1685.26 | K83: NULL | L83: 10 | M83: BUY | O83: =IF(LEFT(UPPER(M83),1)="S","SELL",IF(LEFT(UPPER(M83),1)="B","BUY","INVALID")) -> BUY | P83: =IF(L83 = "NULL", 0, IF(AND(I83=I84, H83=H84), P84 + IF(O83="BUY", L83, -L83), IF(O83="BUY", L83, -L83))) -> 10 | Q83: =DATEVALUE(Table1[[#This Row],[Date]]) -> 45676 | R83: =IF(F83="NULL", "INVALID", "VALID") -> VALID | S83: =IF(R83="VALID", IF(AND(J83="NULL",K83="NULL"), "INVALID", "VALID"), "INVALID") -> VALID | T83: =IF(S83="VALID", IF(P83<0, "INVALID", "VALID"), "INVALID") -> VALID | U83: =IF(T83="VALID", IF(Table1[[#This Row],[Quantity]]="NULL", "INVALID", "VALID"), "INVALID") -> VALID | V83: =IF(U83="VALID", "KEEP","DELETE") -> KEEP
F84: ORD1013 | G84: 2025-06-13 | H84: FMCG | I84: ITC | J84: 1698.57 | K84: NULL | L84: 25 | M84: BUY | O84: =IF(LEFT(UPPER(M84),1)="S","SELL",IF(LEFT(UPPER(M84),1)="B","BUY","INVALID")) -> BUY | P84: =IF(L84 = "NULL", 0, IF(AND(I84=I85, H84=H85), P85 + IF(O84="BUY", L84, -L84), IF(O84="BUY", L84, -L84))) -> 310 | Q84: =DATEVALUE(Table1[[#This Row],[Date]]) -> 45821 | R84: =IF(F84="NULL", "INVALID", "VALID") -> VALID | S84: =IF(R84="VALID", IF(AND(J84="NULL",K84="NULL"), "INVALID", "VALID"), "INVALID") -> VALID | T84: =IF(S84="VALID", IF(P84<0, "INVALID", "VALID"), "INVALID") -> VALID | U84: =IF(T84="VALID", IF(Table1[[#This Row],[Quantity]]="NULL", "INVALID", "VALID"), "INVALID") -> VALID | V84: =IF(U84="VALID", "KEEP","DELETE") -> KEEP
F85: ORD1010 | G85: 2025-06-12 | H85: FMCG | I85: ITC | J85: 1423.42 | K85: NULL | L85: 100 | M85: BUY | O85: =IF(LEFT(UPPER(M85),1)="S","SELL",IF(LEFT(UPPER(M85),1)="B","BUY","INVALID")) -> BUY | P85: =IF(L85 = "NULL", 0, IF(AND(I85=I86, H85=H86), P86 + IF(O85="BUY", L85, -L85), IF(O85="BUY", L85, -L85))) -> 285 | Q85: =DATEVALUE(Table1[[#This Row],[Date]]) -> 45820 | R85: =IF(F85="NULL", "INVALID", "VALID") -> VALID | S85: =IF(R85="VALID", IF(AND(J85="NULL",K85="NULL"), "INVALID", "VALID"), "INVALID") -> VALID | T85: =IF(S85="VALID", IF(P85<0, "INVALID", "VALID"), "INVALID") -> VALID | U85: =IF(T85="VALID", IF(Table1[[#This Row],[Quantity]]="NULL", "INVALID", "VALID"), "INVALID") -> VALID | V85: =IF(U85="VALID", "KEEP","DELETE") -> KEEP
F86: ORD1067 | G86: 2025-06-08 | H86: FMCG | I86: ITC | J86: 1334.82 | K86: NULL | L86: 75 | M86: BUY | O86: =IF(LEFT(UPPER(M86),1)="S","SELL",IF(LEFT(UPPER(M86),1)="B","BUY","INVALID")) -> BUY | P86: =IF(L86 = "NULL", 0, IF(AND(I86=I87, H86=H87), P87 + IF(O86="BUY", L86, -L86), IF(O86="BUY", L86, -L86))) -> 185 | Q86: =DATEVALUE(Table1[[#This Row],[Date]]) -> 45816 | R86: =IF(F86="NULL", "INVALID", "VALID") -> VALID | S86: =IF(R86="VALID", IF(AND(J86="NULL",K86="NULL"), "INVALID", "VALID"), "INVALID") -> VALID | T86: =IF(S86="VALID", IF(P86<0, "INVALID", "VALID"), "INVALID") -> VALID | U86: =IF(T86="VALID", IF(Table1[[#This Row],[Quantity]]="NULL", "INVALID", "VALID"), "INVALID") -> VALID | V86: =IF(U86="VALID", "KEEP","DELETE") -> KEEP
F87: ORD1137 | G87: 2025-06-05 | H87: FMCG | I87: ITC | J87: 2019.54 | K87: NULL | L87: 75 | M87: BUY | O87: =IF(LEFT(UPPER(M87),1)="S","SELL",IF(LEFT(UPPER(M87),1)="B","BUY","INVALID")) -> BUY | P87: =IF(L87 = "NULL", 0, IF(AND(I87=I88, H87=H88), P88 + IF(O87="BUY", L87, -L87), IF(O87="BUY", L87, -L87))) -> 110 | Q87: =DATEVALUE(Table1[[#This Row],[Date]]) -> 45813 | R87: =IF(F87="NULL", "INVALID", "VALID") -> VALID | S87: =IF(R87="VALID", IF(AND(J87="NULL",K87="NULL"), "INVALID", "VALID"), "INVALID") -> VALID | T87: =IF(S87="VALID", IF(P87<0, "INVALID", "VALID"), "INVALID") -> VALID | U87: =IF(T87="VALID", IF(Table1[[#This Row],[Quantity]]="NULL", "INVALID", "VALID"), "INVALID") -> VALID | V87: =IF(U87="VALID", "KEEP","DELETE") -> KEEP
F88: ORD1126 | G88: 2025-05-02 | H88: FMCG | I88: ITC | J88: NULL | K88: 2518.37 | L88: 50 | M88: SELL | O88: =IF(LEFT(UPPER(M88),1)="S","SELL",IF(LEFT(UPPER(M88),1)="B","BUY","INVALID")) -> SELL | P88: =IF(L88 = "NULL", 0, IF(AND(I88=I89, H88=H89), P89 + IF(O88="BUY", L88, -L88), IF(O88="BUY", L88, -L88))) -> 35 | Q88: =DATEVALUE(Table1[[#This Row],[Date]]) -> 45779 | R88: =IF(F88="NULL", "INVALID", "VALID") -> VALID | S88: =IF(R88="VALID", IF(AND(J88="NULL",K88="NULL"), "INVALID", "VALID"), "INVALID") -> VALID | T88: =IF(S88="VALID", IF(P88<0, "INVALID", "VALID"), "INVALID") -> VALID | U88: =IF(T88="VALID", IF(Table1[[#This Row],[Quantity]]="NULL", "INVALID", "VALID"), "INVALID") -> VALID | V88: =IF(U88="VALID", "KEEP","DELETE") -> KEEP
F89: ORD1053 | G89: 2025-04-28 | H89: FMCG | I89: ITC | J89: NULL | K89: 1495.42 | L89: 25 | M89: SELL | O89: =IF(LEFT(UPPER(M89),1)="S","SELL",IF(LEFT(UPPER(M89),1)="B","BUY","INVALID")) -> SELL | P89: =IF(L89 = "NULL", 0, IF(AND(I89=I90, H89=H90), P90 + IF(O89="BUY", L89, -L89), IF(O89="BUY", L89, -L89))) -> 85 | Q89: =DATEVALUE(Table1[[#This Row],[Date]]) -> 45775 | R89: =IF(F89="NULL", "INVALID", "VALID") -> VALID | S89: =IF(R89="VALID", IF(AND(J89="NULL",K89="NULL"), "INVALID", "VALID"), "INVALID") -> VALID | T89: =IF(S89="VALID", IF(P89<0, "INVALID", "VALID"), "INVALID") -> VALID | U89: =IF(T89="VALID", IF(Table1[[#This Row],[Quantity]]="NULL", "INVALID", "VALID"), "INVALID") -> VALID | V89: =IF(U89="VALID", "KEEP","DELETE") -> KEEP
F90: ORD1070 | G90: 2025-04-08 | H90: FMCG | I90: ITC | J90: NULL | K90: 768.34 | L90: 10 | M90: SELL | O90: =IF(LEFT(UPPER(M90),1)="S","SELL",IF(LEFT(UPPER(M90),1)="B","BUY","INVALID")) -> SELL | P90: =IF(L90 = "NULL", 0, IF(AND(I90=I91, H90=H91), P91 + IF(O90="BUY", L90, -L90), IF(O90="BUY", L90, -L90))) -> 110 | Q90: =DATEVALUE(Table1[[#This Row],[Date]]) -> 45755 | R90: =IF(F90="NULL", "INVALID", "VALID") -> VALID | S90: =IF(R90="VALID", IF(AND(J90="NULL",K90="NULL"), "INVALID", "VALID"), "INVALID") -> VALID | T90: =IF(S90="VALID", IF(P90<0, "INVALID", "VALID"), "INVALID") -> VALID | U90: =IF(T90="VALID", IF(Table1[[#This Row],[Quantity]]="NULL", "INVALID", "VALID"), "INVALID") -> VALID | V90: =IF(U90="VALID", "KEEP","DELETE") -> KEEP
F91: ORD1179 | G91: 2025-03-01 | H91: FMCG | I91: ITC | J91: NULL | K91: 3343.45 | L91: 15 | M91: SELL | O91: =IF(LEFT(UPPER(M91),1)="S","SELL",IF(LEFT(UPPER(M91),1)="B","BUY","INVALID")) -> SELL | P91: =IF(L91 = "NULL", 0, IF(AND(I91=I92, H91=H92), P92 + IF(O91="BUY", L91, -L91), IF(O91="BUY", L91, -L91))) -> 120 | Q91: =DATEVALUE(Table1[[#This Row],[Date]]) -> 45717 | R91: =IF(F91="NULL", "INVALID", "VALID") -> VALID | S91: =IF(R91="VALID", IF(AND(J91="NULL",K91="NULL"), "INVALID", "VALID"), "INVALID") -> VALID | T91: =IF(S91="VALID", IF(P91<0, "INVALID", "VALID"), "INVALID") -> VALID | U91: =IF(T91="VALID", IF(Table1[[#This Row],[Quantity]]="NULL", "INVALID", "VALID"), "INVALID") -> VALID | V91: =IF(U91="VALID", "KEEP","DELETE") -> KEEP
F92: ORD1044 | G92: 2025-02-24 | H92: FMCG | I92: ITC | J92: 1511.49 | K92: NULL | L92: 100 | M92: BUY | O92: =IF(LEFT(UPPER(M92),1)="S","SELL",IF(LEFT(UPPER(M92),1)="B","BUY","INVALID")) -> BUY | P92: =IF(L92 = "NULL", 0, IF(AND(I92=I93, H92=H93), P93 + IF(O92="BUY", L92, -L92), IF(O92="BUY", L92, -L92))) -> 135 | Q92: =DATEVALUE(Table1[[#This Row],[Date]]) -> 45712 | R92: =IF(F92="NULL", "INVALID", "VALID") -> VALID | S92: =IF(R92="VALID", IF(AND(J92="NULL",K92="NULL"), "INVALID", "VALID"), "INVALID") -> VALID | T92: =IF(S92="VALID", IF(P92<0, "INVALID", "VALID"), "INVALID") -> VALID | U92: =IF(T92="VALID", IF(Table1[[#This Row],[Quantity]]="NULL", "INVALID", "VALID"), "INVALID") -> VALID | V92: =IF(U92="VALID", "KEEP","DELETE") -> KEEP
F93: ORD1041 | G93: 2025-02-05 | H93: FMCG | I93: ITC | J93: 787.2 | K93: NULL | L93: 100 | M93: BUY | O93: =IF(LEFT(UPPER(M93),1)="S","SELL",IF(LEFT(UPPER(M93),1)="B","BUY","INVALID")) -> BUY | P93: =IF(L93 = "NULL", 0, IF(AND(I93=I94, H93=H94), P94 + IF(O93="BUY", L93, -L93), IF(O93="BUY", L93, -L93))) -> 35 | Q93: =DATEVALUE(Table1[[#This Row],[Date]]) -> 45693 | R93: =IF(F93="NULL", "INVALID", "VALID") -> VALID | S93: =IF(R93="VALID", IF(AND(J93="NULL",K93="NULL"), "INVALID", "VALID"), "INVALID") -> VALID | T93: =IF(S93="VALID", IF(P93<0, "INVALID", "VALID"), "INVALID") -> VALID | U93: =IF(T93="VALID", IF(Table1[[#This Row],[Quantity]]="NULL", "INVALID", "VALID"), "INVALID") -> VALID | V93: =IF(U93="VALID", "KEEP","DELETE") -> KEEP
F94: ORD1019 | G94: 2025-01-13 | H94: FMCG | I94: ITC | J94: 1856.91 | K94: NULL | L94: 10 | M94: BUY | O94: =IF(LEFT(UPPER(M94),1)="S","SELL",IF(LEFT(UPPER(M94),1)="B","BUY","INVALID")) -> BUY | P94: =IF(L94 = "NULL", 0, IF(AND(I94=I95, H94=H95), P95 + IF(O94="BUY", L94, -L94), IF(O94="BUY", L94, -L94))) -> -65 | Q94: =DATEVALUE(Table1[[#This Row],[Date]]) -> 45670 | R94: =IF(F94="NULL", "INVALID", "VALID") -> VALID | S94: =IF(R94="VALID", IF(AND(J94="NULL",K94="NULL"), "INVALID", "VALID"), "INVALID") -> VALID | T94: =IF(S94="VALID", IF(P94<0, "INVALID", "VALID"), "INVALID") -> INVALID | U94: =IF(T94="VALID", IF(Table1[[#This Row],[Quantity]]="NULL", "INVALID", "VALID"), "INVALID") -> INVALID | V94: =IF(U94="VALID", "KEEP","DELETE") -> DELETE
F95: ORD1167 | G95: 2025-01-12 | H95: FMCG | I95: ITC | J95: NULL | K95: 945.15 | L95: 75 | M95: SELL | O95: =IF(LEFT(UPPER(M95),1)="S","SELL",IF(LEFT(UPPER(M95),1)="B","BUY","INVALID")) -> SELL | P95: =IF(L95 = "NULL", 0, IF(AND(I95=I96, H95=H96), P96 + IF(O95="BUY", L95, -L95), IF(O95="BUY", L95, -L95))) -> -75 | Q95: =DATEVALUE(Table1[[#This Row],[Date]]) -> 45669 | R95: =IF(F95="NULL", "INVALID", "VALID") -> VALID | S95: =IF(R95="VALID", IF(AND(J95="NULL",K95="NULL"), "INVALID", "VALID"), "INVALID") -> VALID | T95: =IF(S95="VALID", IF(P95<0, "INVALID", "VALID"), "INVALID") -> INVALID | U95: =IF(T95="VALID", IF(Table1[[#This Row],[Quantity]]="NULL", "INVALID", "VALID"), "INVALID") -> INVALID | V95: =IF(U95="VALID", "KEEP","DELETE") -> DELETE
F96: ORD1147 | G96: 2025-06-26 | H96: Banking | I96: KOTAKBANK | J96: NULL | K96: 1638.7 | L96: 100 | M96: SELL | O96: =IF(LEFT(UPPER(M96),1)="S","SELL",IF(LEFT(UPPER(M96),1)="B","BUY","INVALID")) -> SELL | P96: =IF(L96 = "NULL", 0, IF(AND(I96=I97, H96=H97), P97 + IF(O96="BUY", L96, -L96), IF(O96="BUY", L96, -L96))) -> 20 | Q96: =DATEVALUE(Table1[[#This Row],[Date]]) -> 45834 | R96: =IF(F96="NULL", "INVALID", "VALID") -> VALID | S96: =IF(R96="VALID", IF(AND(J96="NULL",K96="NULL"), "INVALID", "VALID"), "INVALID") -> VALID | T96: =IF(S96="VALID", IF(P96<0, "INVALID", "VALID"), "INVALID") -> VALID | U96: =IF(T96="VALID", IF(Table1[[#This Row],[Quantity]]="NULL", "INVALID", "VALID"), "INVALID") -> VALID | V96: =IF(U96="VALID", "KEEP","DELETE") -> KEEP
F97: ORD1060 | G97: 2025-06-25 | H97: Banking | I97: KOTAKBANK | J97: 2554 | K97: NULL | L97: 20 | M97: BUY | O97: =IF(LEFT(UPPER(M97),1)="S","SELL",IF(LEFT(UPPER(M97),1)="B","BUY","INVALID")) -> BUY | P97: =IF(L97 = "NULL", 0, IF(AND(I97=I98, H97=H98), P98 + IF(O97="BUY", L97, -L97), IF(O97="BUY", L97, -L97))) -> 120 | Q97: =DATEVALUE(Table1[[#This Row],[Date]]) -> 45833 | R97: =IF(F97="NULL", "INVALID", "VALID") -> VALID | S97: =IF(R97="VALID", IF(AND(J97="NULL",K97="NULL"), "INVALID", "VALID"), "INVALID") -> VALID | T97: =IF(S97="VALID", IF(P97<0, "INVALID", "VALID"), "INVALID") -> VALID | U97: =IF(T97="VALID", IF(Table1[[#This Row],[Quantity]]="NULL", "INVALID", "VALID"), "INVALID") -> VALID | V97: =IF(U97="VALID", "KEEP","DELETE") -> KEEP
F98: ORD1095 | G98: 2025-05-19 | H98: Banking | I98: KOTAKBANK | J98: 1060.25 | K98: NULL | L98: 50 | M98: BUY | O98: =IF(LEFT(UPPER(M98),1)="S","SELL",IF(LEFT(UPPER(M98),1)="B","BUY","INVALID")) -> BUY | P98: =IF(L98 = "NULL", 0, IF(AND(I98=I99, H98=H99), P99 + IF(O98="BUY", L98, -L98), IF(O98="BUY", L98, -L98))) -> 100 | Q98: =DATEVALUE(Table1[[#This Row],[Date]]) -> 45796 | R98: =IF(F98="NULL", "INVALID", "VALID") -> VALID | S98: =IF(R98="VALID", IF(AND(J98="NULL",K98="NULL"), "INVALID", "VALID"), "INVALID") -> VALID | T98: =IF(S98="VALID", IF(P98<0, "INVALID", "VALID"), "INVALID") -> VALID | U98: =IF(T98="VALID", IF(Table1[[#This Row],[Quantity]]="NULL", "INVALID", "VALID"), "INVALID") -> VALID | V98: =IF(U98="VALID", "KEEP","DELETE") -> KEEP
F99: ORD1165 | G99: 2025-05-18 | H99: Banking | I99: KOTAKBANK | J99: NULL | K99: 3191.51 | L99: 100 | M99: Sl | O99: =IF(LEFT(UPPER(M99),1)="S","SELL",IF(LEFT(UPPER(M99),1)="B","BUY","INVALID")) -> SELL | P99: =IF(L99 = "NULL", 0, IF(AND(I99=I100, H99=H100), P100 + IF(O99="BUY", L99, -L99), IF(O99="BUY", L99, -L99))) -> 50 | Q99: =DATEVALUE(Table1[[#This Row],[Date]]) -> 45795 | R99: =IF(F99="NULL", "INVALID", "VALID") -> VALID | S99: =IF(R99="VALID", IF(AND(J99="NULL",K99="NULL"), "INVALID", "VALID"), "INVALID") -> VALID | T99: =IF(S99="VALID", IF(P99<0, "INVALID", "VALID"), "INVALID") -> VALID | U99: =IF(T99="VALID", IF(Table1[[#This Row],[Quantity]]="NULL", "INVALID", "VALID"), "INVALID") -> VALID | V99: =IF(U99="VALID", "KEEP","DELETE") -> KEEP
F100: ORD1072 | G100: 2025-04-13 | H100: Banking | I100: KOTAKBANK | J100: 896.79 | K100: NULL | L100: 20 | M100: BUY | O100: =IF(LEFT(UPPER(M100),1)="S","SELL",IF(LEFT(UPPER(M100),1)="B","BUY","INVALID")) -> BUY | P100: =IF(L100 = "NULL", 0, IF(AND(I100=I101, H100=H101), P101 + IF(O100="BUY", L100, -L100), IF(O100="BUY", L100, -L100))) -> 150 | Q100: =DATEVALUE(Table1[[#This Row],[Date]]) -> 45760 | R100: =IF(F100="NULL", "INVALID", "VALID") -> VALID | S100: =IF(R100="VALID", IF(AND(J100="NULL",K100="NULL"), "INVALID", "VALID"), "INVALID") -> VALID | T100: =IF(S100="VALID", IF(P100<0, "INVALID", "VALID"), "INVALID") -> VALID | U100: =IF(T100="VALID", IF(Table1[[#This Row],[Quantity]]="NULL", "INVALID", "VALID"), "INVALID") -> VALID | V100: =IF(U100="VALID", "KEEP","DELETE") -> KEEP
F101: ORD1066 | G101: 2025-04-02 | H101: Banking | I101: KOTAKBANK | J101: NULL | K101: 3136.34 | L101: 5 | M101: SELL | O101: =IF(LEFT(UPPER(M101),1)="S","SELL",IF(LEFT(UPPER(M101),1)="B","BUY","INVALID")) -> SELL | P101: =IF(L101 = "NULL", 0, IF(AND(I101=I102, H101=H102), P102 + IF(O101="BUY", L101, -L101), IF(O101="BUY", L101, -L101))) -> 130 | Q101: =DATEVALUE(Table1[[#This Row],[Date]]) -> 45749 | R101: =IF(F101="NULL", "INVALID", "VALID") -> VALID | S101: =IF(R101="VALID", IF(AND(J101="NULL",K101="NULL"), "INVALID", "VALID"), "INVALID") -> VALID | T101: =IF(S101="VALID", IF(P101<0, "INVALID", "VALID"), "INVALID") -> VALID | U101: =IF(T101="VALID", IF(Table1[[#This Row],[Quantity]]="NULL", "INVALID", "VALID"), "INVALID") -> VALID | V101: =IF(U101="VALID", "KEEP","DELETE") -> KEEP
F102: ORD1115 | G102: 2025-03-30 | H102: Banking | I102: KOTAKBANK | J102: 2817.36 | K102: NULL | L102: 5 | M102: BUY | O102: =IF(LEFT(UPPER(M102),1)="S","SELL",IF(LEFT(UPPER(M102),1)="B","BUY","INVALID")) -> BUY | P102: =IF(L102 = "NULL", 0, IF(AND(I102=I103, H102=H103), P103 + IF(O102="BUY", L102, -L102), IF(O102="BUY", L102, -L102))) -> 135 | Q102: =DATEVALUE(Table1[[#This Row],[Date]]) -> 45746 | R102: =IF(F102="NULL", "INVALID", "VALID") -> VALID | S102: =IF(R102="VALID", IF(AND(J102="NULL",K102="NULL"), "INVALID", "VALID"), "INVALID") -> VALID | T102: =IF(S102="VALID", IF(P102<0, "INVALID", "VALID"), "INVALID") -> VALID | U102: =IF(T102="VALID", IF(Table1[[#This Row],[Quantity]]="NULL", "INVALID", "VALID"), "INVALID") -> VALID | V102: =IF(U102="VALID", "KEEP","DELETE") -> KEEP
F103: ORD1182 | G103: 2025-03-19 | H103: Banking | I103: KOTAKBANK | J103: NULL | K103: 2437.54 | L103: 100 | M103: by | O103: =IF(LEFT(UPPER(M103),1)="S","SELL",IF(LEFT(UPPER(M103),1)="B","BUY","INVALID")) -> BUY | P103: =IF(L103 = "NULL", 0, IF(AND(I103=I104, H103=H104), P104 + IF(O103="BUY", L103, -L103), IF(O103="BUY", L103, -L103))) -> 130 | Q103: =DATEVALUE(Table1[[#This Row],[Date]]) -> 45735 | R103: =IF(F103="NULL", "INVALID", "VALID") -> VALID | S103: =IF(R103="VALID", IF(AND(J103="NULL",K103="NULL"), "INVALID", "VALID"), "INVALID") -> VALID | T103: =IF(S103="VALID", IF(P103<0, "INVALID", "VALID"), "INVALID") -> VALID | U103: =IF(T103="VALID", IF(Table1[[#This Row],[Quantity]]="NULL", "INVALID", "VALID"), "INVALID") -> VALID | V103: =IF(U103="VALID", "KEEP","DELETE") -> KEEP
F104: ORD1176 | G104: 2025-03-17 | H104: Banking | I104: KOTAKBANK | J104: 304.07 | K104: NULL | L104: 5 | M104: BUY | O104: =IF(LEFT(UPPER(M104),1)="S","SELL",IF(LEFT(UPPER(M104),1)="B","BUY","INVALID")) -> BUY | P104: =IF(L104 = "NULL", 0, IF(AND(I104=I105, H104=H105), P105 + IF(O104="BUY", L104, -L104), IF(O104="BUY", L104, -L104))) -> 30 | Q104: =DATEVALUE(Table1[[#This Row],[Date]]) -> 45733 | R104: =IF(F104="NULL", "INVALID", "VALID") -> VALID | S104: =IF(R104="VALID", IF(AND(J104="NULL",K104="NULL"), "INVALID", "VALID"), "INVALID") -> VALID | T104: =IF(S104="VALID", IF(P104<0, "INVALID", "VALID"), "INVALID") -> VALID | U104: =IF(T104="VALID", IF(Table1[[#This Row],[Quantity]]="NULL", "INVALID", "VALID"), "INVALID") -> VALID | V104: =IF(U104="VALID", "KEEP","DELETE") -> KEEP
F105: ORD1184 | G105: 2025-03-12 | H105: Banking | I105: KOTAKBANK | J105: NULL | K105: 212.68 | L105: 75 | M105: SELL | O105: =IF(LEFT(UPPER(M105),1)="S","SELL",IF(LEFT(UPPER(M105),1)="B","BUY","INVALID")) -> SELL | P105: =IF(L105 = "NULL", 0, IF(AND(I105=I106, H105=H106), P106 + IF(O105="BUY", L105, -L105), IF(O105="BUY", L105, -L105))) -> 25 | Q105: =DATEVALUE(Table1[[#This Row],[Date]]) -> 45728 | R105: =IF(F105="NULL", "INVALID", "VALID") -> VALID | S105: =IF(R105="VALID", IF(AND(J105="NULL",K105="NULL"), "INVALID", "VALID"), "INVALID") -> VALID | T105: =IF(S105="VALID", IF(P105<0, "INVALID", "VALID"), "INVALID") -> VALID | U105: =IF(T105="VALID", IF(Table1[[#This Row],[Quantity]]="NULL", "INVALID", "VALID"), "INVALID") -> VALID | V105: =IF(U105="VALID", "KEEP","DELETE") -> KEEP
F106: ORD1058 | G106: 2025-03-09 | H106: Banking | I106: KOTAKBANK | J106: 3295.42 | K106: NULL | L106: 15 | M106: BUY | O106: =IF(LEFT(UPPER(M106),1)="S","SELL",IF(LEFT(UPPER(M106),1)="B","BUY","INVALID")) -> BUY | P106: =IF(L106 = "NULL", 0, IF(AND(I106=I107, H106=H107), P107 + IF(O106="BUY", L106, -L106), IF(O106="BUY", L106, -L106))) -> 100 | Q106: =DATEVALUE(Table1[[#This Row],[Date]]) -> 45725 | R106: =IF(F106="NULL", "INVALID", "VALID") -> VALID | S106: =IF(R106="VALID", IF(AND(J106="NULL",K106="NULL"), "INVALID", "VALID"), "INVALID") -> VALID | T106: =IF(S106="VALID", IF(P106<0, "INVALID", "VALID"), "INVALID") -> VALID | U106: =IF(T106="VALID", IF(Table1[[#This Row],[Quantity]]="NULL", "INVALID", "VALID"), "INVALID") -> VALID | V106: =IF(U106="VALID", "KEEP","DELETE") -> KEEP
...

Sheet Data Cleaning Process
G1: 📈 STOCK MARKET PORTFOLIO TRACKER & RETURN ANALYZER
H11: DATASET OVERVIEW
H12: Metric | I12: Detail / Value | M12: Notes
H13: Source Sheet | I13: Raw Order_List | M13: Original unprocessed trading order records
H14: Output Sheet | I14: Cleaned_Order_List | M14: Validated, clean records ready for analysis
H15: Raw Total Rows | I15: 203 data rows (excl. header) | M15: All orders before any cleaning applied
H16: Cleaned Rows Retained | I16: 137 rows (KEEP decision) | M16: 54 rows removed via DELETE; some rows fully filtered
H17: Stocks Covered | I17: 21 stocks across 13 sectors | M17: ASIANPAINT, AXISBANK, BAJFINANCE … WIPRO etc.
H18: Raw Columns (Input) | I18: Order_ID · Date · Sector · Stock_Name Buy_Price · Sell_Price · Quantity · Order_Type | M18: 8 core input columns
H19: Helper Columns Added (Raw Sheet) | I19: Cleaned_Order_Type · Curr_Hold · Date_format Reason_1 · Reason_2 · Reason_3 · Reason_4 · Decision | M19: 8 columns documenting every cleaning decision
H20: Cleaned Output Columns | I20: Order_ID · Date · Sector · Stock_Name · Buy_Price Sell_Price · Quantity · Order_Type · Curr_holding · BP*Qty | M20: 10 final columns incl. 2 newly derived
H23: RAW DATA QUALITY ISSUES IDENTIFIED
H24: Sl No | I24: Issue / Problem | J24: Description & Real Examples from Data | M24: Column(s)
H25: 1 | I25: Misspelled / Inconsistent Order Types | J25: Order_Type contained 12+ non-standard variants instead of clean BUY/SELL: "B" (ORD1076) · "Buy" (ORD1073) · "BUYY" (ORD1011) · "buy" (ORD1124) "BuY" (ORD1191) · "Bub" (ORD1135) · "by" (ORD1169) "SEL" (ORD1057) · "Sell" (ORD1098) · "SELLA" (ORD1079) · "Sl" (ORD1141) · "sale" (ORD1120) | K25: Order_Type | L25: 12 variants | M25: Cleaned_ Order_Type
H26: 2 | I26: "NULL" Text Strings in Price Columns | J26: Buy_Price and/or Sell_Price stored as the literal text "NULL" rather than a blank. Makes numeric operations (SUM, AVG, VLOOKUP) fail completely. Expected: BUY orders → Buy_Price numeric, Sell_Price blank (and vice-versa). | K26: Buy_Price Sell_Price | L26: 94 Buy NULLs 106 Sell NULLs | M26: Reason_2
H27: 3 | I27: Both Prices Missing Simultaneously | J27: Three specific rows had "NULL" in BOTH Buy_Price AND Sell_Price: ORD1148 (MARUTI · SELL · Qty 80) NULL Order_ID (Finance · SELL · Qty 20) NULL Order_ID (SUNPHARMA · buy · Qty NULL) Record is financially meaningless without any price. | K27: Buy_Price & Sell_Price | L27: 3 rows | M27: Reason_2 → INVALID
H28: 4 | I28: Date Stored as Plain Text String | J28: All Date values stored as text strings e.g. "2025-04-09" instead of proper Excel date serial numbers. Prevents date arithmetic, chronological sorting, and timeline-based analysis. Converted values stored in new Date_format column as datetime objects. | K28: Date | L28: All 203 rows | M28: Date_format column
H29: 5 | I29: Negative Cumulative Holdings (Oversell) | J29: Curr_Hold tracks running cumulative quantity per stock (date-ordered). When a SELL makes Curr_Hold < 0, it means selling shares never purchased. Examples: ORD1079 (ASIANPAINT → −10) · ORD1005 (ASIANPAINT → −50) All 9 BHARTIARTL orders · All 11 HDFCBANK orders become negative. | K29: Derived: Curr_Hold | L29: 53 rows | M29: Reason_3 → INVALID
H30: 6 | I30: Missing / NULL Order_ID | J30: Two rows had Order_ID = "NULL" — completely untraceable, unauditable orders. One NULL row also had NULL Stock_Name; another was for SUNPHARMA. | K30: Order_ID | L30: 2 rows | M30: Reason_1 → INVALID
H31: 7 | I31: Missing Quantity | J31: One row (NULL Order_ID · SUNPHARMA · "buy") had Quantity = "NULL". Cannot calculate position size, trade value, or holdings without quantity. | K31: Quantity | L31: 1 row | M31: Reason_4 → INVALID
H35: 3 › STEP-BY-STEP CLEANING PROCESS APPLIED
H36: Step | I36: Action Taken | J36: Rule / Logic Applied | L36: Raw Value (Before) | M36: Clean Value (After) | N36: Helper Column
H37: 1 | I37: Standardise Order Type | J37: All Order_Type variants mapped to canonical BUY or SELL using case-insensitive pattern matching: "B","Buy","buy","BuY","Bub","BUYY","by" → BUY "Sell","SEL","SELLA","Sl","sale" → SELL Result stored in Cleaned_Order_Type column (raw value preserved). | L37: "B","BUYY","by" "SEL","Sl","sale" | M37: "BUY" or "SELL" (uniform uppercase) | N37: Cleaned_Order_Type "Resolved Mistyped Values"
H38: 2 | I38: Replace NULL Strings with Blank Cells | J38: Text "NULL" in Buy_Price / Sell_Price replaced with empty cells. BUY orders → Buy_Price = numeric value, Sell_Price = blank SELL orders → Sell_Price = numeric value, Buy_Price = blank Enables numeric formulas, aggregations and filters to function. | L38: Buy_Price = "NULL" or Sell_Price = "NULL" | M38: Blank cell or actual numeric price value | N38: — (applied in-place in price columns)
H39: 3 | I39: Convert Date Text to Excel Date Format | J39: Date column stored as plain text strings ("2025-04-09"). Converted to proper Excel datetime serial values via DATEVALUE(). Enables chronological sorting, date filtering, day-count arithmetic. Stored in Date_format column; used in Cleaned sheet. | L39: "2025-04-09" (text string) | M39: datetime(2025,4,9) = serial 45756 = Apr 09 2025 | N39: Date_format "Converted text to Actual Date format"
H40: 4 | I40: Flag Missing Order_ID (Reason_1) | J40: Check: IF Order_ID = "NULL" OR blank → Reason_1 = "INVALID" Else → Reason_1 = "VALID" Orders without an ID are untraceable and unauditable. | L40: Order_ID = "NULL" or blank | M40: Reason_1 = "INVALID" → Decision = DELETE | N40: Reason_1 "Order_ID Missing"
H41: 5 | I41: Flag Both-Prices- Missing (Reason_2) | J41: Check: IF Buy_Price = "NULL" AND Sell_Price = "NULL" → Reason_2 = "INVALID" A record with no price data has zero financial value. Single-price missing is acceptable (BUY has Buy_Price, SELL has Sell_Price). | L41: Buy_Price="NULL" AND Sell_Price="NULL" | M41: Reason_2 = "INVALID" → Decision = DELETE | N41: Reason_2 "Both Buy_Price & Sell_Price Missing"
H42: 6 | I42: Flag Oversell / Negative Holdings (Reason_3) | J42: Curr_Hold = running cumulative Quantity per stock (date-ascending order): +Qty for BUY orders, −Qty for SELL orders IF Curr_Hold < 0 → Reason_3 = "INVALID" (selling shares never owned) E.g. BHARTIARTL and HDFCBANK had negative holdings from the very first trade. | L42: SELL reduces Curr_Hold below 0 | M42: Reason_3 = "INVALID" → Decision = DELETE | N42: Reason_3 "Cannot SELL before BUYING"
H43: 7 | I43: Flag Missing Quantity (Reason_4) | J43: Check: IF Quantity = "NULL" OR blank → Reason_4 = "INVALID" Without quantity, position size, trade value (BP*Qty), and Curr_Hold cannot be computed. NOTE: Reason_4 co-fires with Reason_3 on all 54 delete rows (cascade effect — negative holding also implies qty problem). | L43: Quantity = "NULL" or blank | M43: Reason_4 = "INVALID" → Decision = DELETE | N43: Reason_4 "Quantity Missing"
H44: 8 | I44: Apply Final Decision & Build Cleaned Sheet | J44: Decision = "KEEP" if ALL of Reason_1–4 = "VALID" Decision = "DELETE" if ANY Reason = "INVALID" KEEP rows copied to Cleaned_Order_List sheet. Two new columns added in cleaned sheet: • Curr_holding — recalculated cumulative qty on clean rows only • BP*Qty — Buy_Price × Quantity (trade cost value for BUY orders) | L44: 203 raw records with quality issues present | M44: 137 clean records with BP*Qty added | N44: Decision (KEEP / DELETE)
H49: VALIDATION RULE MATRIX — Reason Columns & Decision Logic
H50: Reason Col | I50: Checks For | J50: "VALID" Condition | L50: "INVALID" Condition | M50: Rows Flagged | N50: Impact on Decision
H51: Reason_1 | I51: Order_ID present | J51: Order_ID is non-NULL and non-blank | L51: Order_ID = "NULL" or missing | M51: 2 rows | N51: → DELETE
H52: Reason_2 | I52: Price data present | J52: At least one price column has a numeric value | L52: Both Buy_Price AND Sell_Price = "NULL" | M52: 3 rows | N52: → DELETE
H53: Reason_3 | I53: Holdings non-negative | J53: Cumulative Curr_Hold ≥ 0 after applying this trade | L53: Curr_Hold < 0 (oversell detected) | M53: 53 rows | N53: → DELETE
H54: Reason_4 | I54: Quantity present | J54: Quantity is a valid non-NULL numeric value | L54: Quantity = "NULL" or blank | M54: 54 rows* | N54: → DELETE
H55: Decision | I55: Final verdict | J55: ALL 4 Reasons = "VALID" → "KEEP" | L55: ANY Reason = "INVALID" → "DELETE" | M55: 54 DELETE 149 KEEP | N55: Copied to Cleaned sheet
H63: BEFORE vs AFTER — REAL SAMPLE ROW COMPARISONS
H64: RAW DATA (issues present) | L64: ✔ AFTER CLEANING
H65: Order_ID | I65: Order_Type (Raw) | J65: Date (Raw) | K65: Decision | L65: Order_Type (Clean) | M65: Date (Clean) | N65: Issue Fixed / Reason
H66: ORD1076 | I66: B (typo) | J66: 2025-04-09 (text) | K66: KEEP ✔ | L66: BUY | M66: Apr 09 2025 (date serial) | N66: Order_Type "B" → BUY
H67: ORD1011 | I67: BUYY (typo) | J67: 2025-06-21 (text) | K67: KEEP ✔ | L67: BUY | M67: Jun 21 2025 (date serial) | N67: Order_Type "BUYY" → BUY
H68: ORD1120 | I68: sale (typo) | J68: 2025-04-29 (text) | K68: KEEP ✔ | L68: SELL | M68: Apr 29 2025 (date serial) | N68: Order_Type "sale" → SELL
H69: ORD1079 | I69: SELLA (typo) | J69: 2025-03-18 (text) | K69: DELETE ✘ | L69: — | M69: — | N69: Neg. holding (−10) · R3=INVALID
H70: ORD1141 | I70: Sl (typo) | J70: 2025-03-03 (text) | K70: DELETE ✘ | L70: — | M70: — | N70: Neg. holding (−120) · R3=INVALID
H71: NULL | I71: SELL | J71: 2025-03-13 (text) | K71: DELETE ✘ | L71: — | M71: — | N71: Missing Order_ID + both prices NULL
H72: ORD1148 | I72: SELL | J72: 2025-04-23 (text) | K72: DELETE ✘ | L72: — | M72: — | N72: Both Buy_Price & Sell_Price = NULL
H80: NEW & DERIVED COLUMNS ADDED DURING CLEANING
H81: Column Name | I81: Sheet | J81: Formula / Derivation Logic | M81: Purpose
H82: Cleaned_Order_Type | I82: Raw Order_List | J82: UPPER pattern-match on Order_Type: "B/Buy/buy/BuY/Bub/BUYY/by" → "BUY" | "Sell/SEL/SELLA/Sl/sale" → "SELL" | M82: Uniform BUY/SELL field for all downstream logic and the cleaned sheet
H83: Curr_Hold | I83: Raw Order_List | J83: Per-stock cumulative sum sorted by Date ascending: IF(Order_Type="BUY", +Qty, −Qty) running total restarted per stock | M83: Track running inventory; detect oversell (Reason_3 check)
H84: Date_format | I84: Raw Order_List | J84: DATEVALUE(Date) — converts text "YYYY-MM-DD" to Excel date serial e.g. "2025-04-09" → 45756 → displays as Apr 09 2025 | M84: Enable proper date sorting, filtering, timeline analysis
H85: Reason_1 | I85: Raw Order_List | J85: IF(OR(Order_ID="NULL", Order_ID=""), "INVALID", "VALID") | M85: Flag records with untraceable / unauditable missing Order_ID
H86: Reason_2 | I86: Raw Order_List | J86: IF(AND(Buy_Price="NULL", Sell_Price="NULL"), "INVALID", "VALID") | M86: Flag records where both prices are absent (no financial value)
H87: Reason_3 | I87: Raw Order_List | J87: IF(Curr_Hold < 0, "INVALID", "VALID") | M87: Flag records causing impossible negative stock holdings (oversell)
H88: Reason_4 | I88: Raw Order_List | J88: IF(OR(Quantity="NULL", Quantity=""), "INVALID", "VALID") | M88: Flag records where trade quantity is missing (position size unknown)
H89: Decision | I89: Raw Order_List | J89: IF(AND(Reason_1="VALID", Reason_2="VALID", Reason_3="VALID", Reason_4="VALID"), "KEEP", "DELETE") | M89: Final verdict; only KEEP rows are copied to Cleaned_Order_List
H90: Curr_holding | I90: Cleaned_Order_List | J90: Same cumulative qty logic as Curr_Hold but recalculated on KEEP rows only (negative-holding rows already excluded) | M90: Final per-stock portfolio position after full cleaning
H91: BP*Qty | I91: Cleaned_Order_List | J91: IF(Order_Type="BUY", Buy_Price × Quantity, "") — blank for SELL orders | M91: Trade cost value for BUY orders; feeds Total_Investment in portfolio sheet
H100: CLEANING SUMMARY — RECORDS DISPOSITION & ISSUE COUNTS
H101: Category | J101: Count | K101: Pct of Raw | L101: Notes
H102: Total Raw Records | J102: 203 | K102: 100 % | L102: All records in Raw Order_List (excluding header row)
H103: Records Retained (KEEP) | J103: 149 | K103: 73.4 % | L103: Passed all 4 validation rules → copied to Cleaned_Order_List
H104: Records Removed (DELETE) | J104: 54 | K104: 26.6 % | L104: Failed ≥ 1 validation rule → excluded from cleaned data
H105: Order_Type variants found | J105: 14 | K105: — | L105: 12 non-standard variants standardised to BUY / SELL
H106: Rows with NULL Buy_Price | J106: 94 | K106: 46.3 % | L106: Text "NULL" replaced with blank; numeric value in Sell_Price
H107: Rows with NULL Sell_Price | J107: 106 | K107: 52.2 % | L107: Text "NULL" replaced with blank; numeric value in Buy_Price
H108: Rows with BOTH prices NULL | J108: 3 | K108: 1.5 % | L108: Reason_2 = INVALID → DELETE
H109: Rows with negative holdings | J109: 53 | K109: 26.1 % | L109: Cannot SELL before BUYING → Reason_3 = INVALID → DELETE
H110: Rows with missing Order_ID | J110: 2 | K110: 1.0 % | L110: Untraceable orders → Reason_1 = INVALID → DELETE
H111: Rows with missing Quantity | J111: 1 | K111: 0.5 % | L111: Unknown position size → Reason_4 = INVALID → DELETE
H112: New helper columns added (Raw sheet) | J112: 8 | K112: — | L112: Cleaned_Order_Type, Curr_Hold, Date_format, Reason_1–4, Decision
H113: New derived columns (Cleaned sheet) | J113: 2 | K113: — | L113: Curr_holding, BP*Qty

Sheet Cleaned Data
H1: 📈 STOCK MARKET PORTFOLIO TRACKER & RETURN ANALYZER
H6: Cleaned Data
H11: Order_ID | I11: Date | J11: Sector | K11: Stock_Name | L11: Buy_Price | M11: Sell_Price | N11: Quantity | O11: Order_Type | P11: Curr_holding | Q11: BP*Qty
H12: ORD1076 | I12: 45756 | J12: Paints | K12: ASIANPAINT | L12: 2464.09 | N12: 10 | O12: BUY | P12: =IF(J12=J13, P13 + IF(O12="BUY", N12, -N12), IF(O12="BUY", N12, -N12)) -> 35 | Q12: =IF(orderTable[[#This Row],[Buy_Price]]<>"",ROUND(IF(orderTable[[#This Row],[Order_Type]]="BUY",orderTable[[#This Row],[Buy_Price]]*orderTable[[#This Row],[Quantity]],""),2), "") -> 24640.9
H13: ORD1073 | I13: 45747 | J13: Paints | K13: ASIANPAINT | M13: 3284.04 | N13: 25 | O13: SELL | P13: =IF(J13=J14, P14 + IF(O13="BUY", N13, -N13), IF(O13="BUY", N13, -N13)) -> 25 | Q13: =IF(orderTable[[#This Row],[Buy_Price]]<>"",ROUND(IF(orderTable[[#This Row],[Order_Type]]="BUY",orderTable[[#This Row],[Buy_Price]]*orderTable[[#This Row],[Quantity]],""),2), "")
H14: ORD1166 | I14: 45706 | J14: Paints | K14: ASIANPAINT | L14: 1920.27 | N14: 50 | O14: BUY | P14: =IF(J14=J15, P15 + IF(O14="BUY", N14, -N14), IF(O14="BUY", N14, -N14)) -> 50 | Q14: =IF(orderTable[[#This Row],[Buy_Price]]<>"",ROUND(IF(orderTable[[#This Row],[Order_Type]]="BUY",orderTable[[#This Row],[Buy_Price]]*orderTable[[#This Row],[Quantity]],""),2), "") -> 96013.5
H15: ORD1186 | I15: 45831 | J15: Banking | K15: AXISBANK | L15: 2282.67 | N15: 25 | O15: BUY | P15: =IF(J15=J16, P16 + IF(O15="BUY", N15, -N15), IF(O15="BUY", N15, -N15)) -> 50 | Q15: =IF(orderTable[[#This Row],[Buy_Price]]<>"",ROUND(IF(orderTable[[#This Row],[Order_Type]]="BUY",orderTable[[#This Row],[Buy_Price]]*orderTable[[#This Row],[Quantity]],""),2), "") -> 57066.75
H16: ORD1011 | I16: 45829 | J16: Banking | K16: AXISBANK | L16: 1390.11 | N16: 20 | O16: BUY | P16: =IF(J16=J17, P17 + IF(O16="BUY", N16, -N16), IF(O16="BUY", N16, -N16)) -> 25 | Q16: =IF(orderTable[[#This Row],[Buy_Price]]<>"",ROUND(IF(orderTable[[#This Row],[Order_Type]]="BUY",orderTable[[#This Row],[Buy_Price]]*orderTable[[#This Row],[Quantity]],""),2), "") -> 27802.2
H17: ORD1122 | I17: 45800 | J17: Banking | K17: AXISBANK | M17: 1228.25 | N17: 25 | O17: SELL | P17: =IF(J17=J18, P18 + IF(O17="BUY", N17, -N17), IF(O17="BUY", N17, -N17)) -> 5 | Q17: =IF(orderTable[[#This Row],[Buy_Price]]<>"",ROUND(IF(orderTable[[#This Row],[Order_Type]]="BUY",orderTable[[#This Row],[Buy_Price]]*orderTable[[#This Row],[Quantity]],""),2), "")
H18: ORD1177 | I18: 45793 | J18: Banking | K18: AXISBANK | M18: 1644.42 | N18: 20 | O18: SELL | P18: =IF(J18=J19, P19 + IF(O18="BUY", N18, -N18), IF(O18="BUY", N18, -N18)) -> 30 | Q18: =IF(orderTable[[#This Row],[Buy_Price]]<>"",ROUND(IF(orderTable[[#This Row],[Order_Type]]="BUY",orderTable[[#This Row],[Buy_Price]]*orderTable[[#This Row],[Quantity]],""),2), "")
H19: ORD1127 | I19: 45748 | J19: Banking | K19: AXISBANK | M19: 3804.69 | N19: 50 | O19: SELL | P19: =IF(J19=J20, P20 + IF(O19="BUY", N19, -N19), IF(O19="BUY", N19, -N19)) -> 50 | Q19: =IF(orderTable[[#This Row],[Buy_Price]]<>"",ROUND(IF(orderTable[[#This Row],[Order_Type]]="BUY",orderTable[[#This Row],[Buy_Price]]*orderTable[[#This Row],[Quantity]],""),2), "")
H20: ORD1195 | I20: 45664 | J20: Banking | K20: AXISBANK | L20: 2410.7 | N20: 100 | O20: BUY | P20: =IF(J20=J21, P21 + IF(O20="BUY", N20, -N20), IF(O20="BUY", N20, -N20)) -> 100 | Q20: =IF(orderTable[[#This Row],[Buy_Price]]<>"",ROUND(IF(orderTable[[#This Row],[Order_Type]]="BUY",orderTable[[#This Row],[Buy_Price]]*orderTable[[#This Row],[Quantity]],""),2), "") -> 241070
H21: ORD1022 | I21: 45832 | J21: Finance | K21: BAJFINANCE | L21: 2428.95 | N21: 10 | O21: BUY | P21: =IF(J21=J22, P22 + IF(O21="BUY", N21, -N21), IF(O21="BUY", N21, -N21)) -> 280 | Q21: =IF(orderTable[[#This Row],[Buy_Price]]<>"",ROUND(IF(orderTable[[#This Row],[Order_Type]]="BUY",orderTable[[#This Row],[Buy_Price]]*orderTable[[#This Row],[Quantity]],""),2), "") -> 24289.5
H22: ORD1199 | I22: 45829 | J22: Finance | K22: BAJFINANCE | L22: 1451.96 | N22: 50 | O22: BUY | P22: =IF(J22=J23, P23 + IF(O22="BUY", N22, -N22), IF(O22="BUY", N22, -N22)) -> 270 | Q22: =IF(orderTable[[#This Row],[Buy_Price]]<>"",ROUND(IF(orderTable[[#This Row],[Order_Type]]="BUY",orderTable[[#This Row],[Buy_Price]]*orderTable[[#This Row],[Quantity]],""),2), "") -> 72598
H23: ORD1057 | I23: 45828 | J23: Finance | K23: BAJFINANCE | M23: 2448.55 | N23: 5 | O23: SELL | P23: =IF(J23=J24, P24 + IF(O23="BUY", N23, -N23), IF(O23="BUY", N23, -N23)) -> 220 | Q23: =IF(orderTable[[#This Row],[Buy_Price]]<>"",ROUND(IF(orderTable[[#This Row],[Order_Type]]="BUY",orderTable[[#This Row],[Buy_Price]]*orderTable[[#This Row],[Quantity]],""),2), "")
H24: ORD1078 | I24: 45828 | J24: Finance | K24: BAJFINANCE | L24: 1370.14 | N24: 10 | O24: BUY | P24: =IF(J24=J25, P25 + IF(O24="BUY", N24, -N24), IF(O24="BUY", N24, -N24)) -> 225 | Q24: =IF(orderTable[[#This Row],[Buy_Price]]<>"",ROUND(IF(orderTable[[#This Row],[Order_Type]]="BUY",orderTable[[#This Row],[Buy_Price]]*orderTable[[#This Row],[Quantity]],""),2), "") -> 13701.4
H25: ORD1091 | I25: 45814 | J25: Finance | K25: BAJFINANCE | M25: 3709.22 | N25: 100 | O25: SELL | P25: =IF(J25=J26, P26 + IF(O25="BUY", N25, -N25), IF(O25="BUY", N25, -N25)) -> 215 | Q25: =IF(orderTable[[#This Row],[Buy_Price]]<>"",ROUND(IF(orderTable[[#This Row],[Order_Type]]="BUY",orderTable[[#This Row],[Buy_Price]]*orderTable[[#This Row],[Quantity]],""),2), "")
H26: ORD1181 | I26: 45808 | J26: Finance | K26: BAJFINANCE | L26: 397.44 | N26: 50 | O26: BUY | P26: =IF(J26=J27, P27 + IF(O26="BUY", N26, -N26), IF(O26="BUY", N26, -N26)) -> 315 | Q26: =IF(orderTable[[#This Row],[Buy_Price]]<>"",ROUND(IF(orderTable[[#This Row],[Order_Type]]="BUY",orderTable[[#This Row],[Buy_Price]]*orderTable[[#This Row],[Quantity]],""),2), "") -> 19872
H27: ORD1018 | I27: 45807 | J27: Finance | K27: BAJFINANCE | M27: 2731.75 | N27: 75 | O27: SELL | P27: =IF(J27=J28, P28 + IF(O27="BUY", N27, -N27), IF(O27="BUY", N27, -N27)) -> 265 | Q27: =IF(orderTable[[#This Row],[Buy_Price]]<>"",ROUND(IF(orderTable[[#This Row],[Order_Type]]="BUY",orderTable[[#This Row],[Buy_Price]]*orderTable[[#This Row],[Quantity]],""),2), "")
H28: ORD1008 | I28: 45805 | J28: Finance | K28: BAJFINANCE | M28: 2894.7 | N28: 50 | O28: SELL | P28: =IF(J28=J29, P29 + IF(O28="BUY", N28, -N28), IF(O28="BUY", N28, -N28)) -> 340 | Q28: =IF(orderTable[[#This Row],[Buy_Price]]<>"",ROUND(IF(orderTable[[#This Row],[Order_Type]]="BUY",orderTable[[#This Row],[Buy_Price]]*orderTable[[#This Row],[Quantity]],""),2), "")
H29: ORD1030 | I29: 45798 | J29: Finance | K29: BAJFINANCE | L29: 580.11 | N29: 100 | O29: BUY | P29: =IF(J29=J30, P30 + IF(O29="BUY", N29, -N29), IF(O29="BUY", N29, -N29)) -> 390 | Q29: =IF(orderTable[[#This Row],[Buy_Price]]<>"",ROUND(IF(orderTable[[#This Row],[Order_Type]]="BUY",orderTable[[#This Row],[Buy_Price]]*orderTable[[#This Row],[Quantity]],""),2), "") -> 58011
H30: ORD1116 | I30: 45787 | J30: Finance | K30: BAJFINANCE | M30: 2554.22 | N30: 10 | O30: SELL | P30: =IF(J30=J31, P31 + IF(O30="BUY", N30, -N30), IF(O30="BUY", N30, -N30)) -> 290 | Q30: =IF(orderTable[[#This Row],[Buy_Price]]<>"",ROUND(IF(orderTable[[#This Row],[Order_Type]]="BUY",orderTable[[#This Row],[Buy_Price]]*orderTable[[#This Row],[Quantity]],""),2), "")
H31: ORD1124 | I31: 45772 | J31: Finance | K31: BAJFINANCE | L31: 2463.54 | N31: 100 | O31: BUY | P31: =IF(J31=J32, P32 + IF(O31="BUY", N31, -N31), IF(O31="BUY", N31, -N31)) -> 300 | Q31: =IF(orderTable[[#This Row],[Buy_Price]]<>"",ROUND(IF(orderTable[[#This Row],[Order_Type]]="BUY",orderTable[[#This Row],[Buy_Price]]*orderTable[[#This Row],[Quantity]],""),2), "") -> 246354
H32: ORD1101 | I32: 45769 | J32: Finance | K32: BAJFINANCE | L32: 1785.57 | N32: 25 | O32: BUY | P32: =IF(J32=J33, P33 + IF(O32="BUY", N32, -N32), IF(O32="BUY", N32, -N32)) -> 200 | Q32: =IF(orderTable[[#This Row],[Buy_Price]]<>"",ROUND(IF(orderTable[[#This Row],[Order_Type]]="BUY",orderTable[[#This Row],[Buy_Price]]*orderTable[[#This Row],[Quantity]],""),2), "") -> 44639.25
H33: ORD1098 | I33: 45765 | J33: Finance | K33: BAJFINANCE | M33: 1585.88 | N33: 20 | O33: SELL | P33: =IF(J33=J34, P34 + IF(O33="BUY", N33, -N33), IF(O33="BUY", N33, -N33)) -> 175 | Q33: =IF(orderTable[[#This Row],[Buy_Price]]<>"",ROUND(IF(orderTable[[#This Row],[Order_Type]]="BUY",orderTable[[#This Row],[Buy_Price]]*orderTable[[#This Row],[Quantity]],""),2), "")
H34: ORD1055 | I34: 45747 | J34: Finance | K34: BAJFINANCE | L34: 1844.71 | N34: 15 | O34: BUY | P34: =IF(J34=J35, P35 + IF(O34="BUY", N34, -N34), IF(O34="BUY", N34, -N34)) -> 195 | Q34: =IF(orderTable[[#This Row],[Buy_Price]]<>"",ROUND(IF(orderTable[[#This Row],[Order_Type]]="BUY",orderTable[[#This Row],[Buy_Price]]*orderTable[[#This Row],[Quantity]],""),2), "") -> 27670.65
H35: ORD1119 | I35: 45740 | J35: Finance | K35: BAJFINANCE | M35: 1912.79 | N35: 25 | O35: SELL | P35: =IF(J35=J36, P36 + IF(O35="BUY", N35, -N35), IF(O35="BUY", N35, -N35)) -> 180 | Q35: =IF(orderTable[[#This Row],[Buy_Price]]<>"",ROUND(IF(orderTable[[#This Row],[Order_Type]]="BUY",orderTable[[#This Row],[Buy_Price]]*orderTable[[#This Row],[Quantity]],""),2), "")
H36: ORD1129 | I36: 45728 | J36: Finance | K36: BAJFINANCE | L36: 791.66 | N36: 100 | O36: BUY | P36: =IF(J36=J37, P37 + IF(O36="BUY", N36, -N36), IF(O36="BUY", N36, -N36)) -> 205 | Q36: =IF(orderTable[[#This Row],[Buy_Price]]<>"",ROUND(IF(orderTable[[#This Row],[Order_Type]]="BUY",orderTable[[#This Row],[Buy_Price]]*orderTable[[#This Row],[Quantity]],""),2), "") -> 79166
H37: ORD1037 | I37: 45720 | J37: Finance | K37: BAJFINANCE | L37: 2573.23 | N37: 100 | O37: BUY | P37: =IF(J37=J38, P38 + IF(O37="BUY", N37, -N37), IF(O37="BUY", N37, -N37)) -> 105 | Q37: =IF(orderTable[[#This Row],[Buy_Price]]<>"",ROUND(IF(orderTable[[#This Row],[Order_Type]]="BUY",orderTable[[#This Row],[Buy_Price]]*orderTable[[#This Row],[Quantity]],""),2), "") -> 257323
H38: ORD1014 | I38: 45716 | J38: Finance | K38: BAJFINANCE | L38: 2443.46 | N38: 5 | O38: BUY | P38: =IF(J38=J39, P39 + IF(O38="BUY", N38, -N38), IF(O38="BUY", N38, -N38)) -> 5 | Q38: =IF(orderTable[[#This Row],[Buy_Price]]<>"",ROUND(IF(orderTable[[#This Row],[Order_Type]]="BUY",orderTable[[#This Row],[Buy_Price]]*orderTable[[#This Row],[Quantity]],""),2), "") -> 12217.3
H39: ORD1190 | I39: 45700 | J39: Finance | K39: BAJFINANCE | M39: 1931.04 | N39: 25 | O39: SELL | P39: =IF(J39=J40, P40 + IF(O39="BUY", N39, -N39), IF(O39="BUY", N39, -N39)) -> 0 | Q39: =IF(orderTable[[#This Row],[Buy_Price]]<>"",ROUND(IF(orderTable[[#This Row],[Order_Type]]="BUY",orderTable[[#This Row],[Buy_Price]]*orderTable[[#This Row],[Quantity]],""),2), "")
H40: ORD1023 | I40: 45686 | J40: Finance | K40: BAJFINANCE | M40: 2748.51 | N40: 50 | O40: SELL | P40: =IF(J40=J41, P41 + IF(O40="BUY", N40, -N40), IF(O40="BUY", N40, -N40)) -> 25 | Q40: =IF(orderTable[[#This Row],[Buy_Price]]<>"",ROUND(IF(orderTable[[#This Row],[Order_Type]]="BUY",orderTable[[#This Row],[Buy_Price]]*orderTable[[#This Row],[Quantity]],""),2), "")
H41: ORD1007 | I41: 45678 | J41: Finance | K41: BAJFINANCE | L41: 3409.94 | N41: 75 | O41: BUY | P41: =IF(J41=J42, P42 + IF(O41="BUY", N41, -N41), IF(O41="BUY", N41, -N41)) -> 75 | Q41: =IF(orderTable[[#This Row],[Buy_Price]]<>"",ROUND(IF(orderTable[[#This Row],[Order_Type]]="BUY",orderTable[[#This Row],[Buy_Price]]*orderTable[[#This Row],[Quantity]],""),2), "") -> 255745.5
H42: ORD1001 | I42: 45809 | J42: Banking | K42: ICICIBANK | L42: 2416.94 | N42: 10 | O42: BUY | P42: =IF(J42=J43, P43 + IF(O42="BUY", N42, -N42), IF(O42="BUY", N42, -N42)) -> 165 | Q42: =IF(orderTable[[#This Row],[Buy_Price]]<>"",ROUND(IF(orderTable[[#This Row],[Order_Type]]="BUY",orderTable[[#This Row],[Buy_Price]]*orderTable[[#This Row],[Quantity]],""),2), "") -> 24169.4
H43: ORD1110 | I43: 45802 | J43: Banking | K43: ICICIBANK | L43: 572.84 | N43: 10 | O43: BUY | P43: =IF(J43=J44, P44 + IF(O43="BUY", N43, -N43), IF(O43="BUY", N43, -N43)) -> 155 | Q43: =IF(orderTable[[#This Row],[Buy_Price]]<>"",ROUND(IF(orderTable[[#This Row],[Order_Type]]="BUY",orderTable[[#This Row],[Buy_Price]]*orderTable[[#This Row],[Quantity]],""),2), "") -> 5728.4
H44: ORD1161 | I44: 45788 | J44: Banking | K44: ICICIBANK | M44: 3572.63 | N44: 25 | O44: SELL | P44: =IF(J44=J45, P45 + IF(O44="BUY", N44, -N44), IF(O44="BUY", N44, -N44)) -> 145 | Q44: =IF(orderTable[[#This Row],[Buy_Price]]<>"",ROUND(IF(orderTable[[#This Row],[Order_Type]]="BUY",orderTable[[#This Row],[Buy_Price]]*orderTable[[#This Row],[Quantity]],""),2), "")
H45: ORD1068 | I45: 45763 | J45: Banking | K45: ICICIBANK | L45: 3046.43 | N45: 15 | O45: BUY | P45: =IF(J45=J46, P46 + IF(O45="BUY", N45, -N45), IF(O45="BUY", N45, -N45)) -> 170 | Q45: =IF(orderTable[[#This Row],[Buy_Price]]<>"",ROUND(IF(orderTable[[#This Row],[Order_Type]]="BUY",orderTable[[#This Row],[Buy_Price]]*orderTable[[#This Row],[Quantity]],""),2), "") -> 45696.45
H46: ORD1171 | I46: 45744 | J46: Banking | K46: ICICIBANK | L46: 1722.79 | N46: 25 | O46: BUY | P46: =IF(J46=J47, P47 + IF(O46="BUY", N46, -N46), IF(O46="BUY", N46, -N46)) -> 155 | Q46: =IF(orderTable[[#This Row],[Buy_Price]]<>"",ROUND(IF(orderTable[[#This Row],[Order_Type]]="BUY",orderTable[[#This Row],[Buy_Price]]*orderTable[[#This Row],[Quantity]],""),2), "") -> 43069.75
H47: ORD1097 | I47: 45742 | J47: Banking | K47: ICICIBANK | L47: 365.17 | N47: 75 | O47: BUY | P47: =IF(J47=J48, P48 + IF(O47="BUY", N47, -N47), IF(O47="BUY", N47, -N47)) -> 130 | Q47: =IF(orderTable[[#This Row],[Buy_Price]]<>"",ROUND(IF(orderTable[[#This Row],[Order_Type]]="BUY",orderTable[[#This Row],[Buy_Price]]*orderTable[[#This Row],[Quantity]],""),2), "") -> 27387.75
H48: ORD1187 | I48: 45737 | J48: Banking | K48: ICICIBANK | L48: 3176.4 | N48: 5 | O48: BUY | P48: =IF(J48=J49, P49 + IF(O48="BUY", N48, -N48), IF(O48="BUY", N48, -N48)) -> 55 | Q48: =IF(orderTable[[#This Row],[Buy_Price]]<>"",ROUND(IF(orderTable[[#This Row],[Order_Type]]="BUY",orderTable[[#This Row],[Buy_Price]]*orderTable[[#This Row],[Quantity]],""),2), "") -> 15882
H49: ORD1169 | I49: 45683 | J49: Banking | K49: ICICIBANK | M49: 3232.57 | N49: 50 | O49: BUY | P49: =IF(J49=J50, P50 + IF(O49="BUY", N49, -N49), IF(O49="BUY", N49, -N49)) -> 50 | Q49: =IF(orderTable[[#This Row],[Buy_Price]]<>"",ROUND(IF(orderTable[[#This Row],[Order_Type]]="BUY",orderTable[[#This Row],[Buy_Price]]*orderTable[[#This Row],[Quantity]],""),2), "")
H50: ORD1096 | I50: 45835 | J50: IT | K50: INFY | L50: 655.28 | N50: 75 | O50: BUY | P50: =IF(J50=J51, P51 + IF(O50="BUY", N50, -N50), IF(O50="BUY", N50, -N50)) -> 275 | Q50: =IF(orderTable[[#This Row],[Buy_Price]]<>"",ROUND(IF(orderTable[[#This Row],[Order_Type]]="BUY",orderTable[[#This Row],[Buy_Price]]*orderTable[[#This Row],[Quantity]],""),2), "") -> 49146
H51: ORD1142 | I51: 45834 | J51: IT | K51: INFY | L51: 158.96 | N51: 100 | O51: BUY | P51: =IF(J51=J52, P52 + IF(O51="BUY", N51, -N51), IF(O51="BUY", N51, -N51)) -> 200 | Q51: =IF(orderTable[[#This Row],[Buy_Price]]<>"",ROUND(IF(orderTable[[#This Row],[Order_Type]]="BUY",orderTable[[#This Row],[Buy_Price]]*orderTable[[#This Row],[Quantity]],""),2), "") -> 15896
H52: ORD1192 | I52: 45831 | J52: IT | K52: INFY | L52: 2676.41 | N52: 20 | O52: BUY | P52: =IF(J52=J53, P53 + IF(O52="BUY", N52, -N52), IF(O52="BUY", N52, -N52)) -> 100 | Q52: =IF(orderTable[[#This Row],[Buy_Price]]<>"",ROUND(IF(orderTable[[#This Row],[Order_Type]]="BUY",orderTable[[#This Row],[Buy_Price]]*orderTable[[#This Row],[Quantity]],""),2), "") -> 53528.2
H53: ORD1050 | I53: 45806 | J53: IT | K53: INFY | L53: 1502.65 | N53: 20 | O53: BUY | P53: =IF(J53=J54, P54 + IF(O53="BUY", N53, -N53), IF(O53="BUY", N53, -N53)) -> 80 | Q53: =IF(orderTable[[#This Row],[Buy_Price]]<>"",ROUND(IF(orderTable[[#This Row],[Order_Type]]="BUY",orderTable[[#This Row],[Buy_Price]]*orderTable[[#This Row],[Quantity]],""),2), "") -> 30053
H54: ORD1021 | I54: 45793 | J54: IT | K54: INFY | M54: 1428.83 | N54: 100 | O54: SELL | P54: =IF(J54=J55, P55 + IF(O54="BUY", N54, -N54), IF(O54="BUY", N54, -N54)) -> 60 | Q54: =IF(orderTable[[#This Row],[Buy_Price]]<>"",ROUND(IF(orderTable[[#This Row],[Order_Type]]="BUY",orderTable[[#This Row],[Buy_Price]]*orderTable[[#This Row],[Quantity]],""),2), "")
H55: ORD1120 | I55: 45776 | J55: IT | K55: INFY | M55: 3301.99 | N55: 20 | O55: SELL | P55: =IF(J55=J56, P56 + IF(O55="BUY", N55, -N55), IF(O55="BUY", N55, -N55)) -> 160 | Q55: =IF(orderTable[[#This Row],[Buy_Price]]<>"",ROUND(IF(orderTable[[#This Row],[Order_Type]]="BUY",orderTable[[#This Row],[Buy_Price]]*orderTable[[#This Row],[Quantity]],""),2), "")
H56: ORD1175 | I56: 45771 | J56: IT | K56: INFY | M56: 3370.1 | N56: 10 | O56: SELL | P56: =IF(J56=J57, P57 + IF(O56="BUY", N56, -N56), IF(O56="BUY", N56, -N56)) -> 180 | Q56: =IF(orderTable[[#This Row],[Buy_Price]]<>"",ROUND(IF(orderTable[[#This Row],[Order_Type]]="BUY",orderTable[[#This Row],[Buy_Price]]*orderTable[[#This Row],[Quantity]],""),2), "")
H57: ORD1056 | I57: 45770 | J57: IT | K57: INFY | L57: 1387.92 | N57: 15 | O57: BUY | P57: =IF(J57=J58, P58 + IF(O57="BUY", N57, -N57), IF(O57="BUY", N57, -N57)) -> 190 | Q57: =IF(orderTable[[#This Row],[Buy_Price]]<>"",ROUND(IF(orderTable[[#This Row],[Order_Type]]="BUY",orderTable[[#This Row],[Buy_Price]]*orderTable[[#This Row],[Quantity]],""),2), "") -> 20818.8
H58: ORD1155 | I58: 45761 | J58: IT | K58: INFY | M58: 1117.97 | N58: 10 | O58: SELL | P58: =IF(J58=J59, P59 + IF(O58="BUY", N58, -N58), IF(O58="BUY", N58, -N58)) -> 175 | Q58: =IF(orderTable[[#This Row],[Buy_Price]]<>"",ROUND(IF(orderTable[[#This Row],[Order_Type]]="BUY",orderTable[[#This Row],[Buy_Price]]*orderTable[[#This Row],[Quantity]],""),2), "")
H59: ORD1174 | I59: 45716 | J59: IT | K59: INFY | L59: 2264.39 | N59: 25 | O59: BUY | P59: =IF(J59=J60, P60 + IF(O59="BUY", N59, -N59), IF(O59="BUY", N59, -N59)) -> 185 | Q59: =IF(orderTable[[#This Row],[Buy_Price]]<>"",ROUND(IF(orderTable[[#This Row],[Order_Type]]="BUY",orderTable[[#This Row],[Buy_Price]]*orderTable[[#This Row],[Quantity]],""),2), "") -> 56609.75
H60: ORD1036 | I60: 45712 | J60: IT | K60: INFY | L60: 1082.9 | N60: 100 | O60: BUY | P60: =IF(J60=J61, P61 + IF(O60="BUY", N60, -N60), IF(O60="BUY", N60, -N60)) -> 160 | Q60: =IF(orderTable[[#This Row],[Buy_Price]]<>"",ROUND(IF(orderTable[[#This Row],[Order_Type]]="BUY",orderTable[[#This Row],[Buy_Price]]*orderTable[[#This Row],[Quantity]],""),2), "") -> 108290
H61: ORD1136 | I61: 45679 | J61: IT | K61: INFY | L61: 658.29 | N61: 25 | O61: BUY | P61: =IF(J61=J62, P62 + IF(O61="BUY", N61, -N61), IF(O61="BUY", N61, -N61)) -> 60 | Q61: =IF(orderTable[[#This Row],[Buy_Price]]<>"",ROUND(IF(orderTable[[#This Row],[Order_Type]]="BUY",orderTable[[#This Row],[Buy_Price]]*orderTable[[#This Row],[Quantity]],""),2), "") -> 16457.25
H62: ORD1009 | I62: 45678 | J62: IT | K62: INFY | L62: 2365.23 | N62: 25 | O62: BUY | P62: =IF(J62=J63, P63 + IF(O62="BUY", N62, -N62), IF(O62="BUY", N62, -N62)) -> 35 | Q62: =IF(orderTable[[#This Row],[Buy_Price]]<>"",ROUND(IF(orderTable[[#This Row],[Order_Type]]="BUY",orderTable[[#This Row],[Buy_Price]]*orderTable[[#This Row],[Quantity]],""),2), "") -> 59130.75
H63: ORD1054 | I63: 45676 | J63: IT | K63: INFY | L63: 1685.26 | N63: 10 | O63: BUY | P63: =IF(J63=J64, P64 + IF(O63="BUY", N63, -N63), IF(O63="BUY", N63, -N63)) -> 10 | Q63: =IF(orderTable[[#This Row],[Buy_Price]]<>"",ROUND(IF(orderTable[[#This Row],[Order_Type]]="BUY",orderTable[[#This Row],[Buy_Price]]*orderTable[[#This Row],[Quantity]],""),2), "") -> 16852.6
H64: ORD1013 | I64: 45821 | J64: FMCG | K64: ITC | L64: 1698.57 | N64: 25 | O64: BUY | P64: =IF(J64=J65, P65 + IF(O64="BUY", N64, -N64), IF(O64="BUY", N64, -N64)) -> 375 | Q64: =IF(orderTable[[#This Row],[Buy_Price]]<>"",ROUND(IF(orderTable[[#This Row],[Order_Type]]="BUY",orderTable[[#This Row],[Buy_Price]]*orderTable[[#This Row],[Quantity]],""),2), "") -> 42464.25
H65: ORD1010 | I65: 45820 | J65: FMCG | K65: ITC | L65: 1423.42 | N65: 100 | O65: BUY | P65: =IF(J65=J66, P66 + IF(O65="BUY", N65, -N65), IF(O65="BUY", N65, -N65)) -> 350 | Q65: =IF(orderTable[[#This Row],[Buy_Price]]<>"",ROUND(IF(orderTable[[#This Row],[Order_Type]]="BUY",orderTable[[#This Row],[Buy_Price]]*orderTable[[#This Row],[Quantity]],""),2), "") -> 142342
H66: ORD1067 | I66: 45816 | J66: FMCG | K66: ITC | L66: 1334.82 | N66: 75 | O66: BUY | P66: =IF(J66=J67, P67 + IF(O66="BUY", N66, -N66), IF(O66="BUY", N66, -N66)) -> 250 | Q66: =IF(orderTable[[#This Row],[Buy_Price]]<>"",ROUND(IF(orderTable[[#This Row],[Order_Type]]="BUY",orderTable[[#This Row],[Buy_Price]]*orderTable[[#This Row],[Quantity]],""),2), "") -> 100111.5
H67: ORD1137 | I67: 45813 | J67: FMCG | K67: ITC | L67: 2019.54 | N67: 75 | O67: BUY | P67: =IF(J67=J68, P68 + IF(O67="BUY", N67, -N67), IF(O67="BUY", N67, -N67)) -> 175 | Q67: =IF(orderTable[[#This Row],[Buy_Price]]<>"",ROUND(IF(orderTable[[#This Row],[Order_Type]]="BUY",orderTable[[#This Row],[Buy_Price]]*orderTable[[#This Row],[Quantity]],""),2), "") -> 151465.5
H68: ORD1126 | I68: 45779 | J68: FMCG | K68: ITC | M68: 2518.37 | N68: 50 | O68: SELL | P68: =IF(J68=J69, P69 + IF(O68="BUY", N68, -N68), IF(O68="BUY", N68, -N68)) -> 100 | Q68: =IF(orderTable[[#This Row],[Buy_Price]]<>"",ROUND(IF(orderTable[[#This Row],[Order_Type]]="BUY",orderTable[[#This Row],[Buy_Price]]*orderTable[[#This Row],[Quantity]],""),2), "")
H69: ORD1053 | I69: 45775 | J69: FMCG | K69: ITC | M69: 1495.42 | N69: 25 | O69: SELL | P69: =IF(J69=J70, P70 + IF(O69="BUY", N69, -N69), IF(O69="BUY", N69, -N69)) -> 150 | Q69: =IF(orderTable[[#This Row],[Buy_Price]]<>"",ROUND(IF(orderTable[[#This Row],[Order_Type]]="BUY",orderTable[[#This Row],[Buy_Price]]*orderTable[[#This Row],[Quantity]],""),2), "")
H70: ORD1070 | I70: 45755 | J70: FMCG | K70: ITC | M70: 768.34 | N70: 10 | O70: SELL | P70: =IF(J70=J71, P71 + IF(O70="BUY", N70, -N70), IF(O70="BUY", N70, -N70)) -> 175 | Q70: =IF(orderTable[[#This Row],[Buy_Price]]<>"",ROUND(IF(orderTable[[#This Row],[Order_Type]]="BUY",orderTable[[#This Row],[Buy_Price]]*orderTable[[#This Row],[Quantity]],""),2), "")
H71: ORD1179 | I71: 45717 | J71: FMCG | K71: ITC | M71: 3343.45 | N71: 15 | O71: SELL | P71: =IF(J71=J72, P72 + IF(O71="BUY", N71, -N71), IF(O71="BUY", N71, -N71)) -> 185 | Q71: =IF(orderTable[[#This Row],[Buy_Price]]<>"",ROUND(IF(orderTable[[#This Row],[Order_Type]]="BUY",orderTable[[#This Row],[Buy_Price]]*orderTable[[#This Row],[Quantity]],""),2), "")
H72: ORD1044 | I72: 45712 | J72: FMCG | K72: ITC | L72: 1511.49 | N72: 100 | O72: BUY | P72: =IF(J72=J73, P73 + IF(O72="BUY", N72, -N72), IF(O72="BUY", N72, -N72)) -> 200 | Q72: =IF(orderTable[[#This Row],[Buy_Price]]<>"",ROUND(IF(orderTable[[#This Row],[Order_Type]]="BUY",orderTable[[#This Row],[Buy_Price]]*orderTable[[#This Row],[Quantity]],""),2), "") -> 151149
H73: ORD1041 | I73: 45693 | J73: FMCG | K73: ITC | L73: 787.2 | N73: 100 | O73: BUY | P73: =IF(J73=J74, P74 + IF(O73="BUY", N73, -N73), IF(O73="BUY", N73, -N73)) -> 100 | Q73: =IF(orderTable[[#This Row],[Buy_Price]]<>"",ROUND(IF(orderTable[[#This Row],[Order_Type]]="BUY",orderTable[[#This Row],[Buy_Price]]*orderTable[[#This Row],[Quantity]],""),2), "") -> 78720
H74: ORD1147 | I74: 45834 | J74: Banking | K74: KOTAKBANK | M74: 1638.7 | N74: 100 | O74: SELL | P74: =IF(J74=J75, P75 + IF(O74="BUY", N74, -N74), IF(O74="BUY", N74, -N74)) -> 20 | Q74: =IF(orderTable[[#This Row],[Buy_Price]]<>"",ROUND(IF(orderTable[[#This Row],[Order_Type]]="BUY",orderTable[[#This Row],[Buy_Price]]*orderTable[[#This Row],[Quantity]],""),2), "")
H75: ORD1060 | I75: 45833 | J75: Banking | K75: KOTAKBANK | L75: 2554 | N75: 20 | O75: BUY | P75: =IF(J75=J76, P76 + IF(O75="BUY", N75, -N75), IF(O75="BUY", N75, -N75)) -> 120 | Q75: =IF(orderTable[[#This Row],[Buy_Price]]<>"",ROUND(IF(orderTable[[#This Row],[Order_Type]]="BUY",orderTable[[#This Row],[Buy_Price]]*orderTable[[#This Row],[Quantity]],""),2), "") -> 51080
H76: ORD1095 | I76: 45796 | J76: Banking | K76: KOTAKBANK | L76: 1060.25 | N76: 50 | O76: BUY | P76: =IF(J76=J77, P77 + IF(O76="BUY", N76, -N76), IF(O76="BUY", N76, -N76)) -> 100 | Q76: =IF(orderTable[[#This Row],[Buy_Price]]<>"",ROUND(IF(orderTable[[#This Row],[Order_Type]]="BUY",orderTable[[#This Row],[Buy_Price]]*orderTable[[#This Row],[Quantity]],""),2), "") -> 53012.5
H77: ORD1165 | I77: 45795 | J77: Banking | K77: KOTAKBANK | M77: 3191.51 | N77: 100 | O77: SELL | P77: =IF(J77=J78, P78 + IF(O77="BUY", N77, -N77), IF(O77="BUY", N77, -N77)) -> 50 | Q77: =IF(orderTable[[#This Row],[Buy_Price]]<>"",ROUND(IF(orderTable[[#This Row],[Order_Type]]="BUY",orderTable[[#This Row],[Buy_Price]]*orderTable[[#This Row],[Quantity]],""),2), "")
H78: ORD1072 | I78: 45760 | J78: Banking | K78: KOTAKBANK | L78: 896.79 | N78: 20 | O78: BUY | P78: =IF(J78=J79, P79 + IF(O78="BUY", N78, -N78), IF(O78="BUY", N78, -N78)) -> 150 | Q78: =IF(orderTable[[#This Row],[Buy_Price]]<>"",ROUND(IF(orderTable[[#This Row],[Order_Type]]="BUY",orderTable[[#This Row],[Buy_Price]]*orderTable[[#This Row],[Quantity]],""),2), "") -> 17935.8
H79: ORD1066 | I79: 45749 | J79: Banking | K79: KOTAKBANK | M79: 3136.34 | N79: 5 | O79: SELL | P79: =IF(J79=J80, P80 + IF(O79="BUY", N79, -N79), IF(O79="BUY", N79, -N79)) -> 130 | Q79: =IF(orderTable[[#This Row],[Buy_Price]]<>"",ROUND(IF(orderTable[[#This Row],[Order_Type]]="BUY",orderTable[[#This Row],[Buy_Price]]*orderTable[[#This Row],[Quantity]],""),2), "")
H80: ORD1115 | I80: 45746 | J80: Banking | K80: KOTAKBANK | L80: 2817.36 | N80: 5 | O80: BUY | P80: =IF(J80=J81, P81 + IF(O80="BUY", N80, -N80), IF(O80="BUY", N80, -N80)) -> 135 | Q80: =IF(orderTable[[#This Row],[Buy_Price]]<>"",ROUND(IF(orderTable[[#This Row],[Order_Type]]="BUY",orderTable[[#This Row],[Buy_Price]]*orderTable[[#This Row],[Quantity]],""),2), "") -> 14086.8
H81: ORD1182 | I81: 45735 | J81: Banking | K81: KOTAKBANK | M81: 2437.54 | N81: 100 | O81: BUY | P81: =IF(J81=J82, P82 + IF(O81="BUY", N81, -N81), IF(O81="BUY", N81, -N81)) -> 130 | Q81: =IF(orderTable[[#This Row],[Buy_Price]]<>"",ROUND(IF(orderTable[[#This Row],[Order_Type]]="BUY",orderTable[[#This Row],[Buy_Price]]*orderTable[[#This Row],[Quantity]],""),2), "")
H82: ORD1176 | I82: 45733 | J82: Banking | K82: KOTAKBANK | L82: 304.07 | N82: 5 | O82: BUY | P82: =IF(J82=J83, P83 + IF(O82="BUY", N82, -N82), IF(O82="BUY", N82, -N82)) -> 30 | Q82: =IF(orderTable[[#This Row],[Buy_Price]]<>"",ROUND(IF(orderTable[[#This Row],[Order_Type]]="BUY",orderTable[[#This Row],[Buy_Price]]*orderTable[[#This Row],[Quantity]],""),2), "") -> 1520.35
H83: ORD1184 | I83: 45728 | J83: Banking | K83: KOTAKBANK | M83: 212.68 | N83: 75 | O83: SELL | P83: =IF(J83=J84, P84 + IF(O83="BUY", N83, -N83), IF(O83="BUY", N83, -N83)) -> 25 | Q83: =IF(orderTable[[#This Row],[Buy_Price]]<>"",ROUND(IF(orderTable[[#This Row],[Order_Type]]="BUY",orderTable[[#This Row],[Buy_Price]]*orderTable[[#This Row],[Quantity]],""),2), "")
H84: ORD1058 | I84: 45725 | J84: Banking | K84: KOTAKBANK | L84: 3295.42 | N84: 15 | O84: BUY | P84: =IF(J84=J85, P85 + IF(O84="BUY", N84, -N84), IF(O84="BUY", N84, -N84)) -> 100 | Q84: =IF(orderTable[[#This Row],[Buy_Price]]<>"",ROUND(IF(orderTable[[#This Row],[Order_Type]]="BUY",orderTable[[#This Row],[Buy_Price]]*orderTable[[#This Row],[Quantity]],""),2), "") -> 49431.3
H85: ORD1189 | I85: 45709 | J85: Banking | K85: KOTAKBANK | M85: 2591.51 | N85: 15 | O85: SELL | P85: =IF(J85=J86, P86 + IF(O85="BUY", N85, -N85), IF(O85="BUY", N85, -N85)) -> 85 | Q85: =IF(orderTable[[#This Row],[Buy_Price]]<>"",ROUND(IF(orderTable[[#This Row],[Order_Type]]="BUY",orderTable[[#This Row],[Buy_Price]]*orderTable[[#This Row],[Quantity]],""),2), "")
H86: ORD1158 | I86: 45689 | J86: Banking | K86: KOTAKBANK | L86: 2963.7 | N86: 100 | O86: BUY | P86: =IF(J86=J87, P87 + IF(O86="BUY", N86, -N86), IF(O86="BUY", N86, -N86)) -> 100 | Q86: =IF(orderTable[[#This Row],[Buy_Price]]<>"",ROUND(IF(orderTable[[#This Row],[Order_Type]]="BUY",orderTable[[#This Row],[Buy_Price]]*orderTable[[#This Row],[Quantity]],""),2), "") -> 296370
H87: ORD1062 | I87: 45821 | J87: Infrastructure | K87: LT | L87: 161.88 | N87: 15 | O87: BUY | P87: =IF(J87=J88, P88 + IF(O87="BUY", N87, -N87), IF(O87="BUY", N87, -N87)) -> 265 | Q87: =IF(orderTable[[#This Row],[Buy_Price]]<>"",ROUND(IF(orderTable[[#This Row],[Order_Type]]="BUY",orderTable[[#This Row],[Buy_Price]]*orderTable[[#This Row],[Quantity]],""),2), "") -> 2428.2
H88: ORD1063 | I88: 45801 | J88: Infrastructure | K88: LT | L88: 2633.12 | N88: 75 | O88: BUY | P88: =IF(J88=J89, P89 + IF(O88="BUY", N88, -N88), IF(O88="BUY", N88, -N88)) -> 250 | Q88: =IF(orderTable[[#This Row],[Buy_Price]]<>"",ROUND(IF(orderTable[[#This Row],[Order_Type]]="BUY",orderTable[[#This Row],[Buy_Price]]*orderTable[[#This Row],[Quantity]],""),2), "") -> 197484
H89: ORD1012 | I89: 45794 | J89: Infrastructure | K89: LT | L89: 2190.59 | N89: 15 | O89: BUY | P89: =IF(J89=J90, P90 + IF(O89="BUY", N89, -N89), IF(O89="BUY", N89, -N89)) -> 175 | Q89: =IF(orderTable[[#This Row],[Buy_Price]]<>"",ROUND(IF(orderTable[[#This Row],[Order_Type]]="BUY",orderTable[[#This Row],[Buy_Price]]*orderTable[[#This Row],[Quantity]],""),2), "") -> 32858.85
H90: ORD1180 | I90: 45777 | J90: Infrastructure | K90: LT | M90: 1136.28 | N90: 5 | O90: SELL | P90: =IF(J90=J91, P91 + IF(O90="BUY", N90, -N90), IF(O90="BUY", N90, -N90)) -> 160 | Q90: =IF(orderTable[[#This Row],[Buy_Price]]<>"",ROUND(IF(orderTable[[#This Row],[Order_Type]]="BUY",orderTable[[#This Row],[Buy_Price]]*orderTable[[#This Row],[Quantity]],""),2), "")
H91: ORD1075 | I91: 45746 | J91: Infrastructure | K91: LT | L91: 513.15 | N91: 75 | O91: BUY | P91: =IF(J91=J92, P92 + IF(O91="BUY", N91, -N91), IF(O91="BUY", N91, -N91)) -> 165 | Q91: =IF(orderTable[[#This Row],[Buy_Price]]<>"",ROUND(IF(orderTable[[#This Row],[Order_Type]]="BUY",orderTable[[#This Row],[Buy_Price]]*orderTable[[#This Row],[Quantity]],""),2), "") -> 38486.25
H92: ORD1128 | I92: 45707 | J92: Infrastructure | K92: LT | M92: 1005.21 | N92: 10 | O92: SELL | P92: =IF(J92=J93, P93 + IF(O92="BUY", N92, -N92), IF(O92="BUY", N92, -N92)) -> 90 | Q92: =IF(orderTable[[#This Row],[Buy_Price]]<>"",ROUND(IF(orderTable[[#This Row],[Order_Type]]="BUY",orderTable[[#This Row],[Buy_Price]]*orderTable[[#This Row],[Quantity]],""),2), "")
H93: ORD1046 | I93: 45697 | J93: Infrastructure | K93: LT | L93: 1092.3 | N93: 100 | O93: BUY | P93: =IF(J93=J94, P94 + IF(O93="BUY", N93, -N93), IF(O93="BUY", N93, -N93)) -> 100 | Q93: =IF(orderTable[[#This Row],[Buy_Price]]<>"",ROUND(IF(orderTable[[#This Row],[Order_Type]]="BUY",orderTable[[#This Row],[Buy_Price]]*orderTable[[#This Row],[Quantity]],""),2), "") -> 109230
H94: ORD1183 | I94: 45804 | J94: Automobile | K94: MARUTI | M94: 518.34 | N94: 75 | O94: SELL | P94: =IF(J94=J95, P95 + IF(O94="BUY", N94, -N94), IF(O94="BUY", N94, -N94)) -> 80 | Q94: =IF(orderTable[[#This Row],[Buy_Price]]<>"",ROUND(IF(orderTable[[#This Row],[Order_Type]]="BUY",orderTable[[#This Row],[Buy_Price]]*orderTable[[#This Row],[Quantity]],""),2), "")
H95: ORD1173 | I95: 45796 | J95: Automobile | K95: MARUTI | L95: 2153.44 | N95: 100 | O95: BUY | P95: =IF(J95=J96, P96 + IF(O95="BUY", N95, -N95), IF(O95="BUY", N95, -N95)) -> 155 | Q95: =IF(orderTable[[#This Row],[Buy_Price]]<>"",ROUND(IF(orderTable[[#This Row],[Order_Type]]="BUY",orderTable[[#This Row],[Buy_Price]]*orderTable[[#This Row],[Quantity]],""),2), "") -> 215344
H96: ORD1082 | I96: 45768 | J96: Automobile | K96: MARUTI | L96: 1167.98 | N96: 20 | O96: BUY | P96: =IF(J96=J97, P97 + IF(O96="BUY", N96, -N96), IF(O96="BUY", N96, -N96)) -> 55 | Q96: =IF(orderTable[[#This Row],[Buy_Price]]<>"",ROUND(IF(orderTable[[#This Row],[Order_Type]]="BUY",orderTable[[#This Row],[Buy_Price]]*orderTable[[#This Row],[Quantity]],""),2), "") -> 23359.6
H97: ORD1045 | I97: 45757 | J97: Automobile | K97: MARUTI | L97: 701.53 | N97: 5 | O97: BUY | P97: =IF(J97=J98, P98 + IF(O97="BUY", N97, -N97), IF(O97="BUY", N97, -N97)) -> 35 | Q97: =IF(orderTable[[#This Row],[Buy_Price]]<>"",ROUND(IF(orderTable[[#This Row],[Order_Type]]="BUY",orderTable[[#This Row],[Buy_Price]]*orderTable[[#This Row],[Quantity]],""),2), "") -> 3507.65
H98: ORD1074 | I98: 45724 | J98: Automobile | K98: MARUTI | M98: 3249.35 | N98: 10 | O98: SELL | P98: =IF(J98=J99, P99 + IF(O98="BUY", N98, -N98), IF(O98="BUY", N98, -N98)) -> 30 | Q98: =IF(orderTable[[#This Row],[Buy_Price]]<>"",ROUND(IF(orderTable[[#This Row],[Order_Type]]="BUY",orderTable[[#This Row],[Buy_Price]]*orderTable[[#This Row],[Quantity]],""),2), "")
H99: ORD1121 | I99: 45704 | J99: Automobile | K99: MARUTI | M99: 257.84 | N99: 50 | O99: SELL | P99: =IF(J99=J100, P100 + IF(O99="BUY", N99, -N99), IF(O99="BUY", N99, -N99)) -> 40 | Q99: =IF(orderTable[[#This Row],[Buy_Price]]<>"",ROUND(IF(orderTable[[#This Row],[Order_Type]]="BUY",orderTable[[#This Row],[Buy_Price]]*orderTable[[#This Row],[Quantity]],""),2), "")
H100: ORD1163 | I100: 45675 | J100: Automobile | K100: MARUTI | L100: 3238.26 | N100: 15 | O100: BUY | P100: =IF(J100=J101, P101 + IF(O100="BUY", N100, -N100), IF(O100="BUY", N100, -N100)) -> 90 | Q100: =IF(orderTable[[#This Row],[Buy_Price]]<>"",ROUND(IF(orderTable[[#This Row],[Order_Type]]="BUY",orderTable[[#This Row],[Buy_Price]]*orderTable[[#This Row],[Quantity]],""),2), "") -> 48573.9
H101: ORD1193 | I101: 45661 | J101: Automobile | K101: MARUTI | L101: 453.82 | N101: 75 | O101: BUY | P101: =IF(J101=J102, P102 + IF(O101="BUY", N101, -N101), IF(O101="BUY", N101, -N101)) -> 75 | Q101: =IF(orderTable[[#This Row],[Buy_Price]]<>"",ROUND(IF(orderTable[[#This Row],[Order_Type]]="BUY",orderTable[[#This Row],[Buy_Price]]*orderTable[[#This Row],[Quantity]],""),2), "") -> 34036.5
H102: ORD1083 | I102: 45830 | J102: FMCG | K102: NESTLEIND | M102: 1695.31 | N102: 100 | O102: SELL | P102: =IF(J102=J103, P103 + IF(O102="BUY", N102, -N102), IF(O102="BUY", N102, -N102)) -> 55 | Q102: =IF(orderTable[[#This Row],[Buy_Price]]<>"",ROUND(IF(orderTable[[#This Row],[Order_Type]]="BUY",orderTable[[#This Row],[Buy_Price]]*orderTable[[#This Row],[Quantity]],""),2), "")
H103: ORD1052 | I103: 45829 | J103: FMCG | K103: NESTLEIND | M103: 3587.21 | N103: 20 | O103: SELL | P103: =IF(J103=J104, P104 + IF(O103="BUY", N103, -N103), IF(O103="BUY", N103, -N103)) -> 155 | Q103: =IF(orderTable[[#This Row],[Buy_Price]]<>"",ROUND(IF(orderTable[[#This Row],[Order_Type]]="BUY",orderTable[[#This Row],[Buy_Price]]*orderTable[[#This Row],[Quantity]],""),2), "")
H104: ORD1145 | I104: 45823 | J104: FMCG | K104: NESTLEIND | L104: 1574.22 | N104: 20 | O104: BUY | P104: =IF(J104=J105, P105 + IF(O104="BUY", N104, -N104), IF(O104="BUY", N104, -N104)) -> 175 | Q104: =IF(orderTable[[#This Row],[Buy_Price]]<>"",ROUND(IF(orderTable[[#This Row],[Order_Type]]="BUY",orderTable[[#This Row],[Buy_Price]]*orderTable[[#This Row],[Quantity]],""),2), "") -> 31484.4
H105: ORD1150 | I105: 45805 | J105: FMCG | K105: NESTLEIND | L105: 3498.57 | N105: 25 | O105: BUY | P105: =IF(J105=J106, P106 + IF(O105="BUY", N105, -N105), IF(O105="BUY", N105, -N105)) -> 155 | Q105: =IF(orderTable[[#This Row],[Buy_Price]]<>"",ROUND(IF(orderTable[[#This Row],[Order_Type]]="BUY",orderTable[[#This Row],[Buy_Price]]*orderTable[[#This Row],[Quantity]],""),2), "") -> 87464.25
H106: ORD1099 | I106: 45780 | J106: FMCG | K106: NESTLEIND | L106: 3020.05 | N106: 75 | O106: BUY | P106: =IF(J106=J107, P107 + IF(O106="BUY", N106, -N106), IF(O106="BUY", N106, -N106)) -> 130 | Q106: =IF(orderTable[[#This Row],[Buy_Price]]<>"",ROUND(IF(orderTable[[#This Row],[Order_Type]]="BUY",orderTable[[#This Row],[Buy_Price]]*orderTable[[#This Row],[Quantity]],""),2), "") -> 226503.75
H107: ORD1016 | I107: 45759 | J107: FMCG | K107: NESTLEIND | M107: 971.76 | N107: 100 | O107: SELL | P107: =IF(J107=J108, P108 + IF(O107="BUY", N107, -N107), IF(O107="BUY", N107, -N107)) -> 55 | Q107: =IF(orderTable[[#This Row],[Buy_Price]]<>"",ROUND(IF(orderTable[[#This Row],[Order_Type]]="BUY",orderTable[[#This Row],[Buy_Price]]*orderTable[[#This Row],[Quantity]],""),2), "")
H108: ORD1130 | I108: 45733 | J108: FMCG | K108: NESTLEIND | M108: 3419.24 | N108: 20 | O108: SELL | P108: =IF(J108=J109, P109 + IF(O108="BUY", N108, -N108), IF(O108="BUY", N108, -N108)) -> 155 | Q108: =IF(orderTable[[#This Row],[Buy_Price]]<>"",ROUND(IF(orderTable[[#This Row],[Order_Type]]="BUY",orderTable[[#This Row],[Buy_Price]]*orderTable[[#This Row],[Quantity]],""),2), "")
...

Sheet My Holdings
I1: 📈 STOCK MARKET PORTFOLIO TRACKER & RETURN ANALYZER
I6: My Holdings | T6: Live Stock DATA
I15: Stock_Name | J15: Sector | K15: Quantity | L15: Avg_Buy_Price | M15: Total_Investment | N15: Current_Price | O15: Market_Value | P15: Profit/Loss | Q15: Return % | T15: Stock_Name | U15: Ticker symbol | V15: Current_Price
I16: {=_FV(Table5[[#This Row],[Stock_Name]],"Ticker symbol",TRUE)} -> ASIANPAINT | J16: =_xlfn.XLOOKUP(I16,orderTable[Stock_Name],orderTable[Sector],"Undefined",0,1) -> Paints | K16: =SUMIFS(orderTable[Quantity],orderTable[Stock_Name],'My Holdings'!I16,orderTable[Order_Type],"BUY") - SUMIFS(orderTable[Quantity],orderTable[Stock_Name],'My Holdings'!I16,orderTable[Order_Type],"SELL") -> 35 | L16: =ROUND(SUMIFS(orderTable[BP*Qty],orderTable[Stock_Name],'My Holdings'!I16,orderTable[Order_Type],"BUY") / SUMIFS(orderTable[Quantity],orderTable[Stock_Name],'My Holdings'!I16,orderTable[Order_Type],"BUY"),2) -> 2010.91 | M16: =L16*K16 -> 70381.85 | N16: =_xlfn.XLOOKUP(I16,Table5[Ticker symbol],Table5[Current_Price],0,0,1) -> 2671.9 | O16: =N16*K16 -> 93516.5 | P16: =O16-M16 -> 23134.65 | Q16: =IF(M16<>0,P16/M16,0) -> 0.32870193 | T16: #VALUE! | U16: {=_FV(Table5[[#This Row],[Stock_Name]],"Ticker symbol",TRUE)} -> ASIANPAINT | V16: {=_FV(T16,"Price")} -> 2671.9
I17: {=_FV(Table5[[#This Row],[Stock_Name]],"Ticker symbol",TRUE)} -> AXISBANK | J17: =_xlfn.XLOOKUP(I17,orderTable[Stock_Name],orderTable[Sector],"Undefined",0,1) -> Banking | K17: =SUMIFS(orderTable[Quantity],orderTable[Stock_Name],'My Holdings'!I17,orderTable[Order_Type],"BUY") - SUMIFS(orderTable[Quantity],orderTable[Stock_Name],'My Holdings'!I17,orderTable[Order_Type],"SELL") -> 50 | L17: =ROUND(SUMIFS(orderTable[BP*Qty],orderTable[Stock_Name],'My Holdings'!I17,orderTable[Order_Type],"BUY") / SUMIFS(orderTable[Quantity],orderTable[Stock_Name],'My Holdings'!I17,orderTable[Order_Type],"BUY"),2) -> 2247.85 | M17: =L17*K17 -> 112392.5 | N17: =_xlfn.XLOOKUP(I17,Table5[Ticker symbol],Table5[Current_Price],0,0,1) -> 1304.1 | O17: =N17*K17 -> 65205 | P17: =O17-M17 -> -47187.5 | Q17: =IF(M17<>0,P17/M17,0) -> -0.41984563 | T17: #VALUE! | U17: {=_FV(Table5[[#This Row],[Stock_Name]],"Ticker symbol",TRUE)} -> AXISBANK | V17: {=_FV(T17,"Price")} -> 1304.1
I18: {=_FV(Table5[[#This Row],[Stock_Name]],"Ticker symbol",TRUE)} -> BAJFINANCE | J18: =_xlfn.XLOOKUP(I18,orderTable[Stock_Name],orderTable[Sector],"Undefined",0,1) -> Finance | K18: =SUMIFS(orderTable[Quantity],orderTable[Stock_Name],'My Holdings'!I18,orderTable[Order_Type],"BUY") - SUMIFS(orderTable[Quantity],orderTable[Stock_Name],'My Holdings'!I18,orderTable[Order_Type],"SELL") -> 280 | L18: =ROUND(SUMIFS(orderTable[BP*Qty],orderTable[Stock_Name],'My Holdings'!I18,orderTable[Order_Type],"BUY") / SUMIFS(orderTable[Quantity],orderTable[Stock_Name],'My Holdings'!I18,orderTable[Order_Type],"BUY"),2) -> 1736.86 | M18: =L18*K18 -> 486320.8 | N18: =_xlfn.XLOOKUP(I18,Table5[Ticker symbol],Table5[Current_Price],0,0,1) -> 931.15 | O18: =N18*K18 -> 260722 | P18: =O18-M18 -> -225598.8 | Q18: =IF(M18<>0,P18/M18,0) -> -0.46388886 | T18: #VALUE! | U18: {=_FV(Table5[[#This Row],[Stock_Name]],"Ticker symbol",TRUE)} -> BAJFINANCE | V18: {=_FV(T18,"Price")} -> 931.15
I19: {=_FV(Table5[[#This Row],[Stock_Name]],"Ticker symbol",TRUE)} -> ICICIBANK | J19: =_xlfn.XLOOKUP(I19,orderTable[Stock_Name],orderTable[Sector],"Undefined",0,1) -> Banking | K19: =SUMIFS(orderTable[Quantity],orderTable[Stock_Name],'My Holdings'!I19,orderTable[Order_Type],"BUY") - SUMIFS(orderTable[Quantity],orderTable[Stock_Name],'My Holdings'!I19,orderTable[Order_Type],"SELL") -> 165 | L19: =ROUND(SUMIFS(orderTable[BP*Qty],orderTable[Stock_Name],'My Holdings'!I19,orderTable[Order_Type],"BUY") / SUMIFS(orderTable[Quantity],orderTable[Stock_Name],'My Holdings'!I19,orderTable[Order_Type],"BUY"),2) -> 852.28 | M19: =L19*K19 -> 140626.2 | N19: =_xlfn.XLOOKUP(I19,Table5[Ticker symbol],Table5[Current_Price],0,0,1) -> 1272.7 | O19: =N19*K19 -> 209995.5 | P19: =O19-M19 -> 69369.3 | Q19: =IF(M19<>0,P19/M19,0) -> 0.49328859 | T19: #VALUE! | U19: {=_FV(Table5[[#This Row],[Stock_Name]],"Ticker symbol",TRUE)} -> ICICIBANK | V19: {=_FV(T19,"Price")} -> 1272.7
I20: {=_FV(Table5[[#This Row],[Stock_Name]],"Ticker symbol",TRUE)} -> INFY | J20: =_xlfn.XLOOKUP(I20,orderTable[Stock_Name],orderTable[Sector],"Undefined",0,1) -> IT | K20: =SUMIFS(orderTable[Quantity],orderTable[Stock_Name],'My Holdings'!I20,orderTable[Order_Type],"BUY") - SUMIFS(orderTable[Quantity],orderTable[Stock_Name],'My Holdings'!I20,orderTable[Order_Type],"SELL") -> 275 | L20: =ROUND(SUMIFS(orderTable[BP*Qty],orderTable[Stock_Name],'My Holdings'!I20,orderTable[Order_Type],"BUY") / SUMIFS(orderTable[Quantity],orderTable[Stock_Name],'My Holdings'!I20,orderTable[Order_Type],"BUY"),2) -> 1028.39 | M20: =L20*K20 -> 282807.25 | N20: =_xlfn.XLOOKUP(I20,Table5[Ticker symbol],Table5[Current_Price],0,0,1) -> 1159.9 | O20: =N20*K20 -> 318972.5 | P20: =O20-M20 -> 36165.25 | Q20: =IF(M20<>0,P20/M20,0) -> 0.1278795 | T20: #VALUE! | U20: {=_FV(Table5[[#This Row],[Stock_Name]],"Ticker symbol",TRUE)} -> INFY | V20: {=_FV(T20,"Price")} -> 1159.9
I21: {=_FV(Table5[[#This Row],[Stock_Name]],"Ticker symbol",TRUE)} -> ITC | J21: =_xlfn.XLOOKUP(I21,orderTable[Stock_Name],orderTable[Sector],"Undefined",0,1) -> FMCG | K21: =SUMIFS(orderTable[Quantity],orderTable[Stock_Name],'My Holdings'!I21,orderTable[Order_Type],"BUY") - SUMIFS(orderTable[Quantity],orderTable[Stock_Name],'My Holdings'!I21,orderTable[Order_Type],"SELL") -> 375 | L21: =ROUND(SUMIFS(orderTable[BP*Qty],orderTable[Stock_Name],'My Holdings'!I21,orderTable[Order_Type],"BUY") / SUMIFS(orderTable[Quantity],orderTable[Stock_Name],'My Holdings'!I21,orderTable[Order_Type],"BUY"),2) -> 1402.64 | M21: =L21*K21 -> 525990 | N21: =_xlfn.XLOOKUP(I21,Table5[Ticker symbol],Table5[Current_Price],0,0,1) -> 291.95 | O21: =N21*K21 -> 109481.25 | P21: =O21-M21 -> -416508.75 | Q21: =IF(M21<>0,P21/M21,0) -> -0.79185678 | T21: #VALUE! | U21: {=_FV(Table5[[#This Row],[Stock_Name]],"Ticker symbol",TRUE)} -> ITC | V21: {=_FV(T21,"Price")} -> 291.95
I22: {=_FV(Table5[[#This Row],[Stock_Name]],"Ticker symbol",TRUE)} -> KOTAKBANK | J22: =_xlfn.XLOOKUP(I22,orderTable[Stock_Name],orderTable[Sector],"Undefined",0,1) -> Banking | K22: =SUMIFS(orderTable[Quantity],orderTable[Stock_Name],'My Holdings'!I22,orderTable[Order_Type],"BUY") - SUMIFS(orderTable[Quantity],orderTable[Stock_Name],'My Holdings'!I22,orderTable[Order_Type],"SELL") -> 20 | L22: =ROUND(SUMIFS(orderTable[BP*Qty],orderTable[Stock_Name],'My Holdings'!I22,orderTable[Order_Type],"BUY") / SUMIFS(orderTable[Quantity],orderTable[Stock_Name],'My Holdings'!I22,orderTable[Order_Type],"BUY"),2) -> 1534.72 | M22: =L22*K22 -> 30694.4 | N22: =_xlfn.XLOOKUP(I22,Table5[Ticker symbol],Table5[Current_Price],0,0,1) -> 388.7 | O22: =N22*K22 -> 7774 | P22: =O22-M22 -> -22920.4 | Q22: =IF(M22<>0,P22/M22,0) -> -0.74672905 | T22: #VALUE! | U22: {=_FV(Table5[[#This Row],[Stock_Name]],"Ticker symbol",TRUE)} -> KOTAKBANK | V22: {=_FV(T22,"Price")} -> 388.7
I23: {=_FV(Table5[[#This Row],[Stock_Name]],"Ticker symbol",TRUE)} -> LT | J23: =_xlfn.XLOOKUP(I23,orderTable[Stock_Name],orderTable[Sector],"Undefined",0,1) -> Infrastructure | K23: =SUMIFS(orderTable[Quantity],orderTable[Stock_Name],'My Holdings'!I23,orderTable[Order_Type],"BUY") - SUMIFS(orderTable[Quantity],orderTable[Stock_Name],'My Holdings'!I23,orderTable[Order_Type],"SELL") -> 265 | L23: =ROUND(SUMIFS(orderTable[BP*Qty],orderTable[Stock_Name],'My Holdings'!I23,orderTable[Order_Type],"BUY") / SUMIFS(orderTable[Quantity],orderTable[Stock_Name],'My Holdings'!I23,orderTable[Order_Type],"BUY"),2) -> 1358.88 | M23: =L23*K23 -> 360103.2 | N23: =_xlfn.XLOOKUP(I23,Table5[Ticker symbol],Table5[Current_Price],0,0,1) -> 4047.5 | O23: =N23*K23 -> 1072587.5 | P23: =O23-M23 -> 712484.3 | Q23: =IF(M23<>0,P23/M23,0) -> 1.9785559 | T23: #VALUE! | U23: {=_FV(Table5[[#This Row],[Stock_Name]],"Ticker symbol",TRUE)} -> LT | V23: {=_FV(T23,"Price")} -> 4047.5
I24: {=_FV(Table5[[#This Row],[Stock_Name]],"Ticker symbol",TRUE)} -> MARUTI | J24: =_xlfn.XLOOKUP(I24,orderTable[Stock_Name],orderTable[Sector],"Undefined",0,1) -> Automobile | K24: =SUMIFS(orderTable[Quantity],orderTable[Stock_Name],'My Holdings'!I24,orderTable[Order_Type],"BUY") - SUMIFS(orderTable[Quantity],orderTable[Stock_Name],'My Holdings'!I24,orderTable[Order_Type],"SELL") -> 80 | L24: =ROUND(SUMIFS(orderTable[BP*Qty],orderTable[Stock_Name],'My Holdings'!I24,orderTable[Order_Type],"BUY") / SUMIFS(orderTable[Quantity],orderTable[Stock_Name],'My Holdings'!I24,orderTable[Order_Type],"BUY"),2) -> 1510.8 | M24: =L24*K24 -> 120864 | N24: =_xlfn.XLOOKUP(I24,Table5[Ticker symbol],Table5[Current_Price],0,0,1) -> 13364 | O24: =N24*K24 -> 1069120 | P24: =O24-M24 -> 948256 | Q24: =IF(M24<>0,P24/M24,0) -> 7.8456447 | T24: #VALUE! | U24: {=_FV(Table5[[#This Row],[Stock_Name]],"Ticker symbol",TRUE)} -> MARUTI | V24: {=_FV(T24,"Price")} -> 13364
I25: {=_FV(Table5[[#This Row],[Stock_Name]],"Ticker symbol",TRUE)} -> NESTLEIND | J25: =_xlfn.XLOOKUP(I25,orderTable[Stock_Name],orderTable[Sector],"Undefined",0,1) -> FMCG | K25: =SUMIFS(orderTable[Quantity],orderTable[Stock_Name],'My Holdings'!I25,orderTable[Order_Type],"BUY") - SUMIFS(orderTable[Quantity],orderTable[Stock_Name],'My Holdings'!I25,orderTable[Order_Type],"SELL") -> 55 | L25: =ROUND(SUMIFS(orderTable[BP*Qty],orderTable[Stock_Name],'My Holdings'!I25,orderTable[Order_Type],"BUY") / SUMIFS(orderTable[Quantity],orderTable[Stock_Name],'My Holdings'!I25,orderTable[Order_Type],"BUY"),2) -> 1428.77 | M25: =L25*K25 -> 78582.35 | N25: =_xlfn.XLOOKUP(I25,Table5[Ticker symbol],Table5[Current_Price],0,0,1) -> 1427.5 | O25: =N25*K25 -> 78512.5 | P25: =O25-M25 -> -69.85 | Q25: =IF(M25<>0,P25/M25,0) -> -0.00088887645 | T25: #VALUE! | U25: {=_FV(Table5[[#This Row],[Stock_Name]],"Ticker symbol",TRUE)} -> NESTLEIND | V25: {=_FV(T25,"Price")} -> 1427.5
I26: {=_FV(Table5[[#This Row],[Stock_Name]],"Ticker symbol",TRUE)} -> POWERGRID | J26: =_xlfn.XLOOKUP(I26,orderTable[Stock_Name],orderTable[Sector],"Undefined",0,1) -> Power | K26: =SUMIFS(orderTable[Quantity],orderTable[Stock_Name],'My Holdings'!I26,orderTable[Order_Type],"BUY") - SUMIFS(orderTable[Quantity],orderTable[Stock_Name],'My Holdings'!I26,orderTable[Order_Type],"SELL") -> 105 | L26: =ROUND(SUMIFS(orderTable[BP*Qty],orderTable[Stock_Name],'My Holdings'!I26,orderTable[Order_Type],"BUY") / SUMIFS(orderTable[Quantity],orderTable[Stock_Name],'My Holdings'!I26,orderTable[Order_Type],"BUY"),2) -> 2408.82 | M26: =L26*K26 -> 252926.1 | N26: =_xlfn.XLOOKUP(I26,Table5[Ticker symbol],Table5[Current_Price],0,0,1) -> 300.15 | O26: =N26*K26 -> 31515.75 | P26: =O26-M26 -> -221410.35 | Q26: =IF(M26<>0,P26/M26,0) -> -0.87539542 | T26: #VALUE! | U26: {=_FV(Table5[[#This Row],[Stock_Name]],"Ticker symbol",TRUE)} -> POWERGRID | V26: {=_FV(T26,"Price")} -> 300.15
I27: {=_FV(Table5[[#This Row],[Stock_Name]],"Ticker symbol",TRUE)} -> SBIN | J27: =_xlfn.XLOOKUP(I27,orderTable[Stock_Name],orderTable[Sector],"Undefined",0,1) -> Banking | K27: =SUMIFS(orderTable[Quantity],orderTable[Stock_Name],'My Holdings'!I27,orderTable[Order_Type],"BUY") - SUMIFS(orderTable[Quantity],orderTable[Stock_Name],'My Holdings'!I27,orderTable[Order_Type],"SELL") -> 100 | L27: =ROUND(SUMIFS(orderTable[BP*Qty],orderTable[Stock_Name],'My Holdings'!I27,orderTable[Order_Type],"BUY") / SUMIFS(orderTable[Quantity],orderTable[Stock_Name],'My Holdings'!I27,orderTable[Order_Type],"BUY"),2) -> 807.96 | M27: =L27*K27 -> 80796 | N27: =_xlfn.XLOOKUP(I27,Table5[Ticker symbol],Table5[Current_Price],0,0,1) -> 967.8 | O27: =N27*K27 -> 96780 | P27: =O27-M27 -> 15984 | Q27: =IF(M27<>0,P27/M27,0) -> 0.19783158 | T27: #VALUE! | U27: {=_FV(Table5[[#This Row],[Stock_Name]],"Ticker symbol",TRUE)} -> SBIN | V27: {=_FV(T27,"Price")} -> 967.8
... I30: {=_FV(Table5[[#This Row],[Stock_Name]],"Ticker symbol",TRUE)} -> WIPRO | J30: =_xlfn.XLOOKUP(I30,orderTable[Stock_Name],orderTable[Sector],"Undefined",0,1) -> IT | K30: =SUMIFS(orderTable[Quantity],orderTable[Stock_Name],'My Holdings'!I30,orderTable[Order_Type],"BUY") - SUMIFS(orderTable[Quantity],orderTable[Stock_Name],'My Holdings'!I30,orderTable[Order_Type],"SELL") -> 240 | L30: =ROUND(SUMIFS(orderTable[BP*Qty],orderTable[Stock_Name],'My Holdings'!I30,orderTable[Order_Type],"BUY") / SUMIFS(orderTable[Quantity],orderTable[Stock_Name],'My Holdings'!I30,orderTable[Order_Type],"BUY"),2) -> 1564.27 | M30: =L30*K30 -> 375424.8 | N30: =_xlfn.XLOOKUP(I30,Table5[Ticker symbol],Table5[Current_Price],0,0,1) -> 201.58 | O30: =N30*K30 -> 48379.2 | P30: =O30-M30 -> -327045.6 | Q30: =IF(M30<>0,P30/M30,0) -> -0.87113478 | T30: #VALUE! | U30: {=_FV(Table5[[#This Row],[Stock_Name]],"Ticker symbol",TRUE)} -> WIPRO | V30: {=_FV(T30,"Price")} -> 201.58
I32: Totals | M32: =SUM(M16:M30) -> 3533128.6 | O32: =SUM(O16:O30) -> 6272596.7 | P32: =SUM(P16:P30) -> 2739468.1 | Q32: =IF(M32<>0,P32/M32,0) -> 0.77536609

Sheet Portfolio Analysis
G1: 📈 STOCK MARKET PORTFOLIO TRACKER & RETURN ANALYZER
K8: Sector Wise Allocation | V8: Investment Vs P/L | AA8: Sector | AB8: (All) | AD8: Quantity in Hold
H9: Sector | I9: Investment | R9: Row Labels | S9: Investment | T9: P/L
H10: Automobile | I10: 120864 | R10: ASIANPAINT | S10: 70381.85 | T10: 23134.65 | AA10: Stock Name | AB10: Sum of Quantity
H11: Banking | I11: 364509.1 | R11: AXISBANK | S11: 112392.5 | T11: -47187.5 | AA11: ASIANPAINT | AB11: 35
H12: Cement | I12: 399879.15 | R12: BAJFINANCE | S12: 486320.8 | T12: -225598.8 | AA12: AXISBANK | AB12: 50
H13: Finance | I13: 486320.8 | R13: ICICIBANK | S13: 140626.2 | T13: 69369.3 | AA13: BAJFINANCE | AB13: 280
H14: FMCG | I14: 604572.35 | R14: INFY | S14: 282807.25 | T14: 36165.25 | AA14: ICICIBANK | AB14: 165
H15: Infrastructure | I15: 360103.2 | R15: ITC | S15: 525990 | T15: -416508.75 | AA15: INFY | AB15: 275
H16: IT | I16: 658232.05 | R16: KOTAKBANK | S16: 30694.4 | T16: -22920.4 | AA16: ITC | AB16: 375
H17: Paints | I17: 70381.85 | R17: LT | S17: 360103.2 | T17: 712484.3 | AA17: KOTAKBANK | AB17: 20
H18: Power | I18: 252926.1 | R18: MARUTI | S18: 120864 | T18: 948256 | AA18: LT | AB18: 265
H19: Retail | I19: 215340 | R19: NESTLEIND | S19: 78582.35 | T19: -69.85 | AA19: MARUTI | AB19: 80
H20: Grand Total | I20: 3533128.6 | R20: POWERGRID | S20: 252926.1 | T20: -221410.35 | AA20: NESTLEIND | AB20: 55
R21: SBIN | S21: 80796 | T21: 15984 | AA21: POWERGRID | AB21: 105
R22: TITAN | S22: 215340 | T22: 198450 | AA22: SBIN | AB22: 100
R23: ULTRACEMCO | S23: 399879.15 | T23: 1996365.9 | AA23: TITAN | AB23: 100
R24: WIPRO | S24: 375424.8 | T24: -327045.6 | AA24: ULTRACEMCO | AB24: 205
R25: Grand Total | S25: 3533128.6 | T25: 2739468.1 | AA25: WIPRO | AB25: 240
H26: Sector | I26: (All) | AA26: Grand Total | AB26: 2350
H28: Row Labels | I28: Investment | J28: Current Value | K28: Sum of Profit/Loss
H29: ASIANPAINT | I29: 70381.85 | J29: 93516.5 | K29: 23134.65 | M29: Total Investment Vs Total Market Value Vs Profit/Loss
H30: 35 | I30: 70381.85 | J30: 93516.5 | K30: 23134.65
H31: AXISBANK | I31: 112392.5 | J31: 65205 | K31: -47187.5
H32: 50 | I32: 112392.5 | J32: 65205 | K32: -47187.5
H33: BAJFINANCE | I33: 486320.8 | J33: 260722 | K33: -225598.8
H34: 280 | I34: 486320.8 | J34: 260722 | K34: -225598.8
H35: ICICIBANK | I35: 140626.2 | J35: 209995.5 | K35: 69369.3
H36: 165 | I36: 140626.2 | J36: 209995.5 | K36: 69369.3
H37: INFY | I37: 282807.25 | J37: 318972.5 | K37: 36165.25
H38: 275 | I38: 282807.25 | J38: 318972.5 | K38: 36165.25
H39: ITC | I39: 525990 | J39: 109481.25 | K39: -416508.75
H40: 375 | I40: 525990 | J40: 109481.25 | K40: -416508.75
H41: KOTAKBANK | I41: 30694.4 | J41: 7774 | K41: -22920.4
H42: 20 | I42: 30694.4 | J42: 7774 | K42: -22920.4
H43: LT | I43: 360103.2 | J43: 1072587.5 | K43: 712484.3
H44: 265 | I44: 360103.2 | J44: 1072587.5 | K44: 712484.3
H45: MARUTI | I45: 120864 | J45: 1069120 | K45: 948256
H46: 80 | I46: 120864 | J46: 1069120 | K46: 948256 | AD46: Count of Days (Date) | AE46: Column Labels
H47: NESTLEIND | I47: 78582.35 | J47: 78512.5 | K47: -69.85 | AD47: Row Labels | AE47: Jan | AF47: Feb | AG47: Mar | AH47: Apr | AI47: May | AJ47: Jun | AK47: Grand Total
H48: 55 | I48: 78582.35 | J48: 78512.5 | K48: -69.85 | AD48: Automobile | AE48: 2 | AF48: 1 | AG48: 1 | AH48: 2 | AI48: 2 | AK48: 8
H49: POWERGRID | I49: 252926.1 | J49: 31515.75 | K49: -221410.35 | AD49: Banking | AE49: 3 | AF49: 2 | AG49: 8 | AH49: 4 | AI49: 6 | AJ49: 5 | AK49: 28
H50: 105 | I50: 252926.1 | J50: 31515.75 | K50: -221410.35 | AD50: Cement | AE50: 1 | AF50: 1 | AG50: 3 | AI50: 5 | AJ50: 2 | AK50: 12
H51: SBIN | I51: 80796 | J51: 96780 | K51: 15984 | AD51: Finance | AE51: 2 | AF51: 2 | AG51: 4 | AH51: 3 | AI51: 5 | AJ51: 5 | AK51: 21
H52: 100 | I52: 80796 | J52: 96780 | K52: 15984 | AD52: FMCG | AE52: 1 | AF52: 3 | AG52: 2 | AH52: 3 | AI52: 3 | AJ52: 7 | AK52: 19
H53: TITAN | I53: 215340 | J53: 413790 | K53: 198450 | AD53: Infrastructure | AF53: 2 | AG53: 1 | AH53: 1 | AI53: 2 | AJ53: 1 | AK53: 7
H54: 100 | I54: 215340 | J54: 413790 | K54: 198450 | AD54: IT | AE54: 5 | AF54: 4 | AG54: 2 | AH54: 5 | AI54: 3 | AJ54: 6 | AK54: 25
H55: ULTRACEMCO | I55: 399879.15 | J55: 2396245 | K55: 1996365.9 | AD55: Paints | AF55: 1 | AG55: 1 | AH55: 1 | AK55: 3
H56: 205 | I56: 399879.15 | J56: 2396245 | K56: 1996365.9 | AD56: Power | AH56: 1 | AI56: 1 | AJ56: 5 | AK56: 7
H57: WIPRO | I57: 375424.8 | J57: 48379.2 | K57: -327045.6 | AD57: Retail | AE57: 1 | AF57: 2 | AH57: 1 | AI57: 1 | AJ57: 2 | AK57: 7
H58: 240 | I58: 375424.8 | J58: 48379.2 | K58: -327045.6 | AD58: Grand Total | AE58: 15 | AF58: 18 | AG58: 22 | AH58: 21 | AI58: 28 | AJ58: 33 | AK58: 137
H59: Grand Total | I59: 3533128.6 | J59: 6272596.7 | K59: 2739468.1
H65: Sum of Quantity | I65: Column Labels | R65: Monthly Buy+Sell | AA65: Sector VS Month VS Days
H66: Row Labels | I66: Jan | J66: Feb | K66: Mar | L66: Apr | M66: May | N66: Jun | O66: Grand Total
H67: ASIANPAINT | J67: 50 | K67: 25 | L67: 10 | O67: 85
H68: AXISBANK | I68: 100 | L68: 50 | M68: 45 | N68: 45 | O68: 240
H69: BAJFINANCE | I69: 125 | J69: 30 | K69: 240 | L69: 145 | M69: 285 | N69: 175 | O69: 1000
H70: ICICIBANK | I70: 50 | K70: 105 | L70: 15 | M70: 35 | N70: 10 | O70: 215
H71: INFY | I71: 60 | J71: 125 | L71: 55 | M71: 120 | N71: 195 | O71: 555
H72: ITC | J72: 200 | K72: 15 | L72: 35 | M72: 50 | N72: 275 | O72: 575
H73: KOTAKBANK | J73: 115 | K73: 200 | L73: 25 | M73: 150 | N73: 120 | O73: 610
H74: LT | J74: 110 | K74: 75 | L74: 5 | M74: 90 | N74: 15 | O74: 295
H75: MARUTI | I75: 90 | J75: 50 | K75: 10 | L75: 25 | M75: 175 | O75: 350
H76: NESTLEIND | I76: 100 | J76: 75 | K76: 20 | L76: 100 | M76: 100 | N76: 140 | O76: 535
H77: POWERGRID | L77: 75 | M77: 25 | N77: 185 | O77: 285
H78: SBIN | I78: 100 | O78: 100
H79: TITAN | I79: 100 | J79: 175 | L79: 25 | M79: 15 | N79: 35 | O79: 350
H80: ULTRACEMCO | I80: 50 | J80: 75 | K80: 125 | M80: 215 | N80: 30 | O80: 495
H81: WIPRO | I81: 20 | J81: 15 | K81: 85 | L81: 5 | M81: 20 | N81: 125 | O81: 270
H82: Grand Total | I82: 795 | J82: 1020 | K82: 900 | L82: 570 | M82: 1325 | N82: 1350 | O82: 5960
